Workbook
Name DATA: DATE!$D$2:$D$110
Name DettagliospesegenericheBA: 'Spese Generiche BANCOMAT '!$A:$G
Name DettagliospesegenericheCC: 'Dettaglio Spese Generiche CC'!$A:$G
Name TabellaColori: CATEGORIE!$D$6:$E$17
Name TABELLASPESE: 'Spese Generiche BANCOMAT '!#REF!
Name TABELLASPESE: 'Dettaglio Spese Generiche CC'!#REF!
Name TAGLIARIFORNIMENTO: 'SPESE MENSILI MACCHINA'!$C$37:$C$58

Sheet CATEGORIE
G2: MACRO AREA | H2: TIPOLOGIA | I2: CATEGORIA | J2: FOGLIO
G3: AUTO - SPESE FISSE | H3: SPESE FISSE AUTO | I3: COSTO MOBILITA' | J3: BILANCIO
G4: AUTO - SPESE VARIABILI | H4: SPESE PER LA MACCHINA | I4: COSTO MOBILITA' | J4: ANALISI SPESE GENERICHE CARTA
H5: SPESE PER LA MACCHINA | I5: COSTO MOBILITA' | J5: ANALISI SPESE GENERICHE CONTO
D6: CATEGORIA | E6: COLORE | G6: CARBURANTE | H6: RIFORNIMENTI | I6: COSTO MOBILITA' | J6: BILANCIO
D7: COSTO MOBILITA' | H7: COMMISSIONI RIFORNIMENTI | I7: COSTO MOBILITA' | J7: BILANCIO
D8: COSTO CASA | G8: TRASPORTI E PARCHEGGI | H8: TRASPORTI E PARCHEGGI | I8: COSTO MOBILITA' | J8: ANALISI SPESE GENERICHE CARTA
D9: COSTO SOPRAVVIVENZA | H9: TRASPORTI E PARCHEGGI | I9: COSTO MOBILITA' | J9: ANALISI SPESE GENERICHE CONTO
D10: COSTO ABBONAMENTI | G10: CASA - SPESE FISSE | H10: SPESE FISSE CASA | I10: COSTO CASA | J10: BILANCIO
D11: COSTO SVAGHI (CINEMA&BAR&RISTO) | G11: CASA - SPESE VARIABILI | H11: SPESE PER LA CASA | I11: COSTO CASA | J11: ANALISI SPESE GENERICHE CARTA
D12: COSTO VACANZE | H12: SPESE PER LA CASA | I12: COSTO CASA | J12: ANALISI SPESE GENERICHE CONTO
D13: COSTO SFIZI | H13: SPESE PER L'AFFITTO | I13: COSTO CASA | J13: BILANCIO
D14: MOVIMENTI CONTO | H14: SPESE PER IL GARAGE | I14: COSTO CASA | J14: BILANCIO
D15: TASSE | H15: SPESA GAS | I15: COSTO CASA | J15: BILANCIO
D16: GESTIONE CONTO | H16: SPESA LUCE | I16: COSTO CASA | J16: BILANCIO
D17: RATE GENERICHE | H17: INTERNET | I17: COSTO CASA | J17: BILANCIO
H18: BRICO | I18: COSTO CASA | J18: ANALISI SPESE GENERICHE CARTA
H19: BRICO | I19: COSTO CASA | J19: ANALISI SPESE GENERICHE CONTO
H20: TELEFONO | I20: COSTO SOPRAVVIVENZA
H21: RICARICHE TELEFONICHE | I21: COSTO SOPRAVVIVENZA
H22: SPESE PER LA MACCHINA | I22: COSTO SOPRAVVIVENZA
H23: MACCHINETTA AUTOMATICA | I23: COSTO SOPRAVVIVENZA
H24: COSMETICI | I24: COSTO SOPRAVVIVENZA
H25: MEDICINALI | I25: COSTO SOPRAVVIVENZA
H26: ALIMENTARI | I26: COSTO SOPRAVVIVENZA
H27: VISITE MEDICHE | I27: COSTO SOPRAVVIVENZA
H28: MENSA | I28: COSTO SOPRAVVIVENZA
H29: PROVIDER INTERNET | I29: COSTO SOPRAVVIVENZA
H30: ABBONAMENTI ANNUALI | I30: COSTO ABBONAMENTI
H31: ABBONAMENTI VIDEO MENSILI | I31: COSTO ABBONAMENTI
... H54: RATE MENSILI | I54: RATE GENERICHE

Sheet BILANCIO
B1: PIANO RISPARMI | U1: =MONTH(B2) -> 10
B2: 46296
B3: =CONCATENATE("Spesa Carta ",Valutazioni!E3," €") -> Spesa Carta 2230,93 €
B4: =CONCATENATE("Budget Rimanente ",Valutazioni!I3," €") -> Budget Rimanente 0 €
B5: =CONCATENATE(CONCATENATE("Margine mensile ",YEAR(B2))," ",ROUND(AVERAGEIF(CN71:CQ71,">0"),1)," €") -> Margine mensile 2026 491,8 €
B7: =YEAR(B2) -> 2026 | C7: =IF(YEAR($B$2)=C9,TRUE,FALSE) -> FALSE | D7: =IF(YEAR($B$2)=D9,TRUE,FALSE) -> FALSE | E7: =IF(YEAR($B$2)=E9,TRUE,FALSE) -> FALSE | F7: =IF(YEAR($B$2)=F9,TRUE,FALSE) -> FALSE | G7: =IF(YEAR($B$2)=G9,TRUE,FALSE) -> FALSE | H7: =IF(YEAR($B$2)=H9,TRUE,FALSE) -> FALSE | I7: =IF(YEAR($B$2)=I9,TRUE,FALSE) -> TRUE | K7: =IF(YEAR($B$2)=K9,TRUE,FALSE) -> FALSE | L7: =IF(YEAR($B$2)=L9,TRUE,FALSE) -> FALSE | M7: =IF(YEAR($B$2)=M9,TRUE,FALSE) -> FALSE | N7: =IF(YEAR($B$2)=N9,TRUE,FALSE) -> FALSE | O7: =IF(YEAR($B$2)=O9,TRUE,FALSE) -> FALSE | P7: =IF(YEAR($B$2)=P9,TRUE,FALSE) -> FALSE | Q7: =IF(YEAR($B$2)=Q9,TRUE,FALSE) -> TRUE | S7: =IF($B$2=S9,TRUE,FALSE) -> FALSE | T7: =IF($B$2=T9,TRUE,FALSE) -> FALSE | U7: =IF($B$2=U9,TRUE,FALSE) -> FALSE | V7: =IF($B$2=V9,TRUE,FALSE) -> FALSE | W7: =IF($B$2=W9,TRUE,FALSE) -> FALSE | X7: =IF($B$2=X9,TRUE,FALSE) -> FALSE | Y7: =IF($B$2=Y9,TRUE,FALSE) -> FALSE | Z7: =IF($B$2=Z9,TRUE,FALSE) -> FALSE | ... GT7: =IF($B$2=GT9,TRUE,FALSE) -> FALSE
C8: =IF(C9<=$B$2,1,0) -> 1 | D8: =IF(D9<=$B$2,1,0) -> 1 | E8: =IF(E9<=$B$2,1,0) -> 1 | F8: =IF(F9<=$B$2,1,0) -> 1 | G8: =IF(G9<=$B$2,1,0) -> 1 | H8: =IF(H9<=$B$2,1,0) -> 1 | I8: =IF(I9<=$B$2,1,0) -> 1 | K8: =IF(K9<=$B$2,1,0) -> 1 | L8: =IF(L9<=$B$2,1,0) -> 1 | M8: =IF(M9<=$B$2,1,0) -> 1 | N8: =IF(N9<=$B$2,1,0) -> 1 | O8: =IF(O9<=$B$2,1,0) -> 1 | P8: =IF(P9<=$B$2,1,0) -> 1 | Q8: =IF(Q9<=$B$2,1,0) -> 1 | S8: =IF(S9<=$B$2,1,0) -> 1 | T8: =IF(T9<=$B$2,1,0) -> 1 | U8: =IF(U9<=$B$2,1,0) -> 1 | V8: =IF(V9<=$B$2,1,0) -> 1 | W8: =IF(W9<=$B$2,1,0) -> 1 | X8: =IF(X9<=$B$2,1,0) -> 1 | Y8: =IF(Y9<=$B$2,1,0) -> 1 | Z8: =IF(Z9<=$B$2,1,0) -> 1 | ... GT8: =IF(GT9<=$B$2,1,0) -> 0
C9: 2020 | D9: 2021 | E9: 2022 | F9: 2023 | G9: 2024 | H9: 2025 | I9: 2026 | K9: 2020 | L9: 2021 | M9: 2022 | N9: 2023 | O9: 2024 | P9: 2025 | Q9: 2026 | S9: 43739 | T9: 43770 | U9: 43800 | V9: 43831 | W9: 43862 | X9: 43891 | Y9: 43922 | Z9: 43952 | AA9: 43983 | AB9: 44013 | AC9: 44044 | AD9: 44075 | AE9: 44105 | AF9: 44136 | AG9: 44166 | AH9: 44197 | AI9: 44228 | AJ9: 44256 | AK9: 44287 | AL9: 44317 | AM9: 44348 | AN9: 44378 | AO9: 44409 | AP9: 44440 | AQ9: 44470 | AR9: 44501 | AS9: 44531 | AT9: 44562 | AU9: 44593 | AV9: 44621 | AW9: 44652 | AX9: 44682 | AY9: 44713 | AZ9: 44743 | BA9: 44774 | BB9: 44805 | BC9: 44835 | BD9: 44866 | BE9: 44896 | BF9: 44927 | BG9: 44958 | BH9: 44986 | BI9: 45017 | BJ9: 45047 | BK9: 45078 | BL9: 45108 | BM9: 45139 | BN9: 45170 | BO9: 45200 | BP9: 45231 | BQ9: 45261 | BR9: 45292 | BS9: 45323 | BT9: 45352 | BU9: 45383 | BV9: 45413 | BW9: 45444 | BX9: 45474 | BY9: 45505 | BZ9: 45536 | CA9: 45566 | CB9: 45597 | CC9: 45627 | CD9: 45658 | CE9: 45689 | CF9: 45717 | CG9: 45748 | CH9: 45778 | CI9: 45809 | CJ9: 45839 | CK9: 45870 | CL9: 45901 | CM9: 45931 | CN9: 45962 | CO9: 45992 | CP9: 46023 | CQ9: 46054 | CR9: 46082 | CS9: 46113 | CT9: 46143 | CU9: 46174 | CV9: 46204 | CW9: 46235 | CX9: 46266 | CY9: 46296 | CZ9: 46327 | DA9: 46357 | DB9: 46388 | DC9: 46419 | DD9: 46447 | DE9: 46478 | DF9: 46508 | DG9: 46539 | DH9: 46569 | DI9: 46600 | DJ9: 46631 | DK9: 46661 | DL9: 46692 | DM9: 46722 | DN9: 46753 | DO9: 46784 | DP9: 46813 | DQ9: 46844 | DR9: 46874 | DS9: 46905 | DT9: 46935 | DU9: 46966 | DV9: 46997 | DW9: 47027 | DX9: 47058 | DY9: 47088 | DZ9: 47119 | EA9: 47150 | EB9: 47178 | EC9: 47209 | ED9: 47239 | EE9: 47270 | EF9: 47300 | EG9: 47331 | EH9: 47362 | EI9: 47392 | EJ9: 47423 | EK9: 47453 | EL9: 47484 | EM9: 47515 | EN9: 47543 | EO9: 47574 | EP9: 47604 | EQ9: 47635 | ER9: 47665 | ES9: 47696 | ET9: 47727 | EU9: 47757 | EV9: 47788 | EW9: 47818 | EX9: 47849 | EY9: 47880 | EZ9: 47908 | FA9: 47939 | FB9: 47969 | FC9: 48000 | FD9: 48030 | FE9: 48061 | FF9: 48092 | FG9: 48122 | FH9: 48153 | FI9: 48183 | FJ9: 48214 | FK9: 48245 | FL9: 48274 | FM9: 48305 | FN9: 48335 | FO9: 48366 | FP9: 48396 | FQ9: 48427 | FR9: 48458 | FS9: 48488 | FT9: 48519 | FU9: 48549 | FV9: 48580 | FW9: 48611 | FX9: 48639 | FY9: 48670 | FZ9: 48700 | GA9: 48731 | GB9: 48761 | GC9: 48792 | GD9: 48823 | GE9: 48853 | GF9: 48884 | GG9: 48914 | GH9: 48945 | GI9: 48976 | GJ9: 49004 | GK9: 49035 | GL9: 49065 | GM9: 49096 | GN9: 49126 | GO9: 49157 | GP9: 49188 | GQ9: 49218 | GR9: 49249 | GS9: 49279 | GT9: 49310
B10: RIMANENZA INIZIALE | C10: =U32 -> 11552.48 | D10: =C35 -> 2224.51 | E10: =D35 -> 4838.61 | F10: =E35 -> 3883.43 | G10: =F35 -> 3214.45 | H10: =G35 -> 8487.16 | I10: =H35 -> 11614.742 | K10: MEDIA ANNUA CONTO | S10: 7395.16 | T10: =S32 -> 7851.23 | U10: =T32 -> 8195.8 | V10: =U32 -> 11552.48 | W10: =V32 -> 11541.37 | X10: =W32 -> 11543.58 | Y10: =X32 -> 11517.65 | Z10: =Y32 -> 11874.52 | AA10: =Z32 -> 12417.52 | ... GT10: =GS32 -> 122399.15
B11: STIPENDIO MENSILE | C11: =SUM(V11:AG11) -> 26686 | D11: =SUM(AH11:AS11) -> 26628 | E11: =SUM(AT11:BE11) -> 27484 | F11: =SUM(BF11:BQ11) -> 27474 | G11: =SUM(BR11:CC11) -> 30103 | H11: =SUM(CD11:CO11) -> 30235 | I11: =SUM(CP11:DA11) -> 32872 | K11: =C11/12 -> 2223.8333 | L11: =D11/12 -> 2219 | M11: =E11/12 -> 2290.3333 | N11: =F11/12 -> 2289.5 | O11: =G11/12 -> 2508.5833 | P11: =H11/12 -> 2519.5833 | Q11: =I11/12 -> 2739.3333 | S11: 2158 | T11: 2222 | U11: =2271 -> 2271 | V11: 2741 | W11: 2166 | X11: 2175 | Y11: 2158 | Z11: 2157 | AA11: 2158 | AB11: 2156 | AC11: 2169 | AD11: 2098 | AE11: 2167 | AF11: 2168 | AG11: =2373 -> 2373 | AH11: 1827 | AI11: 2177 | AJ11: 2165 | AK11: 2170 | AL11: 2227 | AM11: 2168 | AN11: 2167 | AO11: =2167+539 -> 2706 | AP11: =2379 -> 2379 | AQ11: 2164 | AR11: 2166 | AS11: =2312 -> 2312 | AT11: =2308 -> 2308 | AU11: 2249 | AV11: 2238 | AW11: 2250 | AX11: 2243 | AY11: 2314 | AZ11: 2242 | BA11: 2244 | BB11: =2519 -> 2519 | BC11: 2238 | BD11: =2248 -> 2248 | BE11: =2391 -> 2391 | BF11: 2078 | BG11: =2294 -> 2294 | BH11: 2245 | BI11: 2251 | BJ11: 2250 | BK11: 2251 | BL11: 2326 | BM11: 2327 | BN11: 2325 | BO11: =BN11 -> 2325 | BP11: 2327 | BQ11: =2475 -> 2475 | BR11: 3111 | BS11: =2425 -> 2425 | BT11: 2373 | BU11: 2373 | BV11: =BU11 -> 2373 | BW11: =2385 -> 2385 | BX11: 2541 | BY11: =2394 -> 2394 | BZ11: 2389 | CA11: 2538 | CB11: 2429 | CC11: =2772 -> 2772 | CD11: 3117 | CE11: 2538 | CF11: =CB11 -> 2429 | CG11: 2506 | CH11: 2506 | CI11: 2411 | CJ11: 2430 | CK11: 2367 | CL11: 2430 | CM11: 2430 | CN11: 2461 | CO11: 2610 | CP11: 3012 | CQ11: 2497 | CR11: 2486 | CS11: =CR11 -> 2486 | CT11: 2486 | CU11: 2636 | CV11: =2638 -> 2638 | CW11: 3488 | CX11: 3229 | CY11: =CV11 -> 2638 | CZ11: =CY11 -> 2638 | DA11: =CZ11 -> 2638 | DB11: =CZ11 -> 2638 | DC11: =DB11 -> 2638 | DD11: =DC11 -> 2638 | DE11: =DD11 -> 2638 | DF11: =DE11 -> 2638 | DG11: =DF11 -> 2638 | DH11: =DG11 -> 2638 | DI11: =DH11 -> 2638 | DJ11: =DI11 -> 2638 | ... DM11: =DL11 -> 2638 | DN11: =DL11 -> 2638 | DO11: =DN11 -> 2638 | DP11: =DO11 -> 2638 | DQ11: =DP11 -> 2638 | DR11: =DQ11 -> 2638 | DS11: =DR11 -> 2638 | DT11: =DS11 -> 2638 | DU11: =DT11 -> 2638 | DV11: =DU11 -> 2638 | ... DY11: =DX11 -> 2638 | DZ11: =DX11 -> 2638 | EA11: =DZ11 -> 2638 | EB11: =EA11 -> 2638 | EC11: =EB11 -> 2638 | ED11: =EC11 -> 2638 | EE11: =ED11 -> 2638 | EF11: =EE11 -> 2638 | EG11: =EF11 -> 2638 | EH11: =EG11 -> 2638 | ... EK11: =EJ11 -> 2638 | EL11: =EJ11 -> 2638 | EM11: =EL11 -> 2638 | EN11: =EM11 -> 2638 | EO11: =EN11 -> 2638 | EP11: =EO11 -> 2638 | EQ11: =EP11 -> 2638 | ER11: =EQ11 -> 2638 | ES11: =ER11 -> 2638 | ET11: =ES11 -> 2638 | ... GT11: =GS11 -> 2638
B12: TREDICESIMA + PREMIO (MBO) | C12: =SUM(V12:AG12) -> 5791 | D12: =SUM(AH12:AS12) -> 3290 | E12: =SUM(AT12:BE12) -> 3871 | F12: =SUM(BF12:BQ12) -> 2332 | G12: =SUM(BR12:CC12) -> 6240 | H12: =SUM(CD12:CO12) -> 5937 | I12: =SUM(CP12:DA12) -> 50120.05 | K12: =C12/12 -> 482.58333 | L12: =D12/12 -> 274.16667 | M12: =E12/12 -> 322.58333 | N12: =F12/12 -> 194.33333 | O12: =G12/12 -> 520 | P12: =IFERROR(SUM(CD12:CO12)/12,0) -> 494.75 | Q12: =IFERROR(SUM(CP12:DA12)/12,0) -> 4176.6708 | U12: 3525 | AG12: =2500+3291 -> 5791 | AS12: 3290 | BE12: 3871 | BQ12: 2332 | BT12: 3613 | CC12: 2627 | CF12: 3313 | CO12: 2624 | CS12: 3428 | CT12: =8581.07 -> 8581.07 | CU12: 35680.98 | DA12: 2430 | DM12: 2430 | DY12: 2430 | EK12: 2430 | EW12: 2430 | FI12: 2430 | FU12: 2430 | GG12: 2430 | GS12: 2430
B13: TOTALE STIPENDIO | C13: =C11+C12 -> 32477 | D13: =D11+D12 -> 29918 | E13: =E11+E12 -> 31355 | F13: =F11+F12 -> 29806 | G13: =G11+G12 -> 36343 | H13: =H11+H12 -> 36172 | I13: =I11+I12 -> 82992.05 | K13: =C13/12 -> 2706.4167 | L13: =D13/12 -> 2493.1667 | M13: =E13/12 -> 2612.9167 | N13: =F13/12 -> 2483.8333 | O13: =G13/12 -> 3028.5833 | P13: =H13/12 -> 3014.3333 | Q13: =Q11+Q12 -> 6916.0042 | CB13: =CB11+CB12 -> 2429 | CC13: =CC11+CC12 -> 5399 | CD13: =CD11+CD12 -> 3117 | CE13: =CE11+CE12 -> 2538 | CF13: =CF11+CF12 -> 5742 | CG13: =CG11+CG12 -> 2506 | CH13: =CH11+CH12 -> 2506 | CI13: =CI11+CI12 -> 2411 | ... GT13: =GT11+GT12 -> 2638
B14: SITUAZIONE CONTO IN BANCA | D14: =(D11-C11)/C11 -> -0.0021734243 | E14: =(E11-D11)/D11 -> 0.032146613 | F14: =(F11-E11)/E11 -> -0.00036384806 | G14: =(G11-F11)/F11 -> 0.095690471 | H14: =(H11-G11)/G11 -> 0.004384945 | I14: =(I11-H11)/H11 -> 0.087216802 | S14: =S10+S11 -> 9553.16 | T14: =T10+T11 -> 10073.23 | U14: =U10+U11 -> 10466.8 | V14: =V10+V11 -> 14293.48 | W14: =W10+W11 -> 13707.37 | X14: =X10+X11 -> 13718.58 | Y14: =Y10+Y11 -> 13675.65 | Z14: =Z10+Z11 -> 14031.52 | ... GT14: =GT10+GT11 -> 125037.15
B15: - SPESA AFFITTO | E15: =SUM(AT15:BE15) -> 0 | F15: =SUM(AJ15:AU15) -> 0 | G15: =SUM(AK15:AV15) -> 0 | H15: =SUM(AL15:AW15) -> 0 | I15: =SUM(AM15:AX15) -> 0 | S15: 420.5 | T15: 420.5 | U15: 420.5 | V15: 420.5 | W15: 420.5 | X15: 420.5 | Y15: 420.5 | Z15: 420.5 | AA15: 420.5 | AB15: 420.5 | AC15: 420.5 | AD15: 420.5 | AE15: 420.5 | AF15: 420.5 | AG15: 420.5 | AH15: 420.5
B16: - SPESE FISSE CASA | C16: =SUM(V16:AG16)+SUM(V17:AG17)+SUM(V15:AG15) -> 17059.5 | D16: =SUM(AH16:AS16)+SUM(AH17:AS17)+SUM(AH15:AS15) -> 8286 | E16: =SUM(AT16:BE16) -> 29295 | F16: =SUM(BF16:BQ16) -> 10606 | G16: =SUM(BR16:CC16) -> 10231 | H16: =SUM(CD16:CO16) -> 8760 | I16: =SUM(CP16:DA16) -> 9966 | K16: =C16/12 -> 1421.625 | L16: =D16/12 -> 690.5 | M16: =E16/12 -> 2441.25 | N16: =F16/12 -> 883.83333 | O16: =G16/12 -> 852.58333 | P16: =H16/12 -> 730 | Q16: =IFERROR(AVERAGEIF(CP16:DA16,">0"),0) -> 830.5 | AF16: 11003 | AG16: =350.5 -> 350.5 | AI16: 500.5 | AJ16: 350.5 | AK16: 500.5 | AL16: 500.5 | AM16: 600.5 | AN16: 550.5 | AO16: 900.5 | AP16: 950.5 | AQ16: 1000.5 | AR16: 950.5 | AS16: 1000.5 | AT16: =50.5+845.5 -> 896 | AU16: 870.5 | AV16: 600.5 | AW16: 700.5 | AX16: 820.5 | AY16: 700.5 | AZ16: =820.5+50.5+200.5 -> 1071.5 | BA16: 870.5 | BB16: =BA16+19002.5 -> 19873 | BC16: =870.5 -> 870.5 | BD16: =BC16 -> 870.5 | BE16: =1150.5 -> 1150.5 | BF16: 820.5 | BG16: 870.5 | BH16: =BG16 -> 870.5 | BI16: 850.5 | BJ16: =BH16 -> 870.5 | BK16: =BJ16 -> 870.5 | BL16: =BK16 -> 870.5 | BM16: =BL16 -> 870.5 | BN16: =BM16 -> 870.5 | BO16: =BN16 -> 870.5 | BP16: =BO16 -> 870.5 | BQ16: 1100.5 | BR16: 870 | BS16: =819.5+0.5 -> 820 | BT16: =849.5+0.5 -> 850 | BU16: =785+0.5 -> 785.5 | BV16: =859.5+0.5 -> 860 | BW16: =BV16 -> 860 | BX16: =BW16 -> 860 | BY16: =BX16 -> 860 | BZ16: =BY16 -> 860 | CA16: =BZ16 -> 860 | CB16: =859.5+0.5 -> 860 | CC16: =825+59.5+0.5+0.5 -> 885.5 | CD16: =(749.5+0.5)+(99.5+0.5) -> 850 | CE16: =799.5+0.5 -> 800 | CF16: =739.5+0.5 -> 740 | CG16: =CF16-60 -> 680 | CH16: =CF16 -> 740 | CI16: =679.5+0.5 -> 680 | CJ16: =639.5+0.5 -> 640 | CK16: =740 -> 740 | CL16: =640 -> 640 | CM16: =770 -> 770 | CN16: 700 | CO16: 780 | CP16: 780 | CQ16: 500 | CR16: 850 | CS16: =700 -> 700 | CT16: =699.5+0.5 -> 700 | CU16: 700 | CV16: 750 | CW16: =740 -> 740 | CX16: =685.5+1340.5 -> 2026 | CY16: 740 | CZ16: =CY16 -> 740 | DA16: =CZ16 -> 740 | DB16: =DA16 -> 740 | DC16: =DB16 -> 740 | DD16: =DC16 -> 740 | DE16: =DD16 -> 740 | DF16: =DE16 -> 740 | DG16: =DF16 -> 740 | ... GT16: =GS16 -> 740
B17: - SPESA GARAGE | E17: =SUM(AT17:BE17) -> 0 | F17: =SUM(BF17:BQ17) -> 0 | G17: =SUM(BR17:CC17) -> 0 | H17: =SUM(CD17:CO17) -> 0 | I17: =SUM(CE17:CP17) -> 0 | Q17: =IFERROR(AVERAGEIF(CE17:CP17,">0"),0) -> 0 | W17: 180 | Z17: 180 | AC17: 180 | AF17: 60 | AG17: 60 | AH17: 60
B18: - SPESE FISSE AUTO | C18: =SUM(V18:AG18) -> 3564 | D18: =SUM(AH18:AS18) -> 3568.5 | E18: =SUM(AT18:BE18) -> 16885.23 | F18: =SUM(BF18:BQ18) -> 3259 | G18: =SUM(BR18:CC18) -> 3259 | H18: =SUM(CD18:CO18) -> 3259 | I18: =SUM(CP18:DA18) -> 3259 | K18: =C18/12 -> 297 | L18: =D18/12 -> 297.375 | M18: =E18/12 -> 1407.1025 | N18: =F18/12 -> 271.58333 | O18: =G18/12 -> 271.58333 | P18: =H18/12 -> 271.58333 | Q18: =IFERROR(AVERAGEIF(CP18:DA18,">0"),0) -> 271.58333 | S18: 297 | T18: 297 | U18: 297 | V18: 297 | W18: 297 | X18: 297 | Y18: 297 | Z18: 297 | AA18: 297 | AB18: 297 | AC18: 297 | AD18: 297 | AE18: 297 | AF18: 297 | AG18: 297 | AH18: 297 | AI18: 297 | AJ18: 297 | AK18: 297.5 | AL18: 297.5 | AM18: 297.5 | AN18: 297.5 | AO18: 297.5 | AP18: 297.5 | AQ18: 297.5 | AR18: 297.5 | AS18: 297.5 | AT18: 297.5 | AU18: =199+2.75+0.5+13838.98 -> 14041.23 | AV18: =185.75+2.5 -> 188.25 | AW18: =AV18 -> 188.25 | AX18: =AW18+83 -> 271.25 | AY18: =AX18 -> 271.25 | AZ18: =AY18 -> 271.25 | BA18: =80.5+2.5+185.75+2.5 -> 271.25 | BB18: =BA18 -> 271.25 | BC18: =BB18 -> 271.25 | BD18: =BC18 -> 271.25 | BE18: =BD18 -> 271.25 | BF18: =BE18 -> 271.25 | BG18: =BF18 -> 271.25 | BH18: =BG18 -> 271.25 | BI18: ='SPESE MENSILI MACCHINA'!P50 -> 275.25 | BJ18: =BH18 -> 271.25 | BK18: =BJ18 -> 271.25 | BL18: =BK18 -> 271.25 | BM18: =BL18 -> 271.25 | BN18: =BM18 -> 271.25 | BO18: ='SPESE MENSILI MACCHINA'!P56 -> 271.25 | BP18: =BO18 -> 271.25 | BQ18: =BP18 -> 271.25 | BR18: =BQ18 -> 271.25 | BS18: =BR18 -> 271.25 | BT18: =BS18 -> 271.25 | BU18: =275.25 -> 275.25 | BV18: 271.25 | BW18: =BV18 -> 271.25 | BX18: =BW18 -> 271.25 | BY18: =BX18 -> 271.25 | BZ18: =BY18 -> 271.25 | CA18: =BZ18 -> 271.25 | CB18: =CA18 -> 271.25 | CC18: =CB18 -> 271.25 | CD18: =CC18 -> 271.25 | ... CF18: =CE18 -> 271.25 | CG18: 275.25 | CH18: =CF18 -> 271.25 | CI18: =CH18 -> 271.25 | CJ18: =CI18 -> 271.25 | CK18: =CJ18 -> 271.25 | CL18: =CK18 -> 271.25 | CM18: =CL18 -> 271.25 | CN18: =CM18 -> 271.25 | CO18: =CN18 -> 271.25 | CP18: =CO18 -> 271.25 | ... CR18: =CQ18 -> 271.25 | CS18: =275.25 -> 275.25 | CT18: =CR18 -> 271.25 | CU18: =CT18 -> 271.25 | CV18: =CU18 -> 271.25 | CW18: =CV18 -> 271.25 | CX18: =CW18 -> 271.25 | CY18: =CX18 -> 271.25 | CZ18: =CY18 -> 271.25 | DA18: =CZ18 -> 271.25 | DB18: =DA18 -> 271.25 | ... DT18: =DS18 -> 271.25 | DU18: =DT18-('Gestione finanziamenti'!K10) -> 188.25 | DV18: =DU18 -> 188.25 | DW18: =DV18 -> 188.25 | DX18: =DW18 -> 188.25 | DY18: =DX18 -> 188.25 | DZ18: =DY18 -> 188.25 | EA18: =DZ18 -> 188.25 | EB18: =EA18 -> 188.25 | EC18: =EB18 -> 188.25 | ... FT18: =FS18 -> 188.25
B19: - SPESA ASSICURAZIONE | C19: =SUM(V19:AG19) -> 539.89 | D19: =SUM(AH19:AS19) -> 531.89 | E19: =SUM(AT19:BE19) -> 589.84 | F19: =SUM(BF19:BQ19) -> 380 | G19: =SUM(BR19:CC19) -> 0 | H19: =SUM(CD19:CO19) -> 0 | I19: =SUM(CP19:DA19) -> 0 | K19: =C19/12 -> 44.990833 | L19: =D19/12 -> 44.324167 | M19: =E19/12 -> 49.153333 | N19: =F19/12 -> 31.666667 | O19: =G19/12 -> 0 | P19: =H19/12 -> 0 | Q19: =IFERROR(AVERAGEIF(CE19:CP19,">0"),0) -> 0 | S19: 53.93 | T19: 53.93 | U19: 53.93 | V19: 53.93 | W19: 53.93 | X19: 53.93 | Y19: 53.93 | Z19: 54.02 | AC19: 54.03 | AD19: 54.03 | AE19: 54.03 | AF19: 54.03 | AG19: 54.03 | AH19: 54.03 | AJ19: =54.03+54.03 -> 108.06 | AK19: 54.53 | AL19: 54.62 | AO19: 52.13 | AP19: 52.13 | AQ19: 52.13 | AR19: 52.13 | AS19: 52.13 | AT19: =53.23+2.5 -> 55.73 | AU19: 52.13 | AV19: 52.13 | AW19: 52.13 | AX19: 52.22 | AZ19: 325.5 | BL19: 380
B20: -COMMISSIONI CANONE MENSILE | C20: =SUM(V20:AG20) -> 66 | D20: =SUM(AH20:AS20) -> 112.35 | E20: =SUM(AT20:BE20) -> 82.2 | F20: =SUM(BF20:BQ20) -> 82.2 | G20: =SUM(BR20:CC20) -> 82.2 | H20: =SUM(CD20:CO20) -> 82.2 | I20: =SUM(CP20:DA20) -> 82.2 | K20: =C20/12 -> 5.5 | L20: =D20/12 -> 9.3625 | M20: =E20/12 -> 6.85 | N20: =F20/12 -> 6.85 | O20: =G20/12 -> 6.85 | P20: =H20/12 -> 6.85 | Q20: =IFERROR(AVERAGEIF(CP20:DA20,">0"),0) -> 6.85 | S20: 5.5 | T20: 5.5 | U20: 5.5 | V20: 5.5 | W20: 5.5 | X20: 5.5 | Y20: 5.5 | Z20: 5.5 | AA20: 5.5 | AB20: 5.5 | AC20: 5.5 | AD20: 5.5 | AE20: 5.5 | AF20: 5.5 | AG20: 5.5 | AH20: =5.5+34.2 -> 39.7 | AI20: 5.5 | AJ20: 5.5 | AK20: 6.85 | AL20: 6.85 | AM20: 6.85 | AN20: 6.85 | AO20: 6.85 | AP20: 6.85 | AQ20: 6.85 | AR20: 6.85 | AS20: 6.85 | AT20: 6.85 | AU20: 6.85 | AV20: 6.85 | AW20: 6.85 | AX20: 6.85 | AY20: 6.85 | AZ20: 6.85 | BA20: 6.85 | BB20: 6.85 | BC20: 6.85 | BD20: 6.85 | BE20: 6.85 | BF20: 6.85 | BG20: 6.85 | BH20: 6.85 | BI20: 6.85 | BJ20: 6.85 | BK20: 6.85 | BL20: 6.85 | BM20: 6.85 | BN20: 6.85 | BO20: 6.85 | BP20: 6.85 | BQ20: 6.85 | BR20: 6.85 | BS20: 6.85 | BT20: 6.85 | BU20: 6.85 | BV20: 6.85 | BW20: 6.85 | BX20: 6.85 | BY20: 6.85 | BZ20: 6.85 | CA20: 6.85 | CB20: 6.85 | CC20: 6.85 | CD20: 6.85 | CE20: 6.85 | CF20: 6.85 | CG20: 6.85 | CH20: 6.85 | CI20: 6.85 | CJ20: 6.85 | CK20: 6.85 | CL20: 6.85 | CM20: 6.85 | CN20: 6.85 | CO20: 6.85 | CP20: 6.85 | CQ20: 6.85 | CR20: 6.85 | CS20: 6.85 | CT20: 6.85 | CU20: 6.85 | CV20: 6.85 | CW20: 6.85 | CX20: 6.85 | CY20: 6.85 | CZ20: 6.85 | DA20: 6.85 | DB20: 6.85 | DC20: 6.85 | DD20: 6.85 | DE20: 6.85 | DF20: 6.85 | DG20: 6.85 | DH20: 6.85 | DI20: 6.85 | DJ20: 6.85 | DK20: 6.85 | DL20: 6.85 | DM20: 6.85 | DN20: 6.85 | DO20: 6.85 | DP20: 6.85 | DQ20: 6.85 | DR20: 6.85 | DS20: 6.85 | DT20: 6.85 | DU20: 6.85 | DV20: 6.85 | DW20: 6.85 | DX20: 6.85 | DY20: 6.85 | DZ20: 6.85 | EA20: 6.85 | EB20: 6.85 | EC20: 6.85 | ED20: 6.85 | EE20: 6.85 | EF20: 6.85 | EG20: 6.85 | EH20: 6.85 | EI20: 6.85 | EJ20: 6.85 | EK20: 6.85 | EL20: 6.85 | EM20: 6.85 | EN20: 6.85 | EO20: 6.85 | EP20: 6.85 | EQ20: 6.85 | ER20: 6.85 | ES20: 6.85 | ET20: 6.85 | EU20: 6.85 | EV20: 6.85 | EW20: 6.85 | EX20: 6.85 | EY20: 6.85 | EZ20: 6.85 | FA20: 6.85 | FB20: 6.85 | FC20: 6.85 | FD20: 6.85 | FE20: 6.85 | FF20: 6.85 | FG20: 6.85 | FH20: 6.85 | FI20: 6.85 | FJ20: 6.85 | FK20: 6.85 | FL20: 6.85 | FM20: 6.85 | FN20: 6.85 | FO20: 6.85 | FP20: 6.85 | FQ20: 6.85 | FR20: 6.85 | FS20: 6.85 | FT20: 6.85 | FU20: 6.85 | FV20: 6.85 | FW20: 6.85 | FX20: 6.85 | FY20: 6.85 | FZ20: 6.85 | GA20: 6.85 | GB20: 6.85 | GC20: 6.85 | GD20: 6.85 | GE20: 6.85 | GF20: 6.85 | GG20: 6.85 | GH20: 6.85 | GI20: 6.85 | GJ20: 6.85 | GK20: 6.85 | GL20: 6.85 | GM20: 6.85 | GN20: 6.85 | GO20: 6.85 | GP20: 6.85 | GQ20: 6.85 | GR20: 6.85 | GS20: 6.85 | GT20: 6.85
B21: -SPESE TELEPASS | C21: =SUM(V21:AG21) -> 253.62 | D21: =SUM(AH21:AS21) -> 128.02 | E21: =SUM(AT21:BE21) -> 294.97 | F21: =SUM(BF21:BQ21) -> 262.76 | G21: =SUM(BR21:CC21) -> 157.86 | H21: =SUM(CD21:CO21) -> 52.25 | I21: =SUM(CP21:DA21) -> 0 | K21: =C21/12 -> 21.135 | L21: =D21/12 -> 10.668333 | M21: =E21/12 -> 24.580833 | N21: =F21/12 -> 21.896667 | O21: =G21/12 -> 13.155 | P21: =H21/12 -> 4.3541667 | Q21: =IFERROR(AVERAGEIF(CE21:CP21,">0"),0) -> 52.25 | U21: 55.13 | X21: 93.43 | AA21: 12.53 | AD21: 75.93 | AG21: 71.73 | AJ21: 35.83 | AM21: 34.83 | AP21: 22.53 | AS21: =33.28+1.55 -> 34.83 | AU21: =31.08+1.55 -> 32.63 | AX21: =95.18+1.55 -> 96.73 | BA21: =66.82+1.55 -> 68.37 | BD21: =95.69+1.55 -> 97.24 | BH21: =47.09+1.55 -> 48.64 | BK21: =49.59+1.55 -> 51.14 | BM21: =111.49+1.55 -> 113.04 | BP21: =48.39+1.55 -> 49.94 | BS21: =50.59+1.55 -> 52.14 | BW21: =85.19+1.55 -> 86.74 | CC21: =17.43+1.55 -> 18.98 | CO21: =50.7+1.55 -> 52.25
B22: -SPESA GAS | C22: =SUM(V22:AG22) -> 0 | D22: =SUM(AH22:AS22) -> 521.58 | E22: =SUM(AT22:BE22) -> 610.8 | F22: =SUM(BF22:BQ22) -> 333.84 | G22: =SUM(BR22:CC22) -> 718.14 | H22: =SUM(CD22:CO22) -> 743.07 | I22: =SUM(CP22:DA22) -> 840.12503 | K22: =C22/12 -> 0 | L22: =D22/12 -> 43.465 | M22: =E22/12 -> 50.9 | N22: =F22/12 -> 27.82 | O22: =G22/12 -> 59.845 | P22: =H22/12 -> 61.9225 | Q22: =I22/12 -> 70.010419 | AI22: 111.86 | AK22: 100.96 | AM22: 66.38 | AO22: 41.39 | AQ22: 37.5 | AS22: 163.49 | AU22: =372.21+0.5 -> 372.71 | AW22: =44.18+18+0.5+0.5 -> 63.18 | AY22: =40.16+0.5 -> 40.66 | BA22: =35.03+0.5 -> 35.53 | BC22: =17.33+0.5 -> 17.83 | BE22: =80.39+0.5 -> 80.89 | BG22: ='ANALISI CONSUMI GAS ENERGIA'!AL17+0.5 -> 48.97 | BH22: ='ANALISI CONSUMI GAS ENERGIA'!AN17+0.5 -> 112.98 | BK22: ='ANALISI CONSUMI GAS ENERGIA'!AP17+0.5 -> 58.88 | BM22: ='ANALISI CONSUMI GAS ENERGIA'!AR17+0.5 -> 39.85 | BO22: ='ANALISI CONSUMI GAS ENERGIA'!AT17+0.5 -> 35 | BQ22: ='ANALISI CONSUMI GAS ENERGIA'!AV17+0.5 -> 38.16 | BS22: ='ANALISI CONSUMI GAS ENERGIA'!AX17+0.5 -> 197.9 | BU22: ='ANALISI CONSUMI GAS ENERGIA'!AZ17+0.5 -> 268.9 | BW22: ='ANALISI CONSUMI GAS ENERGIA'!BB17+0.5 -> 108.26 | BY22: ='ANALISI CONSUMI GAS ENERGIA'!BD17+0.5 -> 49.26 | CA22: ='ANALISI CONSUMI GAS ENERGIA'!BF17+0.5 -> 45.79 | CC22: ='ANALISI CONSUMI GAS ENERGIA'!BH17+0.5 -> 48.03 | CE22: ='ANALISI CONSUMI GAS ENERGIA'!BJ17+0.5 -> 270.53 | CG22: ='ANALISI CONSUMI GAS ENERGIA'!BL17+0.5 -> 228.34 | CI22: ='ANALISI CONSUMI GAS ENERGIA'!BN17+0.5 -> 96.49 | CK22: ='ANALISI CONSUMI GAS ENERGIA'!BP17+0.5 -> 49.78 | CM22: ='ANALISI CONSUMI GAS ENERGIA'!BR17+0.5 -> 47.81 | CO22: ='ANALISI CONSUMI GAS ENERGIA'!BT17+0.5 -> 50.12 | CQ22: ='ANALISI CONSUMI GAS ENERGIA'!BV17+0.5 -> 272.08 | CS22: ='ANALISI CONSUMI GAS ENERGIA'!BX17+0.5 -> 319.82 | CU22: ='ANALISI CONSUMI GAS ENERGIA'!BZ17+0.5 -> 120.97 | CW22: 30.25 | CX22: 21.23 | CY22: 20.29 | DA22: ='ANALISI CONSUMI GAS ENERGIA'!CK17 -> 55.485032 | DC22: 270.53 | DE22: 228.34 | DG22: 96.49 | DI22: 49.78 | DK22: 46.517834 | DM22: 47.187905 | DO22: 270.53 | DQ22: 228.34 | DS22: 96.49 | DU22: 49.78 | DW22: 46.517834 | DY22: 47.187905 | EA22: 270.53 | EC22: 228.34 | EE22: 96.49 | EG22: 49.78 | EI22: 46.517834 | EK22: 47.187905 | EM22: 270.53 | EO22: 228.34 | EQ22: 96.49 | ES22: 49.78 | EU22: 46.517834 | EW22: 47.187905 | EY22: 270.53 | FA22: 228.34 | FC22: 96.49 | FE22: 49.78 | FG22: 46.517834 | FI22: 47.187905 | FK22: 270.53 | FM22: 228.34 | FO22: 96.49 | FQ22: 49.78 | FS22: 46.517834 | FU22: 47.187905 | FW22: 270.53 | FY22: 228.34 | GA22: 96.49 | GC22: 49.78 | GE22: 46.517834 | GG22: 47.187905 | GI22: 270.53 | GK22: 228.34 | GM22: 96.49 | GO22: 49.78 | GQ22: 46.517834 | GS22: 47.187905
B23: -SPESA LUCE | C23: =SUM(V23:AG23) -> 0 | D23: =SUM(AH23:AS23) -> 828.89 | E23: =SUM(AT23:BE23) -> 556.23 | F23: =SUM(BF23:BQ23) -> 573.19 | G23: =SUM(BR23:CC23) -> 754.73 | H23: =SUM(CD23:CO23) -> 807.44 | I23: =SUM(CP23:DA23) -> 885.69108 | K23: =C23/12 -> 0 | L23: =D23/12 -> 69.074167 | M23: =E23/12 -> 46.3525 | N23: =F23/12 -> 47.765833 | O23: =G23/12 -> 62.894167 | P23: =H23/12 -> 67.286667 | Q23: =I23/12 -> 73.80759 | AI23: 272.57 | AK23: 133.32 | AM23: 116.72 | AO23: 111.88 | AQ23: 110.75 | AS23: 83.65 | AU23: ='ANALISI CONSUMI GAS ENERGIA'!Z60 -> 101.33 | AW23: =51.4+0.5 -> 51.9 | AY23: =78.61+0.5+18+0.5 -> 97.61 | BA23: =81.65+0.5+18+0.5 -> 100.65 | BB23: =96.31+0.5+9+0.5 -> 106.31 | BE23: =79.43+18+0.5+0.5 -> 98.43 | BG23: ='ANALISI CONSUMI GAS ENERGIA'!AL60+0.5 -> 80.25 | BI23: =18+0.5+69.65+0.5 -> 88.65 | BJ23: =18+0.5+67.91+0.5 -> 86.91 | BM23: ='ANALISI CONSUMI GAS ENERGIA'!AR60+0.5 -> 89.14 | BN23: ='ANALISI CONSUMI GAS ENERGIA'!AT60+0.5 -> 125.24 | BP23: ='ANALISI CONSUMI GAS ENERGIA'!AV60+0.5 -> 103 | BS23: ='ANALISI CONSUMI GAS ENERGIA'!AX60+0.5 -> 106.64 | BT23: ='ANALISI CONSUMI GAS ENERGIA'!AZ60+0.5 -> 129.6 | BV23: ='ANALISI CONSUMI GAS ENERGIA'!BB60+0.5 -> 127.71 | BY23: ='ANALISI CONSUMI GAS ENERGIA'!BD60+0.5 -> 138.12 | CA23: ='ANALISI CONSUMI GAS ENERGIA'!BF60+0.5 -> 147.4 | CC23: ='ANALISI CONSUMI GAS ENERGIA'!BH60+0.5 -> 105.26 | CE23: ='ANALISI CONSUMI GAS ENERGIA'!BJ60+0.5 -> 108.18 | CG23: ='ANALISI CONSUMI GAS ENERGIA'!BL60+0.5 -> 127.39 | CI23: ='ANALISI CONSUMI GAS ENERGIA'!BN60+0.5 -> 125.2 | CK23: ='ANALISI CONSUMI GAS ENERGIA'!BP60+0.5 -> 146.5 | CM23: ='ANALISI CONSUMI GAS ENERGIA'!BR60+0.5 -> 169.76 | CO23: ='ANALISI CONSUMI GAS ENERGIA'!BT60+0.5 -> 130.41 | CQ23: ='ANALISI CONSUMI GAS ENERGIA'!BV60+0.5 -> 131.96 | CS23: ='ANALISI CONSUMI GAS ENERGIA'!BX60+0.5 -> 138.62 | CU23: ='ANALISI CONSUMI GAS ENERGIA'!BZ60+0.5 -> 134.74 | CV23: 69.45 | CW23: 90.27 | CX23: 92.14 | CY23: 97.72 | DA23: ='ANALISI CONSUMI GAS ENERGIA'!CK60 -> 130.79108 | DC23: 108.18 | DE23: 127.39 | DG23: 125.2 | DI23: 146.5 | DK23: 153.4832 | DM23: 119.65911 | DO23: 108.18 | DQ23: 127.39 | DS23: 125.2 | DU23: 146.5 | DW23: 153.4832 | DY23: 119.65911 | EA23: 108.18 | EC23: 127.39 | EE23: 125.2 | EG23: 146.5 | EI23: 153.4832 | EK23: 119.65911 | EM23: 108.18 | EO23: 127.39 | EQ23: 125.2 | ES23: 146.5 | EU23: 153.4832 | EW23: 119.65911 | EY23: 108.18 | FA23: 127.39 | FC23: 125.2 | FE23: 146.5 | FG23: 153.4832 | FI23: 119.65911 | FK23: 108.18 | FM23: 127.39 | FO23: 125.2 | FQ23: 146.5 | FS23: 153.4832 | FU23: 119.65911 | FW23: 108.18 | FY23: 127.39 | GA23: 125.2 | GC23: 146.5 | GE23: 153.4832 | GG23: 119.65911 | GI23: 108.18 | GK23: 127.39 | GM23: 125.2 | GO23: 146.5 | GQ23: 153.4832 | GS23: 119.65911
B24: - PRELIEVO CONTANTI | C24: =SUM(V24:AG24) -> 0 | D24: =SUM(AH24:AS24) -> 3652 | E24: =SUM(AT24:BE24) -> 1980 | F24: =SUM(BF24:BQ24) -> 220 | G24: =SUM(BR24:CC24) -> 442 | H24: =SUM(CD24:CO24) -> 1030 | I24: =SUM(CP24:DA24) -> 1466 | K24: =C24/12 -> 0 | L24: =D24/12 -> 304.33333 | M24: =E24/12 -> 165 | N24: =F24/12 -> 18.333333 | O24: =G24/12 -> 36.833333 | P24: =H24/12 -> 85.833333 | Q24: =IFERROR(AVERAGEIF(CP24:DA24,">0"),0) -> 209.42857 | AJ24: =500+550+500+550 -> 2100 | AK24: 70 | AM24: =100+70 -> 170 | AN24: =50+50+150+100 -> 350 | AO24: =150+100+100 -> 350 | AP24: =250 -> 250 | AQ24: =100+2 -> 102 | AS24: =50+60+50+100 -> 260 | AU24: =100+70+60+50 -> 280 | AV24: =40+40+40 -> 120 | AW24: =60+70+70+70+40+40 -> 350 | AX24: =60+60 -> 120 | AY24: =70+60 -> 130 | BA24: =60+120 -> 180 | BB24: =250+60 -> 310 | BE24: =100+60+60+70+60+80+60 -> 490 | BF24: =60+40 -> 100 | BN24: 50 | BQ24: 70 | BT24: =90+2 -> 92 | BW24: 70 | BZ24: 70 | CA24: =40 -> 40 | CC24: =100+70 -> 170 | CD24: =70+70+70 -> 210 | CF24: 90 | CH24: 70 | CJ24: 70 | CK24: =70+40 -> 110 | CM24: =100+40 -> 140 | CO24: =150+70+50+70 -> 340 | CR24: =70+2 -> 72 | CS24: 80 | CT24: =100+150+100 -> 350 | CU24: =200+80 -> 280 | CV24: 70 | CW24: =80+70+40 -> 190 | CX24: =150+70+2+200+2 -> 424
B25: - RATE MENSILI VARIE | C25: =SUM(V25:AG25) -> 0 | D25: =SUM(AH25:AS25) -> 638.4 | E25: =SUM(AT25:BE25) -> 91.2 | F25: =SUM(BF25:BQ25) -> 0 | G25: =SUM(BR25:CC25) -> 588.87 | H25: =SUM(CD25:CO25) -> 528.53 | I25: =SUM(CP25:DA25) -> 2021.24 | K25: =C25/12 -> 0 | L25: =D25/12 -> 53.2 | M25: =E25/12 -> 7.6 | N25: =F25/12 -> 0 | O25: =G25/12 -> 49.0725 | P25: =H25/12 -> 44.044167 | Q25: =I25/12 -> 168.43667 | AM25: 91.2 | AN25: 91.2 | AO25: 91.2 | AP25: 91.2 | AQ25: 91.2 | AR25: 91.2 | AS25: 91.2 | AT25: 91.2 | BR25: =63.45+2.5 -> 65.95 | BS25: =63.45+2.5 -> 65.95 | BT25: =63.45+2.5 -> 65.95 | BU25: =63.45+2.5 -> 65.95 | BV25: =63.45+2.5 -> 65.95 | BW25: =63.44+2.5 -> 65.94 | CB25: =95.34 -> 95.34 | CC25: =(95.34+2.5) -> 97.84 | CD25: =214.61+2.5 -> 217.11 | CE25: =(119.26+2.5) -> 121.76 | CF25: 121.77 | CO25: =65.39+2.5 -> 67.89 | CP25: =65.4+120.76+2.5 -> 188.66 | CQ25: =65.4+120.77+2.5 -> 188.67 | CR25: =120.77+2.5 -> 123.27 | CS25: =120.77+2.5+249.23 -> 372.5 | CT25: =120.77+2.5+249.23 -> 372.5 | CU25: =370.04+2.5 -> 372.54 | CW25: =37.6+2.5 -> 40.1 | CX25: =37.6+2.5+50.65 -> 90.75 | CY25: =37.6+2.5+50.65 -> 90.75 | CZ25: =37.6+2.5+50.65 -> 90.75 | DA25: =37.6+2.5+50.65 -> 90.75 | DB25: =2.5+50.65 -> 53.15
B26: - SPESE GENERICHE | C26: =SUM(V26:AG26) -> 9181.81 | D26: =SUM(AH26:AS26) -> 7707.81 | E26: =SUM(AT26:BE26) -> 2988.77 | F26: =SUM(BF26:BQ26) -> 1673.08 | G26: =SUM(BR26:CC26) -> 2606.85 | H26: =SUM(CD26:CO26) -> 2155.26 | I26: =SUM(CP26:DA26) -> 6120.49 | K26: =C26/12 -> 765.15083 | L26: =D26/12 -> 642.3175 | M26: =E26/12 -> 249.06417 | N26: =F26/12 -> 139.42333 | O26: =G26/12 -> 217.2375 | P26: =H26/12 -> 179.605 | Q26: =IFERROR(AVERAGEIF(CP26:DA26,">0"),0) -> 765.06125 | S26: ='Riepilogo Mensile BANCOMAT'!K2 -> 0 | T26: ='Riepilogo Mensile BANCOMAT'!L2 -> 25 | U26: ='Riepilogo Mensile BANCOMAT'!M2 -> 687.75 | V26: ='Riepilogo Mensile BANCOMAT'!B3 -> 261.89 | W26: ='Riepilogo Mensile BANCOMAT'!C3 -> 512 | X26: ='Riepilogo Mensile BANCOMAT'!D3 -> 148.8 | Y26: ='Riepilogo Mensile BANCOMAT'!E3 -> 40 | Z26: ='Riepilogo Mensile BANCOMAT'!F3 -> 142 | AA26: ='Riepilogo Mensile BANCOMAT'!G3 -> 352.5 | AB26: ='Riepilogo Mensile BANCOMAT'!H3 -> 190 | AC26: ='Riepilogo Mensile BANCOMAT'!I3 -> 528.4 | ... AG26: ='Riepilogo Mensile BANCOMAT'!M3 -> 5424.98 | AH26: ='Riepilogo Mensile BANCOMAT'!B4 -> 40 | AI26: ='Riepilogo Mensile BANCOMAT'!C4 -> 3076.73 | AJ26: ='Riepilogo Mensile BANCOMAT'!D4 -> 1265.5 | AK26: ='Riepilogo Mensile BANCOMAT'!E4 -> 92.3 | AL26: ='Riepilogo Mensile BANCOMAT'!F4 -> 65.04 | AM26: ='Riepilogo Mensile BANCOMAT'!G4 -> 0 | AN26: ='Riepilogo Mensile BANCOMAT'!H4 -> 549.81 | AO26: ='Riepilogo Mensile BANCOMAT'!I4 -> 1249.1 | ... AS26: ='Riepilogo Mensile BANCOMAT'!M4 -> 827.33 | AT26: ='Riepilogo Mensile BANCOMAT'!B5 -> 1421.01 | AU26: ='Riepilogo Mensile BANCOMAT'!C5 -> 90.41 | AV26: ='Riepilogo Mensile BANCOMAT'!D5 -> 0 | AW26: ='Riepilogo Mensile BANCOMAT'!E5 -> 497.34 | AX26: ='Riepilogo Mensile BANCOMAT'!F5 -> 104.83 | AY26: ='Riepilogo Mensile BANCOMAT'!G5 -> 2 | AZ26: ='Riepilogo Mensile BANCOMAT'!H5 -> 120.5 | BA26: ='Riepilogo Mensile BANCOMAT'!I5 -> 363.4 | ... BE26: ='Riepilogo Mensile BANCOMAT'!M5 -> 256.65 | BF26: ='Riepilogo Mensile BANCOMAT'!B6 -> 356.29 | BG26: ='Riepilogo Mensile BANCOMAT'!C6 -> 0 | BH26: ='Riepilogo Mensile BANCOMAT'!D6 -> 150.5 | BI26: ='Riepilogo Mensile BANCOMAT'!E6 -> 16.8 | BJ26: ='Riepilogo Mensile BANCOMAT'!F6 -> 250 | BK26: ='Riepilogo Mensile BANCOMAT'!G6 -> 0 | BL26: ='Riepilogo Mensile BANCOMAT'!H6 -> 0 | BM26: ='Riepilogo Mensile BANCOMAT'!I6 -> 620.5 | ... BQ26: ='Riepilogo Mensile BANCOMAT'!M6 -> 125.49 | BR26: ='Riepilogo Mensile BANCOMAT'!B7 -> 373.72 | BS26: ='Riepilogo Mensile BANCOMAT'!C7 -> 150.5 | BT26: ='Riepilogo Mensile BANCOMAT'!D7 -> 207.78 | BU26: ='Riepilogo Mensile BANCOMAT'!E7 -> -68 | BV26: ='Riepilogo Mensile BANCOMAT'!F7 -> 79 | BW26: ='Riepilogo Mensile BANCOMAT'!G7 -> 10.2 | BX26: ='Riepilogo Mensile BANCOMAT'!H7 -> 15.04 | BY26: ='Riepilogo Mensile BANCOMAT'!I7 -> 917.6 | ... CC26: ='Riepilogo Mensile BANCOMAT'!M7 -> 604.64 | CD26: ='Riepilogo Mensile BANCOMAT'!B8 -> 364.41 | CE26: ='Riepilogo Mensile BANCOMAT'!C8 -> 26.34 | CF26: ='Riepilogo Mensile BANCOMAT'!D8 -> 637.25 | CG26: ='Riepilogo Mensile BANCOMAT'!E8 -> 532.48 | CH26: ='Riepilogo Mensile BANCOMAT'!F8 -> 4.75 | CI26: ='Riepilogo Mensile BANCOMAT'!G8 -> 0 | CJ26: ='Riepilogo Mensile BANCOMAT'!H8 -> 0 | CK26: ='Riepilogo Mensile BANCOMAT'!I8 -> 48.65 | ... CO26: ='Riepilogo Mensile BANCOMAT'!M8 -> 404.4 | CP26: ='Riepilogo Mensile BANCOMAT'!B9 -> 291.84 | CQ26: ='Riepilogo Mensile BANCOMAT'!C9 -> 0 | CR26: ='Riepilogo Mensile BANCOMAT'!D9 -> 72.6 | CS26: ='Riepilogo Mensile BANCOMAT'!E9 -> 1434.78 | CT26: ='Riepilogo Mensile BANCOMAT'!F9 -> 201.23 | CU26: ='Riepilogo Mensile BANCOMAT'!G9 -> 662.62 | CV26: ='Riepilogo Mensile BANCOMAT'!H9 -> 230.94 | CW26: ='Riepilogo Mensile BANCOMAT'!I9 -> 2423.64 | ... DA26: ='Riepilogo Mensile BANCOMAT'!M9 -> 0 | DB26: ='Riepilogo Mensile BANCOMAT'!B10 -> 0 | DC26: ='Riepilogo Mensile BANCOMAT'!C10 -> 0 | DD26: ='Riepilogo Mensile BANCOMAT'!D10 -> 0 | DE26: ='Riepilogo Mensile BANCOMAT'!E10 -> 0 | DF26: ='Riepilogo Mensile BANCOMAT'!F10 -> 0 | DG26: ='Riepilogo Mensile BANCOMAT'!G10 -> 0 | DH26: ='Riepilogo Mensile BANCOMAT'!H10 -> 0 | DI26: ='Riepilogo Mensile BANCOMAT'!I10 -> 0 | ... DM26: ='Riepilogo Mensile BANCOMAT'!M10 -> 0 | DN26: ='Riepilogo Mensile BANCOMAT'!B11 -> 0 | DO26: ='Riepilogo Mensile BANCOMAT'!C11 -> 0 | DP26: ='Riepilogo Mensile BANCOMAT'!D11 -> 0 | DQ26: ='Riepilogo Mensile BANCOMAT'!E11 -> 0 | DR26: ='Riepilogo Mensile BANCOMAT'!F11 -> 0 | DS26: ='Riepilogo Mensile BANCOMAT'!G11 -> 0 | DT26: ='Riepilogo Mensile BANCOMAT'!H11 -> 0 | DU26: ='Riepilogo Mensile BANCOMAT'!I11 -> 0 | ... DY26: ='Riepilogo Mensile BANCOMAT'!M11 -> 0 | DZ26: ='Riepilogo Mensile BANCOMAT'!B12 -> 0 | EA26: ='Riepilogo Mensile BANCOMAT'!C12 -> 0 | EB26: ='Riepilogo Mensile BANCOMAT'!D12 -> 0 | EC26: ='Riepilogo Mensile BANCOMAT'!E12 -> 0 | ED26: ='Riepilogo Mensile BANCOMAT'!F12 -> 0 | EE26: ='Riepilogo Mensile BANCOMAT'!G12 -> 0 | EF26: ='Riepilogo Mensile BANCOMAT'!H12 -> 0 | EG26: ='Riepilogo Mensile BANCOMAT'!I12 -> 0 | ... EK26: ='Riepilogo Mensile BANCOMAT'!M12 -> 0 | EL26: ='Riepilogo Mensile BANCOMAT'!B13 -> 0 | EM26: ='Riepilogo Mensile BANCOMAT'!C13 -> 0 | EN26: ='Riepilogo Mensile BANCOMAT'!D13 -> 0 | EO26: ='Riepilogo Mensile BANCOMAT'!E13 -> 0 | EP26: ='Riepilogo Mensile BANCOMAT'!F13 -> 0 | EQ26: ='Riepilogo Mensile BANCOMAT'!G13 -> 0 | ER26: ='Riepilogo Mensile BANCOMAT'!H13 -> 0 | ES26: ='Riepilogo Mensile BANCOMAT'!I13 -> 0 | ... EW26: ='Riepilogo Mensile BANCOMAT'!M13 -> 0 | EX26: ='Riepilogo Mensile BANCOMAT'!B14 -> 0 | EY26: ='Riepilogo Mensile BANCOMAT'!C14 -> 0 | EZ26: ='Riepilogo Mensile BANCOMAT'!D14 -> 0 | FA26: ='Riepilogo Mensile BANCOMAT'!E14 -> 0 | FB26: ='Riepilogo Mensile BANCOMAT'!F14 -> 0 | FC26: ='Riepilogo Mensile BANCOMAT'!G14 -> 0 | FD26: ='Riepilogo Mensile BANCOMAT'!H14 -> 0 | FE26: ='Riepilogo Mensile BANCOMAT'!I14 -> 0 | ... FI26: ='Riepilogo Mensile BANCOMAT'!M14 -> 0 | FJ26: ='Riepilogo Mensile BANCOMAT'!B15 -> 0 | FK26: ='Riepilogo Mensile BANCOMAT'!C15 -> 0 | FL26: ='Riepilogo Mensile BANCOMAT'!D15 -> 0 | FM26: ='Riepilogo Mensile BANCOMAT'!E15 -> 0 | FN26: ='Riepilogo Mensile BANCOMAT'!F15 -> 0 | FO26: ='Riepilogo Mensile BANCOMAT'!G15 -> 0 | FP26: ='Riepilogo Mensile BANCOMAT'!H15 -> 0 | FQ26: ='Riepilogo Mensile BANCOMAT'!I15 -> 0 | ... FU26: ='Riepilogo Mensile BANCOMAT'!M15 -> 0 | FV26: ='Riepilogo Mensile BANCOMAT'!B16 -> 0 | FW26: ='Riepilogo Mensile BANCOMAT'!C16 -> 0 | FX26: ='Riepilogo Mensile BANCOMAT'!D16 -> 0 | FY26: ='Riepilogo Mensile BANCOMAT'!E16 -> 0 | FZ26: ='Riepilogo Mensile BANCOMAT'!F16 -> 0 | GA26: ='Riepilogo Mensile BANCOMAT'!G16 -> 0 | GB26: ='Riepilogo Mensile BANCOMAT'!H16 -> 0 | GC26: ='Riepilogo Mensile BANCOMAT'!I16 -> 0 | ... GG26: ='Riepilogo Mensile BANCOMAT'!M16 -> 0 | GH26: ='Riepilogo Mensile BANCOMAT'!B17 -> 0 | GI26: ='Riepilogo Mensile BANCOMAT'!C17 -> 0 | GJ26: ='Riepilogo Mensile BANCOMAT'!D17 -> 0 | GK26: ='Riepilogo Mensile BANCOMAT'!E17 -> 0 | GL26: ='Riepilogo Mensile BANCOMAT'!F17 -> 0 | GM26: ='Riepilogo Mensile BANCOMAT'!G17 -> 0 | GN26: ='Riepilogo Mensile BANCOMAT'!H17 -> 0 | GO26: ='Riepilogo Mensile BANCOMAT'!I17 -> 0 | ... GS26: ='Riepilogo Mensile BANCOMAT'!M17 -> 0 | GT26: ='Riepilogo Mensile BANCOMAT'!B18 -> 0
B27: TOTALE SPESE CONTO | C27: =SUM(C15:C26) -> 30664.82 | D27: =SUM(D15:D26) -> 25975.44 | E27: =SUM(E15:E26) -> 53374.24 | F27: =SUM(F15:F26) -> 17390.07 | G27: =SUM(G15:G26) -> 18840.65 | H27: =SUM(H15:H26) -> 17417.75 | I27: =SUM(CP27:DA27) -> 24640.746 | K27: =C27/12 -> 2555.4017 | L27: =D27/12 -> 2164.62 | M27: =E27/12 -> 4447.8533 | N27: =F27/12 -> 1449.1725 | O27: =G27/12 -> 1570.0542 | P27: =H27/12 -> 1451.4792 | Q27: =IFERROR(AVERAGEIF(CP27:DA27,">0"),0) -> 2053.3955 | S27: =SUM(S15:S26) -> 776.93 | T27: =SUM(T15:T26) -> 801.93 | U27: =SUM(U15:U26) -> 1519.81 | V27: =SUM(V15:V26) -> 1038.82 | W27: =SUM(W15:W26) -> 1468.93 | X27: =SUM(X15:X26) -> 1019.16 | Y27: =SUM(Y15:Y26) -> 816.93 | Z27: =SUM(Z15:Z26) -> 1099.02 | ... AH27: =SUM(AH15:AH26) -> 911.23 | AI27: =SUM(AI15:AI26)-AI22-AI23 -> 3879.73 | AJ27: =SUM(AJ15:AJ26) -> 4162.39 | AK27: =SUM(AK15:AK26)-AK22-AK23 -> 1021.68 | AL27: =SUM(AL15:AL26) -> 924.51 | AM27: =SUM(AM15:AM26)-AM22-AM23 -> 1200.88 | AN27: =SUM(AN15:AN26) -> 1845.86 | AO27: =SUM(AO15:AO26)-AO22-AO23 -> 2947.28 | AP27: =SUM(AP15:AP26) -> 1800.71 | AQ27: =SUM(AQ15:AQ26)-AQ22-AQ23 -> 1783.08 | AR27: =SUM(AR15:AR26) -> 1577.28 | AS27: =SUM(AS15:AS26) -> 2817.48 | AT27: =SUM(AT15:AT26) -> 2768.29 | AU27: =SUM(AU15:AU26) -> 15847.79 | AV27: =SUM(AV15:AV26) -> 967.73 | AW27: =SUM(AW15:AW26) -> 1910.15 | AX27: =SUM(AX15:AX26) -> 1472.38 | AY27: =SUM(AY15:AY26) -> 1248.87 | ... GT27: =SUM(GT15:GT26) -> 746.85
B28: +ENTRATE STRAORDINARIE | C28: =SUM(V28:AG28) -> 1801.12 | D28: =SUM(AH28:AS28) -> 11202 | E28: =SUM(AT28:BE28) -> 33045.29 | F28: =SUM(BF28:BQ28) -> 1061.75 | G28: =SUM(BR28:CC28) -> 2770.49 | H28: =SUM(CD28:CO28) -> 1874.34 | I28: =SUM(CP28:DA28) -> 4205.83 | K28: =C28/12 -> 150.09333 | L28: =D28/12 -> 933.5 | M28: =E28/12 -> 2753.7742 | N28: =F28/12 -> 88.479167 | O28: =G28/12 -> 230.87417 | P28: =H28/12 -> 156.195 | Q28: =IFERROR(SUM(CP28:DA28)/12,0) -> 350.48583 | U28: =200+0.87 -> 200.87 | W28: =180 -> 180 | Z28: 180 | AB28: 220 | AC28: 180 | AD28: 420 | AE28: 210 | AF28: =290+60 -> 350 | AG28: =60+1.12 -> 61.12 | AH28: 60 | AI28: =2000+2650 -> 4650 | AJ28: =630 -> 630 | AM28: =250 -> 250 | AN28: =200+70+5000+200 -> 5470 | AR28: =42+100 -> 142 | AT28: =0.08+13800 -> 13800.08 | AV28: 475.2 | AW28: 18400 | AZ28: =200 -> 200 | BA28: =70 -> 70 | BB28: =100+0.01 -> 100.01 | BF28: 0.12 | BH28: 150 | BJ28: =250 -> 250 | BL28: 380 | BM28: 281.63 | BR28: 0.03 | BV28: 125 | BY28: =255.46 -> 255.46 | BZ28: =100 -> 100 | CA28: =700+200+69+700 -> 1669 | CB28: =77+300 -> 377 | CC28: =(120+62+62) -> 244 | CD28: =0.06+65 -> 65.06 | CF28: =165+85 -> 250 | CG28: =30+30+40+137+77 -> 314 | CK28: =480.28 -> 480.28 | CL28: =87+76+62 -> 225 | CM28: =230+100 -> 330 | CN28: 210 | CP28: =0.11+150 -> 150.11 | CQ28: =136 -> 136 | CS28: =130+440 -> 570 | CU28: =230+150 -> 380 | CV28: 69.45 | CW28: =90.27+1266+418.09+650+30.25 -> 2454.61 | CX28: =21.23+92.14+150+162 -> 425.37 | CY28: =20.29 -> 20.29
B29: +DETRAZIONI IRPEF | C29: =SUM(V29:AG29) -> 0 | D29: =SUM(AH29:AS29) -> 0 | E29: =SUM(AT29:BE29) -> 804 | F29: =SUM(BF29:BQ29) -> 854 | G29: =SUM(BR29:CC29) -> 763 | H29: =SUM(CD29:CO29) -> 590 | I29: =SUM(CP29:DA29) -> 0 | K29: =C29/12 -> 0 | L29: =D29/12 -> 0 | M29: =E29/12 -> 67 | N29: =F29/12 -> 71.166667 | O29: =G29/12 -> 63.583333 | P29: =H29/12 -> 49.166667 | Q29: =IFERROR(SUM(CP29:DA29)/12,0) -> 0 | BA29: 804 | BN29: 854 | BY29: 763 | CK29: 590
B30: TOTALE ENTRATE EXTRA | C30: =SUM(V30:AG30) -> 7592.12 | D30: =SUM(AH30:AS30) -> 14492 | E30: =SUM(AT30:BE30) -> 37720.29 | F30: =SUM(BF30:BQ30) -> 4247.75 | G30: =SUM(BR30:CC30) -> 9773.49 | H30: =SUM(CD30:CO30) -> 8401.34 | I30: =SUM(CP30:DA30) -> 54325.88 | K30: =C30/12 -> 632.67667 | L30: =D30/12 -> 1207.6667 | M30: =E30/12 -> 3143.3575 | N30: =F30/12 -> 353.97917 | O30: =G30/12 -> 814.4575 | P30: =H30/12 -> 700.11167 | Q30: =IFERROR(SUM(CP30:DA30)/12,0) -> 4527.1567 | S30: =S28+S29+S12 -> 0 | T30: =T28+T29+T12 -> 0 | U30: =U28+U29+U12 -> 3725.87 | V30: =V28+V29+V12 -> 0 | W30: =W28+W29+W12 -> 180 | X30: =X28+X29+X12 -> 0 | Y30: =Y28+Y29+Y12 -> 0 | Z30: =Z28+Z29+Z12 -> 180 | ... GT30: =GT28+GT29+GT12 -> 0
B31: - ADDEBITO CARTA DI CREDITO | C31: =SUM(V31:AG31) -> 12941.27 | D31: =SUM(AH31:AS31) -> 13633.79 | E31: =SUM(AT31:BE31) -> 12785.23 | F31: =SUM(BF31:BQ31) -> 15000.66 | G31: =SUM(BR31:CC31) -> 15763.13 | H31: =SUM(CD31:CO31) -> 18091.008 | I31: =SUM(CP31:DA31) -> 20013.164 | K31: =C31/12 -> 1078.4392 | L31: =D31/12 -> 1136.1492 | M31: =E31/12 -> 1065.4358 | N31: =F31/12 -> 1250.055 | O31: =G31/12 -> 1313.5942 | P31: =H31/12 -> 1507.584 | Q31: =IFERROR(AVERAGEIF(CE31:CP31,">0"),0) -> 1565.674 | S31: =IF(S64="",$C$64,S64) -> 925 | T31: =IF(T8=0,Valutazioni!$C$3,T64) -> 1075.5 | U31: =IF(U8=0,Valutazioni!$C$3,U64) -> 1120.38 | V31: =IF(V8=0,Valutazioni!$C$3,V64) -> 1713.29 | W31: =IF(W8=0,Valutazioni!$C$3,W64) -> 874.86 | X31: =IF(X8=0,Valutazioni!$C$3,X64) -> 1181.77 | Y31: =IF(Y8=0,Valutazioni!$C$3,Y64) -> 984.2 | Z31: =IF(Z8=0,Valutazioni!$C$3,Z64) -> 694.98 | AA31: =IF(AA8=0,Valutazioni!$C$3,AA64) -> 850.93 | ... CY31: =IF(CY8=0,Valutazioni!$C$3,CY64) -> 2230.93 | CZ31: =IF(CZ8=0,$B$67*(1+$B$68),CZ64+Valutazioni!$I$3) -> 1100 | DA31: =IF(DA8=0,$B$67*(1+$B$68),DA64+Valutazioni!$I$3) -> 1100 | DB31: =IF(DB8=0,$B$67*(1+$B$68),DB64+Valutazioni!$I$3) -> 1100 | DC31: =IF(DC8=0,$B$67*(1+$B$68),DC64+Valutazioni!$I$3) -> 1100 | DD31: =IF(DD8=0,$B$67*(1+$B$68),DD64+Valutazioni!$I$3) -> 1100 | DE31: =IF(DE8=0,$B$67*(1+$B$68),DE64+Valutazioni!$I$3) -> 1100 | DF31: =IF(DF8=0,$B$67*(1+$B$68),DF64+Valutazioni!$I$3) -> 1100 | DG31: =IF(DG8=0,$B$67*(1+$B$68),DG64+Valutazioni!$I$3) -> 1100 | ... GT31: =IF(GT8=0,$B$67*(1+$B$68),GT64+Valutazioni!$I$3) -> 1100
B32: SALDO CONTO | C32: =C11-C27+C30-C31 -> -9327.97 | D32: =D11-D27+D30-D31 -> 1510.77 | E32: =E11-E27+E30-E31 -> -955.18 | F32: =F11-F27+F30-F31 -> -668.98 | G32: =G11-G27+G30-G31 -> 5272.71 | H32: =H11-H27+H30-H31 -> 3127.582 | I32: =I11-I27+I30-I31 -> 42543.97 | K32: =C32/12 -> -777.33083 | L32: =D32/12 -> 125.8975 | M32: =E32/12 -> -79.598333 | N32: =F32/12 -> -55.748333 | O32: =G32/12 -> 439.3925 | P32: =H32/12 -> 260.63183 | Q32: =I32/12 -> 3545.3308 | S32: =S14-(S27+IF(S31>0,S31,Valutazioni!$C$3)-S28) -> 7851.23 | T32: =T14-(T27+IF(T31>0,T31,Valutazioni!$C$3)-T28) -> 8195.8 | U32: =U14-(U27+IF(U31>0,U31,Valutazioni!$C$3)-U30) -> 11552.48 | V32: =V14-(V27+IF(V31>0,V31,Valutazioni!$C$3)-V30) -> 11541.37 | W32: =W14-(W27+IF(W31>0,W31,Valutazioni!$C$3)-W30) -> 11543.58 | X32: =X14-(X27+IF(X31>0,X31,Valutazioni!$C$3)-X30) -> 11517.65 | Y32: =Y14-(Y27+IF(Y31>0,Y31,Valutazioni!$C$3)-Y30) -> 11874.52 | Z32: =Z14-(Z27+IF(Z31>0,Z31,Valutazioni!$C$3)-Z30) -> 12417.52 | AA32: =AA14-(AA27+IF(AA31>0,AA31,Valutazioni!$C$3)-AA30) -> 12636.56 | AB32: =AB14-(AB27+IF(AB31>0,AB31,Valutazioni!$C$3)-AB30) -> 13224.53 | ... GT32: =GT14-(GT27+IF(GT31>0,GT31,Valutazioni!$C$3)-GT30) -> 123190.3
B33: MARGINE PERCENTUALE % | C33: =C32/(C11+C28) -> -0.32744518 | D33: =D32/(D11+D28) -> 0.039935765 | E33: =E32/(E11+E28) -> -0.015780459 | F33: =F32/(F11+F28) -> -0.023443575 | G33: =G32/(G11+G28) -> 0.16039398 | H33: =H32/(H11+H28) -> 0.09740412 | I33: =I32/(I11+I28) -> 1.1474234 | K33: =K32/(K11+K28) -> -0.32744518 | L33: =L32/(L11+L28) -> 0.039935765 | M33: =M32/(M11+M28) -> -0.015780459 | N33: =N32/(N11+N28) -> -0.023443575 | O33: =O32/(O11+O28) -> 0.16039398 | P33: =P32/(P11+P28) -> 0.09740412 | Q33: =Q32/(Q11+Q28) -> 1.1474234 | T33: =(T32-S32)/S32 -> 0.043887391 | U33: =(U32-T32)/T32 -> 0.40956099 | V33: =(V32-U32)/U32 -> -0.00096169827 | W33: =(W32-V32)/V32 -> 0.00019148507 | X33: =(X32-W32)/W32 -> -0.0022462702 | Y33: =(Y32-X32)/X32 -> 0.030984619 | Z33: =(Z32-Y32)/Y32 -> 0.045728164 | AA33: =(AA32-Z32)/Z32 -> 0.017639593 | ... GT33: =(GT32-GS32)/GS32 -> 0.0064636888
S34: =S9 -> 43739 | T34: =T9 -> 43770 | U34: =U9 -> 43800 | V34: =V9 -> 43831 | W34: =W9 -> 43862 | X34: =X9 -> 43891 | Y34: =Y9 -> 43922 | Z34: =Z9 -> 43952 | ... EQ34: =EQ9 -> 47635
B35: RIMANENZA FINALE | C35: =AG32 -> 2224.51 | D35: =AS32 -> 4838.61 | E35: =BE32 -> 3883.43 | F35: =BQ32 -> 3214.45 | G35: =CC32 -> 8487.16 | H35: =CO32 -> 11614.742 | I35: =DA32 -> 54158.712 | K35: =AVERAGE(V32:AG32) -> 10592.124 | L35: =AVERAGE(AH32:AS32) -> 2915.8117 | M35: =AVERAGE(AT32:BE32) -> 11040.905 | N35: =AVERAGE(BF32:BQ32) -> 2594.7667 | O35: =AVERAGE(BR32:CC32) -> 5674.675 | P35: =AVERAGE(CD32:CO32) -> 10543.306 | Q35: =AVERAGE(CP32:DA32) -> 36557.754
S38: =IF($B$2=S39,TRUE,FALSE) -> FALSE | T38: =IF($B$2=T39,TRUE,FALSE) -> FALSE | U38: =IF($B$2=U39,TRUE,FALSE) -> FALSE | V38: =IF($B$2=V39,TRUE,FALSE) -> FALSE | W38: =IF($B$2=W39,TRUE,FALSE) -> FALSE | X38: =IF($B$2=X39,TRUE,FALSE) -> FALSE | Y38: =IF($B$2=Y39,TRUE,FALSE) -> FALSE | Z38: =IF($B$2=Z39,TRUE,FALSE) -> FALSE | ... GT38: =IF($B$2=GT39,TRUE,FALSE) -> FALSE
B39: SITUAZIONE CARTA DI CREDITO | C39: 2020 | D39: 2021 | E39: 2022 | F39: 2023 | G39: 2024 | H39: 2025 | I39: 2026 | K39: 2020 | L39: 2021 | M39: 2022 | N39: 2023 | O39: 2024 | P39: 2025 | Q39: 2026 | S39: 43718 | T39: 43748 | U39: 43779 | V39: 43809 | W39: 43840 | X39: 43871 | Y39: 43900 | Z39: 43931 | AA39: 43961 | AB39: 43992 | AC39: 44022 | AD39: 44053 | AE39: 44084 | AF39: 44114 | AG39: 44145 | AH39: 44175 | AI39: 44206 | AJ39: 44237 | AK39: 44265 | AL39: 44296 | AM39: 44326 | AN39: 44357 | AO39: 44378 | AP39: 44409 | AQ39: 44440 | AR39: 44470 | AS39: 44501 | AT39: 44531 | AU39: 44562 | AV39: 44593 | AW39: 44621 | AX39: 44652 | AY39: 44682 | AZ39: 44713 | BA39: 44743 | BB39: 44774 | BC39: 44805 | BD39: 44835 | BE39: 44866 | BF39: 44896 | BG39: 44927 | BH39: 44958 | BI39: 44986 | BJ39: 45017 | BK39: 45047 | BL39: 45078 | BM39: 45108 | BN39: 45139 | BO39: 45170 | BP39: 45200 | BQ39: 45231 | BR39: 45261 | BS39: 45292 | BT39: 45323 | BU39: 45352 | BV39: 45383 | BW39: 45413 | BX39: 45444 | BY39: 45474 | BZ39: 45505 | CA39: 45536 | CB39: 45566 | CC39: 45597 | CD39: 45627 | CE39: 45658 | CF39: 45689 | CG39: 45717 | CH39: 45748 | CI39: 45778 | CJ39: 45809 | CK39: 45839 | CL39: 45870 | CM39: 45901 | CN39: 45931 | CO39: 45962 | CP39: 45992 | CQ39: 46023 | CR39: 46054 | CS39: 46082 | CT39: 46113 | CU39: 46143 | CV39: 46174 | CW39: 46204 | CX39: 46235 | CY39: 46266 | CZ39: 46296 | DA39: 46327 | DB39: 46357 | DC39: 46388 | DD39: 46419 | DE39: 46447 | DF39: 46478 | DG39: 46508 | DH39: 46539 | DI39: 46569 | DJ39: 46600 | DK39: 46631 | DL39: 46661 | DM39: 46692 | DN39: 46722 | DO39: 46753 | DP39: 46784 | DQ39: 46813 | DR39: 46844 | DS39: 46874 | DT39: 46905 | DU39: 46935 | DV39: 46966 | DW39: 46997 | DX39: 47027 | DY39: 47058 | DZ39: 47088 | EA39: 47119 | EB39: 47150 | EC39: 47178 | ED39: 47209 | EE39: 47239 | EF39: 47270 | EG39: 47300 | EH39: 47331 | EI39: 47362 | EJ39: 47392 | EK39: 47423 | EL39: 47453 | EM39: 47484 | EN39: 47515 | EO39: 47543 | EP39: 47574 | EQ39: 47604 | ER39: 47635 | ES39: 47665 | ET39: 47696 | EU39: 47727 | EV39: 47757 | EW39: 47788 | EX39: 47818 | EY39: 47849 | EZ39: 47880 | FA39: 47908 | FB39: 47939 | FC39: 47969 | FD39: 48000 | FE39: 48030 | FF39: 48061 | FG39: 48092 | FH39: 48122 | FI39: 48153 | FJ39: 48183 | FK39: 48214 | FL39: 48245 | FM39: 48274 | FN39: 48305 | FO39: 48335 | FP39: 48366 | FQ39: 48396 | FR39: 48427 | FS39: 48458 | FT39: 48488 | FU39: 48519 | FV39: 48549 | FW39: 48580 | FX39: 48611 | FY39: 48639 | FZ39: 48670 | GA39: 48700 | GB39: 48731 | GC39: 48761 | GD39: 48792 | GE39: 48823 | GF39: 48853 | GG39: 48884 | GH39: 48914 | GI39: 48945 | GJ39: 48976 | GK39: 49004 | GL39: 49035 | GM39: 49065 | GN39: 49096 | GO39: 49126 | GP39: 49157 | GQ39: 49188 | GR39: 49218 | GS39: 49249 | GT39: 49279
B40: SPESE FISSE | K40: MEDIA ANNUA CARTA
B41: - MICROSOFT OFFICE | C41: =SUM(V41:AG41) -> 83 | D41: =SUM(AH41:AS41) -> 69 | E41: =SUM(AT41:BE41) -> 59 | F41: =SUM(BF41:BQ41) -> 43.99 | G41: =SUM(BR41:CC41) -> 47.99 | H41: =SUM(CD41:CO41) -> 46.99 | I41: =SUM(CP41:DA41) -> 73.1 | K41: =C41/12 -> 6.9166667 | L41: =D41/12 -> 5.75 | M41: =E41/12 -> 4.9166667 | N41: =F41/12 -> 3.6658333 | O41: =G41/12 -> 3.9991667 | P41: =H41/12 -> 3.9158333 | Q41: =I41/12 -> 6.0916667 | S41: 7 | T41: 7 | U41: 7 | V41: 7 | W41: 7 | X41: 69 | AJ41: 69 | AV41: 19.67 | AW41: 19.67 | AX41: 19.66 | BJ41: 43.99 | BT41: 16 | BU41: 16 | BV41: 15.99 | CH41: 46.99 | CT41: 24.37 | CU41: 24.37 | CV41: =24.36 -> 24.36
B42: - DISNEY PLUS | C42: =SUM(V42:AG42) -> 48.93 | D42: =SUM(AH42:AS42) -> 27.96 | E42: =SUM(AT42:BE42) -> 0 | F42: =SUM(BF42:BQ42) -> 0 | G42: =SUM(BR42:CC42) -> 0 | H42: =SUM(CD42:CO42) -> 8 | I42: =SUM(CP42:DA42) -> 56 | K42: =C42/12 -> 4.0775 | L42: =D42/12 -> 2.33 | M42: =E42/12 -> 0 | N42: =F42/12 -> 0 | O42: =G42/12 -> 0 | P42: =H42/12 -> 0.66666667 | Q42: =I42/12 -> 4.6666667 | Z42: 6.99 | AA42: 6.99 | AC42: 6.99 | AD42: 6.99 | AE42: 6.99 | AF42: 6.99 | AG42: 6.99 | AH42: 6.99 | AI42: 6.99 | AJ42: 6.99 | AK42: 6.99 | CO42: 8 | CP42: 8 | CQ42: 8 | CR42: 8 | CS42: 8 | CT42: 8 | CZ42: 8 | DA42: 8 | DB42: 8 | DC42: 8 | DD42: 8 | DE42: 8 | DF42: 8 | DG42: 8 | DH42: 8 | DI42: 8 | DJ42: 8 | DK42: 8 | DL42: 8 | DM42: 8 | DN42: 8 | DO42: 8 | DP42: 8 | DQ42: 8 | DR42: 8 | DS42: 8 | DT42: 8 | DU42: 8 | DV42: 8 | DW42: 8 | DX42: 8 | DY42: 8 | DZ42: 8 | EA42: 8 | EB42: 8 | EC42: 8 | ED42: 8 | EE42: 8 | EF42: 8 | EG42: 8 | EH42: 8 | EI42: 8 | EJ42: 8 | EK42: 8 | EL42: 8 | EM42: 8 | EN42: 8 | EO42: 8 | EP42: 8 | EQ42: 8 | ER42: 8 | ES42: 8 | ET42: 8 | EU42: 8 | EV42: 8 | EW42: 8 | EX42: 8 | EY42: 8 | EZ42: 8 | FA42: 8 | FB42: 8 | FC42: 8 | FD42: 8 | FE42: 8 | FF42: 8 | FG42: 8 | FH42: 8 | FI42: 8 | FJ42: 8 | FK42: 8 | FL42: 8 | FM42: 8 | FN42: 8 | FO42: 8 | FP42: 8 | FQ42: 8 | FR42: 8 | FS42: 8 | FT42: 8 | FU42: 8 | FV42: 8 | FW42: 8 | FX42: 8 | FY42: 8 | FZ42: 8 | GA42: 8 | GB42: 8 | GC42: 8 | GD42: 8 | GE42: 8 | GF42: 8 | GG42: 8 | GH42: 8 | GI42: 8 | GJ42: 8 | GK42: 8 | GL42: 8 | GM42: 8 | GN42: 8 | GO42: 8 | GP42: 8 | GQ42: 8 | GR42: 8 | GS42: 8 | GT42: 8
B43: - NETFLIX | C43: =SUM(V43:AG43) -> 191.88 | D43: =SUM(AH43:AS43) -> 175.88 | E43: =SUM(AT43:BE43) -> 87.89 | F43: =SUM(BF43:BQ43) -> 95.88 | G43: =SUM(BR43:CC43) -> 95.88 | H43: =SUM(CD43:CO43) -> 86.88 | I43: =SUM(CP43:DA43) -> 83.88 | K43: =C43/12 -> 15.99 | L43: =D43/12 -> 14.656667 | M43: =E43/12 -> 7.3241667 | N43: =F43/12 -> 7.99 | O43: =G43/12 -> 7.99 | P43: =H43/12 -> 7.24 | Q43: =I43/12 -> 6.99 | S43: 15.99 | T43: 15.99 | U43: 15.99 | V43: 15.99 | W43: 15.99 | X43: 15.99 | Y43: 15.99 | Z43: 15.99 | AA43: 15.99 | AB43: 15.99 | AC43: 15.99 | AD43: 15.99 | AE43: 15.99 | AF43: 15.99 | AG43: 15.99 | AH43: 15.99 | AI43: 15.99 | AJ43: 15.99 | AK43: 15.99 | AL43: 15.99 | AM43: 15.99 | AN43: 15.99 | AO43: 15.99 | AP43: 15.99 | AQ43: 11.99 | AR43: 11.99 | AS43: 7.99 | AU43: 7.99 | AV43: 7.99 | AW43: 7.99 | AX43: 7.99 | AY43: 7.99 | AZ43: 7.99 | BA43: 7.99 | BB43: 7.99 | BC43: 7.99 | BD43: 7.99 | BE43: 7.99 | BF43: 7.99 | BG43: 7.99 | BH43: 7.99 | BI43: 7.99 | BJ43: 7.99 | BK43: 7.99 | BL43: 7.99 | BM43: 7.99 | BN43: 7.99 | BO43: 7.99 | BP43: 7.99 | BQ43: 7.99 | BR43: 7.99 | BS43: 7.99 | BT43: 7.99 | BU43: 7.99 | BV43: 7.99 | BW43: 7.99 | BX43: 7.99 | BY43: 7.99 | BZ43: 7.99 | CA43: 7.99 | CB43: 7.99 | CC43: 7.99 | CD43: 9.99 | CE43: 6.99 | CF43: 6.99 | CG43: 6.99 | CH43: 6.99 | CI43: 6.99 | CJ43: 6.99 | CK43: 6.99 | CL43: 6.99 | CM43: 6.99 | CN43: 6.99 | CO43: 6.99 | CP43: 6.99 | CQ43: 6.99 | CR43: 6.99 | CS43: 6.99 | CT43: 6.99 | CU43: 6.99 | CV43: 6.99 | CW43: 6.99 | CX43: 6.99 | CY43: 6.99 | CZ43: 6.99 | DA43: 6.99 | DB43: 6.99 | DC43: 6.99 | DD43: 6.99 | DE43: 6.99 | DF43: 6.99 | DG43: 6.99 | DH43: 6.99 | DI43: 6.99 | DJ43: 6.99 | DK43: 6.99 | DL43: 6.99 | DM43: 6.99 | DN43: 6.99 | DO43: 6.99 | DP43: 6.99 | DQ43: 6.99 | DR43: 6.99 | DS43: 6.99 | DT43: 6.99 | DU43: 6.99 | DV43: 6.99 | DW43: 6.99 | DX43: 6.99 | DY43: 6.99 | DZ43: 6.99 | EA43: 6.99 | EB43: 6.99 | EC43: 6.99 | ED43: 6.99 | EE43: 6.99 | EF43: 6.99 | EG43: 6.99 | EH43: 6.99 | EI43: 6.99 | EJ43: 6.99 | EK43: 6.99 | EL43: 6.99 | EM43: 6.99 | EN43: 6.99 | EO43: 6.99 | EP43: 6.99 | EQ43: 6.99 | ER43: 6.99 | ES43: 6.99 | ET43: 6.99 | EU43: 6.99 | EV43: 6.99 | EW43: 6.99 | EX43: 6.99 | EY43: 6.99 | EZ43: 6.99 | FA43: 6.99 | FB43: 6.99 | FC43: 6.99 | FD43: 6.99 | FE43: 6.99 | FF43: 6.99 | FG43: 6.99 | FH43: 6.99 | FI43: 6.99 | FJ43: 6.99 | FK43: 6.99 | FL43: 6.99 | FM43: 6.99 | FN43: 6.99 | FO43: 6.99 | FP43: 6.99 | FQ43: 6.99 | FR43: 6.99 | FS43: 6.99 | FT43: 6.99 | FU43: 6.99 | FV43: 6.99 | FW43: 6.99 | FX43: 6.99 | FY43: 6.99 | FZ43: 6.99 | GA43: 6.99 | GB43: 6.99 | GC43: 6.99 | GD43: 6.99 | GE43: 6.99 | GF43: 6.99 | GG43: 6.99 | GH43: 6.99 | GI43: 6.99 | GJ43: 6.99 | GK43: 6.99 | GL43: 6.99 | GM43: 6.99 | GN43: 6.99 | GO43: 6.99 | GP43: 6.99 | GQ43: 6.99 | GR43: 6.99 | GS43: 6.99 | GT43: 6.99
B44: - DAZN | C44: =SUM(V44:AG44) -> 59.94 | D44: =SUM(AH44:AS44) -> 119.9 | E44: =SUM(AT44:BE44) -> 119.94 | F44: =SUM(BF44:BQ44) -> 0 | G44: =SUM(BR44:CC44) -> 0 | H44: =SUM(CD44:CO44) -> 70.92 | I44: =SUM(CP44:DA44) -> 0 | K44: =C44/12 -> 4.995 | L44: =D44/12 -> 9.9916667 | M44: =E44/12 -> 9.995 | N44: =F44/12 -> 0 | O44: =G44/12 -> 0 | P44: =H44/12 -> 5.91 | Q44: =I44/12 -> 0 | S44: 9.99 | T44: 9.99 | U44: 9.99 | V44: 9.99 | W44: 9.99 | Z44: 9.99 | AE44: 9.99 | AF44: 9.99 | AG44: 9.99 | AH44: 9.99 | AI44: 9.99 | AJ44: 9.99 | AK44: 9.99 | AL44: 9.99 | AM44: 9.99 | AP44: 9.99 | AQ44: 9.99 | AR44: 19.99 | AS44: 19.99 | AT44: 19.99 | AU44: 19.99 | AV44: 19.99 | AW44: 19.99 | AX44: 19.99 | AZ44: 19.99 | CD44: 5.99 | CE44: =5.99+9.99 -> 15.98 | CF44: 9.99 | CG44: 9.99 | CH44: 9.99 | CI44: 9.99 | CJ44: 8.99
B45: - NOW TV | C45: =SUM(V45:AG45) -> 0 | D45: =SUM(AH45:AS45) -> 309.86 | E45: =SUM(AT45:BE45) -> 239.88 | F45: =SUM(BF45:BQ45) -> 239.88 | G45: =SUM(BR45:CC45) -> 289.88 | H45: =SUM(CD45:CO45) -> 357.96 | I45: =SUM(CP45:DA45) -> 359.88 | K45: =C45/12 -> 0 | L45: =D45/12 -> 25.821667 | M45: =E45/12 -> 19.99 | N45: =F45/12 -> 19.99 | O45: =G45/12 -> 24.156667 | P45: =H45/12 -> 29.83 | Q45: =I45/12 -> 29.99 | AH45: =29.99+29.99 -> 59.98 | AI45: 29.99 | AK45: =29.99+9.99 -> 39.98 | AL45: =29.99+9.99 -> 39.98 | AM45: 19.99 | AN45: 19.99 | AO45: 19.99 | AP45: 19.99 | AQ45: 19.99 | AR45: 19.99 | AS45: 19.99 | AT45: 19.99 | AU45: 19.99 | AV45: 19.99 | AW45: 19.99 | AX45: 19.99 | AY45: 19.99 | AZ45: 19.99 | BA45: 19.99 | BB45: 19.99 | BC45: 19.99 | BD45: 19.99 | BE45: 19.99 | BF45: 19.99 | BG45: 19.99 | BH45: 19.99 | BI45: 19.99 | BJ45: 19.99 | BK45: 19.99 | BL45: 19.99 | BM45: 19.99 | BN45: 19.99 | BO45: 19.99 | BP45: 19.99 | BQ45: 19.99 | BR45: 19.99 | BS45: 19.99 | BT45: 19.99 | BU45: 19.99 | BV45: 19.99 | BW45: 19.99 | BX45: 19.99 | BY45: 29.99 | BZ45: 29.99 | CA45: 29.99 | CB45: 29.99 | CC45: =29.99 -> 29.99 | CD45: =4.99+5+20 -> 29.99 | CE45: 29.99 | CF45: 29.99 | CG45: 28.4 | CH45: 29.66 | CI45: 29.99 | CJ45: 29.99 | CK45: 29.99 | CL45: 29.99 | CM45: 29.99 | CN45: 29.99 | CO45: 29.99 | CP45: 29.99 | CQ45: 29.99 | CR45: 29.99 | CS45: 29.99 | CT45: 29.99 | CU45: 29.99 | CV45: 29.99 | CW45: 29.99 | CX45: 29.99 | CY45: 29.99 | CZ45: 29.99 | DA45: 29.99 | DB45: 29.99 | DC45: 29.99 | DD45: 29.99 | DE45: 29.99 | DF45: 29.99 | DG45: 29.99 | DH45: 29.99 | DI45: 29.99 | DJ45: 29.99 | DK45: 29.99 | DL45: 29.99 | DM45: 29.99 | DN45: 29.99 | DO45: 29.99 | DP45: 29.99 | DQ45: 29.99 | DR45: 29.99 | DS45: 29.99 | DT45: 29.99 | DU45: 29.99 | DV45: 29.99 | DW45: 29.99 | DX45: 29.99 | DY45: 29.99 | DZ45: 29.99 | EA45: 29.99 | EB45: 29.99 | EC45: 29.99 | ED45: 29.99 | EE45: 29.99 | EF45: 29.99 | EG45: 29.99 | EH45: 29.99 | EI45: 29.99 | EJ45: 29.99 | EK45: 29.99 | EL45: 29.99 | EM45: 29.99 | EN45: 29.99 | EO45: 29.99 | EP45: 29.99 | EQ45: 29.99 | ER45: 29.99 | ES45: 29.99 | ET45: 29.99 | EU45: 29.99 | EV45: 29.99 | EW45: 29.99 | EX45: 29.99 | EY45: 29.99 | EZ45: 29.99 | FA45: 29.99 | FB45: 29.99 | FC45: 29.99 | FD45: 29.99 | FE45: 29.99 | FF45: 29.99 | FG45: 29.99 | FH45: 29.99 | FI45: 29.99 | FJ45: 29.99 | FK45: 29.99 | FL45: 29.99 | FM45: 29.99 | FN45: 29.99 | FO45: 29.99 | FP45: 29.99 | FQ45: 29.99 | FR45: 29.99 | FS45: 29.99 | FT45: 29.99 | FU45: 29.99 | FV45: 29.99 | FW45: 29.99 | FX45: 29.99 | FY45: 29.99 | FZ45: 29.99 | GA45: 29.99 | GB45: 29.99 | GC45: 29.99 | GD45: 29.99 | GE45: 29.99 | GF45: 29.99 | GG45: 29.99 | GH45: 29.99 | GI45: 29.99 | GJ45: 29.99 | GK45: 29.99 | GL45: 29.99 | GM45: 29.99 | GN45: 29.99 | GO45: 29.99 | GP45: 29.99 | GQ45: 29.99 | GR45: 29.99 | GS45: 29.99 | GT45: 29.99
B46: - VIDEOGAMES | C46: =SUM(V46:AG46) -> 77.97 | D46: =SUM(AH46:AS46) -> 59.99 | E46: =SUM(AT46:BE46) -> 0 | F46: =SUM(BF46:BQ46) -> 0 | G46: =SUM(BR46:CC46) -> 158.9 | H46: =SUM(CD46:CO46) -> 179.9 | I46: =SUM(CP46:DA46) -> 0 | K46: =C46/12 -> 6.4975 | L46: =D46/12 -> 4.9991667 | M46: =E46/12 -> 0 | N46: =F46/12 -> 0 | O46: =G46/12 -> 13.241667 | P46: =H46/12 -> 14.991667 | Q46: =I46/12 -> 0 | S46: 8.99 | T46: 8.99 | U46: 8.99 | V46: 8.99 | W46: =8.99+59.99 -> 68.98 | AJ46: 59.99 | BT46: 14.99 | BU46: 14.99 | BV46: 14.99 | BW46: 14.99 | BX46: 14.99 | BY46: 14.99 | BZ46: 14.99 | CA46: 17.99 | CB46: 17.99 | CC46: 17.99 | CD46: =17.99 -> 17.99 | CE46: 17.99 | CF46: 17.99 | CG46: 17.99 | CH46: 17.99 | CI46: 17.99 | CJ46: 17.99 | CK46: 17.99 | CL46: 17.99 | CM46: 17.99 | DC46: 12.99 | DD46: 12.99 | DE46: 12.99 | DF46: 12.99 | DG46: 12.99 | DH46: 12.99 | DI46: 12.99 | DJ46: 12.99 | DK46: 12.99 | DL46: 12.99 | DM46: 12.99 | DN46: 12.99 | DO46: 12.99 | DP46: 12.99 | DQ46: 12.99 | DR46: 12.99 | DS46: 12.99 | DT46: 12.99 | DU46: 12.99 | DV46: 12.99 | DW46: 12.99 | DX46: 12.99 | DY46: 12.99 | DZ46: 12.99 | EA46: 12.99 | EB46: 12.99 | EC46: 12.99 | ED46: 12.99 | EE46: 12.99 | EF46: 12.99 | EG46: 12.99 | EH46: 12.99 | EI46: 12.99 | EJ46: 12.99 | EK46: 12.99 | EL46: 12.99 | EM46: 12.99 | EN46: 12.99 | EO46: 12.99 | EP46: 12.99 | EQ46: 12.99 | ER46: 12.99 | ES46: 12.99 | ET46: 12.99
B47: - SPOTIFY | C47: =SUM(V47:AG47) -> 119.88 | D47: =SUM(AH47:AS47) -> 119.88 | E47: =SUM(AT47:BE47) -> 119.88 | F47: =SUM(BF47:BQ47) -> 122.88 | G47: =SUM(BR47:CC47) -> 120.89 | H47: =SUM(CD47:CO47) -> 133.88 | I47: =SUM(CP47:DA47) -> 143.88 | K47: =C47/12 -> 9.99 | L47: =D47/12 -> 9.99 | M47: =E47/12 -> 9.99 | N47: =F47/12 -> 10.24 | O47: =G47/12 -> 10.074167 | P47: =H47/12 -> 11.156667 | Q47: =I47/12 -> 11.99 | S47: 9.99 | T47: 9.99 | U47: 9.99 | V47: 9.99 | W47: 9.99 | X47: 9.99 | Y47: 9.99 | Z47: 9.99 | AA47: 9.99 | AB47: 9.99 | AC47: 9.99 | AD47: 9.99 | AE47: 9.99 | AF47: 9.99 | AG47: 9.99 | AH47: 9.99 | AI47: 9.99 | AJ47: 9.99 | AK47: 9.99 | AL47: 9.99 | AM47: 9.99 | AN47: 9.99 | AO47: 9.99 | AP47: 9.99 | AQ47: 9.99 | AR47: 9.99 | AS47: 9.99 | AT47: 9.99 | AU47: 9.99 | AV47: 9.99 | AW47: 9.99 | AX47: 9.99 | AY47: 9.99 | AZ47: 9.99 | BA47: 9.99 | BB47: 9.99 | BC47: 9.99 | BD47: 9.99 | BE47: 9.99 | BF47: 9.99 | BG47: 9.99 | BH47: 9.99 | BI47: 9.99 | BJ47: 9.99 | BK47: 9.99 | BL47: 9.99 | BM47: 9.99 | BN47: 9.99 | BO47: 10.99 | BP47: 10.99 | BQ47: 10.99 | BR47: 10.99 | BS47: 10.99 | BT47: 10.99 | BU47: 10.99 | BV47: 10.99 | BW47: 10.99 | BX47: 10.99 | BY47: 10.99 | BZ47: 10.99 | CA47: 10.99 | CB47: 10.99 | CD47: 10.99 | CE47: 10.99 | CF47: 10.99 | CG47: 10.99 | CH47: 10.99 | CI47: 10.99 | CJ47: 10.99 | CK47: 10.99 | CL47: 10.99 | CM47: 10.99 | CN47: 11.99 | CO47: 11.99 | CP47: 11.99 | CQ47: 11.99 | CR47: 11.99 | CS47: 11.99 | CT47: 11.99 | CU47: 11.99 | CV47: 11.99 | CW47: 11.99 | CX47: 11.99 | CY47: 11.99 | CZ47: 11.99 | DA47: 11.99 | DB47: 11.99 | DC47: 11.99 | DD47: 11.99 | DE47: 11.99 | DF47: 11.99 | DG47: 11.99 | DH47: 11.99 | DI47: 11.99 | DJ47: 11.99 | DK47: 11.99 | DL47: 11.99 | DM47: 11.99 | DN47: 11.99 | DO47: 11.99 | DP47: 11.99 | DQ47: 11.99 | DR47: 11.99 | DS47: 11.99 | DT47: 11.99 | DU47: 11.99 | DV47: 11.99 | DW47: 11.99 | DX47: 11.99 | DY47: 11.99 | DZ47: 11.99 | EA47: 11.99 | EB47: 11.99 | EC47: 11.99 | ED47: 11.99 | EE47: 11.99 | EF47: 11.99 | EG47: 11.99 | EH47: 11.99 | EI47: 11.99 | EJ47: 11.99 | EK47: 11.99 | EL47: 11.99 | EM47: 11.99 | EN47: 11.99 | EO47: 11.99 | EP47: 11.99 | EQ47: 11.99 | ER47: 11.99 | ES47: 11.99 | ET47: 11.99 | EU47: 11.99 | EV47: 11.99 | EW47: 11.99 | EX47: 11.99 | EY47: 11.99 | EZ47: 11.99 | FA47: 11.99 | FB47: 11.99 | FC47: 11.99 | FD47: 11.99 | FE47: 11.99 | FF47: 11.99 | FG47: 11.99 | FH47: 11.99 | FI47: 11.99 | FJ47: 11.99 | FK47: 11.99 | FL47: 11.99 | FM47: 11.99 | FN47: 11.99 | FO47: 11.99 | FP47: 11.99 | FQ47: 11.99 | FR47: 11.99 | FS47: 11.99 | FT47: 11.99 | FU47: 11.99 | FV47: 11.99 | FW47: 11.99 | FX47: 11.99 | FY47: 11.99 | FZ47: 11.99 | GA47: 11.99 | GB47: 11.99 | GC47: 11.99 | GD47: 11.99 | GE47: 11.99 | GF47: 11.99 | GG47: 11.99 | GH47: 11.99 | GI47: 11.99 | GJ47: 11.99 | GK47: 11.99 | GL47: 11.99 | GM47: 11.99 | GN47: 11.99 | GO47: 11.99 | GP47: 11.99 | GQ47: 11.99 | GR47: 11.99 | GS47: 11.99 | GT47: 11.99
B48: - INTERNET | C48: =SUM(V48:AG48) -> 457.58 | D48: =SUM(AH48:AS48) -> 277.69 | E48: =SUM(AT48:BE48) -> 191.85 | F48: =SUM(BF48:BQ48) -> 168.89 | G48: =SUM(BR48:CC48) -> 173.88 | H48: =SUM(CD48:CO48) -> 179.88 | I48: =SUM(CP48:DA48) -> 169.87 | K48: =C48/12 -> 38.131667 | L48: =D48/12 -> 23.140833 | M48: =E48/12 -> 15.9875 | N48: =F48/12 -> 14.074167 | O48: =G48/12 -> 14.49 | P48: =H48/12 -> 14.99 | Q48: =I48/12 -> 14.155833 | T48: 81.61 | W48: 87.59 | X48: 87.59 | Z48: 97.6 | AC48: 61.6 | AD48: 61.6 | AF48: 61.6 | AI48: 61.6 | AJ48: 61.6 | AN48: 124.52 | AR48: =19.98+9.99 -> 29.97 | AT48: =9.99+9.99+9.99 -> 29.97 | AU48: =9.99+10 -> 19.99 | AV48: 9.99 | AW48: 9.99 | AX48: 23.98 | AY48: 13.99 | AZ48: 13.99 | BA48: 13.99 | BB48: 13.99 | BC48: 13.99 | BD48: 13.99 | BE48: 13.99 | BF48: 13.99 | BG48: 13.99 | BH48: 13.99 | BI48: 13.99 | BJ48: 13.99 | BK48: 13.99 | BL48: 13.99 | BM48: 13.99 | BN48: 13.99 | BO48: 13.99 | BP48: 13.99 | BQ48: 15 | BR48: 13.99 | BS48: 13.99 | BT48: 13.99 | BU48: 13.99 | BV48: 13.99 | BW48: 13.99 | BX48: 14.99 | BY48: =BX48 -> 14.99 | BZ48: =BY48 -> 14.99 | CA48: =BZ48 -> 14.99 | CB48: =CA48 -> 14.99 | CC48: =CB48 -> 14.99 | CD48: =CC48 -> 14.99 | CE48: =CD48 -> 14.99 | CF48: =CE48 -> 14.99 | ... CQ48: =CP48 -> 14.99 | CR48: =22.98 -> 22.98 | CS48: =12.99 -> 12.99 | CT48: =CS48 -> 12.99 | CU48: =CT48 -> 12.99 | CV48: =CU48 -> 12.99 | CW48: =CV48 -> 12.99 | CX48: =CW48 -> 12.99 | CY48: =CX48 -> 12.99 | CZ48: =CY48 -> 12.99 | DA48: =CZ48 -> 12.99 | ... GT48: =GS48 -> 12.99
B49: TELEFONO | C49: =SUM(V49:AG49) -> 0 | D49: =SUM(AH49:AS49) -> 89.91 | E49: =SUM(AT49:BE49) -> 119.88 | F49: =SUM(BF49:BQ49) -> 119.88 | G49: =SUM(BR49:CC49) -> 119.88 | H49: =SUM(CD49:CO49) -> 119.88 | I49: =SUM(CP49:DA49) -> 119.88 | K49: =C49/12 -> 0 | L49: =D49/12 -> 7.4925 | M49: =E49/12 -> 9.99 | N49: =F49/12 -> 9.99 | O49: =G49/12 -> 9.99 | P49: =H49/12 -> 9.99 | Q49: =I49/12 -> 9.99 | AK49: 9.99 | AL49: 9.99 | AM49: 9.99 | AN49: 9.99 | AO49: 9.99 | AP49: 9.99 | AQ49: 9.99 | AR49: =9.99 -> 9.99 | AS49: 9.99 | AT49: 9.99 | AU49: 9.99 | AV49: 9.99 | AW49: 9.99 | AX49: 9.99 | AY49: 9.99 | AZ49: 9.99 | BA49: 9.99 | BB49: 9.99 | BC49: 9.99 | BD49: 9.99 | BE49: 9.99 | BF49: 9.99 | BG49: 9.99 | BH49: 9.99 | BI49: 9.99 | BJ49: 9.99 | BK49: 9.99 | BL49: 9.99 | BM49: 9.99 | BN49: 9.99 | BO49: 9.99 | BP49: 9.99 | BQ49: 9.99 | BR49: 9.99 | BS49: 9.99 | BT49: 9.99 | BU49: 9.99 | BV49: 9.99 | BW49: 9.99 | BX49: 9.99 | BY49: 9.99 | BZ49: 9.99 | CA49: 9.99 | CB49: 9.99 | CC49: 9.99 | CD49: 9.99 | CE49: 9.99 | CF49: 9.99 | CG49: 9.99 | CH49: 9.99 | CI49: =9.99 -> 9.99 | CJ49: 9.99 | CK49: 9.99 | CL49: 9.99 | CM49: 9.99 | CN49: 9.99 | CO49: 9.99 | CP49: 9.99 | CQ49: 9.99 | CR49: 9.99 | CS49: 9.99 | CT49: 9.99 | CU49: 9.99 | CV49: 9.99 | CW49: 9.99 | CX49: 9.99 | CY49: 9.99 | CZ49: 9.99 | DA49: 9.99 | DB49: 9.99 | DC49: 9.99 | DD49: 9.99 | DE49: 9.99 | DF49: 9.99 | DG49: 9.99 | DH49: 9.99 | DI49: 9.99 | DJ49: 9.99 | DK49: 9.99 | DL49: 9.99 | DM49: 9.99 | DN49: 9.99 | DO49: 9.99 | DP49: 9.99 | DQ49: 9.99 | DR49: 9.99 | DS49: 9.99 | DT49: 9.99 | DU49: 9.99 | DV49: 9.99 | DW49: 9.99 | DX49: 9.99 | DY49: 9.99 | DZ49: 9.99 | EA49: 9.99 | EB49: 9.99 | EC49: 9.99 | ED49: 9.99 | EE49: 9.99 | EF49: 9.99 | EG49: 9.99 | EH49: 9.99 | EI49: 9.99 | EJ49: 9.99 | EK49: 9.99 | EL49: 9.99 | EM49: 9.99 | EN49: 9.99 | EO49: 9.99 | EP49: 9.99 | EQ49: 9.99 | ER49: 9.99 | ES49: 9.99 | ET49: 9.99 | EU49: 9.99 | EV49: 9.99 | EW49: 9.99 | EX49: 9.99 | EY49: 9.99 | EZ49: 9.99 | FA49: 9.99 | FB49: 9.99 | FC49: 9.99 | FD49: 9.99 | FE49: 9.99 | FF49: 9.99 | FG49: 9.99 | FH49: 9.99 | FI49: 9.99 | FJ49: 9.99 | FK49: 9.99 | FL49: 9.99 | FM49: 9.99 | FN49: 9.99 | FO49: 9.99 | FP49: 9.99 | FQ49: 9.99 | FR49: 9.99 | FS49: 9.99 | FT49: 9.99 | FU49: 9.99 | FV49: 9.99 | FW49: 9.99 | FX49: 9.99 | FY49: 9.99 | FZ49: 9.99 | GA49: 9.99 | GB49: 9.99 | GC49: 9.99 | GD49: 9.99 | GE49: 9.99 | GF49: 9.99 | GG49: 9.99 | GH49: 9.99 | GI49: 9.99 | GJ49: 9.99 | GK49: 9.99 | GL49: 9.99 | GM49: 9.99 | GN49: 9.99 | GO49: 9.99 | GP49: 9.99 | GQ49: 9.99 | GR49: 9.99 | GS49: 9.99 | GT49: 9.99
B50: - AMAZON PRIME | C50: =SUM(V50:AG50) -> 36 | D50: =SUM(AH50:AS50) -> 50.97 | E50: =SUM(AT50:BE50) -> 54.89 | F50: =SUM(BF50:BQ50) -> 49.9 | G50: =SUM(BR50:CC50) -> 49.9 | H50: =SUM(CD50:CO50) -> 49.9 | I50: =SUM(CP50:DA50) -> 81.86 | K50: =C50/12 -> 3 | L50: =D50/12 -> 4.2475 | M50: =E50/12 -> 4.5741667 | N50: =F50/12 -> 4.1583333 | O50: =G50/12 -> 4.1583333 | P50: =H50/12 -> 4.1583333 | Q50: =I50/12 -> 6.8216667 | S50: 36 | AE50: 36 | AH50: 4.99 | AI50: 4.99 | AJ50: 4.99 | AQ50: 36 | AV50: =3.99+1 -> 4.99 | BC50: 49.9 | BO50: 49.9 | CA50: 49.9 | CM50: 49.9 | CU50: 7.99 | CV50: 7.99 | CW50: 7.99 | CX50: 7.99 | CY50: 49.9 | DK50: 49.9 | DW50: 36 | EI50: 36
B51: - ABBONAMENTI GENERICI | C51: =SUM(V51:AG51) -> 0 | D51: =SUM(AH51:AS51) -> 1 | E51: =SUM(AT51:BE51) -> 62.99 | F51: =SUM(BF51:BQ51) -> 0 | G51: =SUM(BR51:CC51) -> 0 | H51: =SUM(CD51:CO51) -> 4 | I51: =SUM(CP51:DA51) -> 0 | K51: =C51/12 -> 0 | L51: =D51/12 -> 0.083333333 | M51: =E51/12 -> 5.2491667 | N51: =F51/12 -> 0 | O51: =G51/12 -> 0 | P51: =H51/12 -> 0.33333333 | Q51: =I51/12 -> 0 | AS51: 1 | AT51: 1 | AU51: 1 | AW51: 1 | BB51: 59.99 | CE51: 4
B52: - IMPOSTA DI BOLLO | C52: =SUM(V52:AG52) -> 24 | D52: =SUM(AH52:AS52) -> 24 | E52: =SUM(AT52:BE52) -> 24 | F52: =SUM(BF52:BQ52) -> 24 | G52: =SUM(BR52:CC52) -> 24 | H52: =SUM(CD52:CO52) -> 26 | I52: =SUM(CP52:DA52) -> 24 | K52: =C52/12 -> 2 | L52: =D52/12 -> 2 | M52: =E52/12 -> 2 | N52: =F52/12 -> 2 | O52: =G52/12 -> 2 | P52: =H52/12 -> 2.1666667 | Q52: =I52/12 -> 2 | S52: 2 | T52: 2 | U52: 2 | V52: 2 | W52: 2 | X52: 2 | Y52: 2 | Z52: 2 | AA52: 2 | AB52: 2 | AC52: 2 | AD52: 2 | AE52: 2 | AF52: 2 | AG52: 2 | AH52: 2 | AI52: 2 | AJ52: =2 -> 2 | AK52: 2 | AL52: 2 | AM52: 2 | AN52: 2 | AO52: 2 | AP52: 2 | AQ52: 2 | AR52: 2 | AS52: 2 | AT52: 2 | AU52: 2 | AV52: 2 | AW52: 2 | AX52: 2 | AY52: 2 | AZ52: 2 | BA52: 2 | BB52: 2 | BC52: 2 | BD52: 2 | BE52: 2 | BF52: 2 | BG52: 2 | BH52: 2 | BI52: 2 | BJ52: 2 | BK52: 2 | BL52: 2 | BM52: 2 | BN52: 2 | BO52: 2 | BP52: 2 | BQ52: 2 | BR52: 2 | BS52: 2 | BT52: 2 | BU52: 2 | BV52: 2 | BW52: 2 | BX52: 2 | BY52: 2 | BZ52: 2 | CA52: 2 | CB52: 2 | CC52: 2 | CD52: 2 | CE52: 2 | CF52: 2 | CG52: 2 | CH52: 2 | CI52: 4 | CJ52: 2 | CK52: 2 | CL52: 2 | CM52: 2 | CN52: 2 | CO52: 2 | CP52: 2 | CQ52: 2 | CR52: 2 | CS52: 2 | CT52: 2 | CU52: 2 | CV52: 2 | CW52: 2 | CX52: 2 | CY52: 2 | CZ52: 2 | DA52: 2 | DB52: 2 | DC52: 2 | DD52: 2 | DE52: 2 | DF52: 2 | DG52: 2 | DH52: 2 | DI52: 2 | DJ52: 2 | DK52: 2 | DL52: 2 | DM52: 2 | DN52: 2 | DO52: 2 | DP52: 2 | DQ52: 2 | DR52: 2 | DS52: 2 | DT52: 2 | DU52: 2 | DV52: 2 | DW52: 2 | DX52: 2 | DY52: 2 | DZ52: 2 | EA52: 2 | EB52: 2 | EC52: 2 | ED52: 2 | EE52: 2 | EF52: 2 | EG52: 2 | EH52: 2 | EI52: 2 | EJ52: 2 | EK52: 2 | EL52: 2 | EM52: 2 | EN52: 2 | EO52: 2 | EP52: 2 | EQ52: 2 | ER52: 2 | ES52: 2 | ET52: 2 | EU52: 2 | EV52: 2 | EW52: 2 | EX52: 2 | EY52: 2 | EZ52: 2 | FA52: 2 | FB52: 2 | FC52: 2 | FD52: 2 | FE52: 2 | FF52: 2 | FG52: 2 | FH52: 2 | FI52: 2 | FJ52: 2 | FK52: 2 | FL52: 2 | FM52: 2 | FN52: 2 | FO52: 2 | FP52: 2 | FQ52: 2 | FR52: 2 | FS52: 2 | FT52: 2 | FU52: 2 | FV52: 2 | FW52: 2 | FX52: 2 | FY52: 2 | FZ52: 2 | GA52: 2 | GB52: 2 | GC52: 2 | GD52: 2 | GE52: 2 | GF52: 2 | GG52: 2 | GH52: 2 | GI52: 2 | GJ52: 2 | GK52: 2 | GL52: 2 | GM52: 2 | GN52: 2 | GO52: 2 | GP52: 2 | GQ52: 2 | GR52: 2 | GS52: 2 | GT52: 2
B53: TOTALE SPESE FISSE | C53: =SUM(C41:C52) -> 1099.18 | D53: =SUM(AH53:AS53) -> 1326.04 | E53: =SUM(AT53:BE53) -> 1080.2 | F53: =SUM(BF53:BQ53) -> 865.3 | G53: =SUM(BR53:CC53) -> 1071.21 | H53: =SUM(CD53:CO53) -> 1264.19 | I53: =SUM(CP53:DA53) -> 1112.35 | K53: =SUM(K41:K52) -> 91.598333 | L53: =SUM(L41:L52) -> 110.50333 | M53: =SUM(M41:M52) -> 90.016667 | N53: =SUM(N41:N52) -> 72.108333 | O53: =SUM(O41:O52) -> 90.1 | P53: =SUM(P41:P52) -> 105.34917 | Q53: =SUM(Q41:Q52) -> 92.695833 | S53: =SUM(S41:S52) -> 89.96 | T53: =SUM(T41:T52) -> 135.57 | U53: =SUM(U41:U52) -> 53.96 | V53: =SUM(V41:V52) -> 53.96 | W53: =SUM(W41:W52) -> 201.54 | X53: =SUM(X41:X52) -> 184.57 | Y53: =SUM(Y41:Y52) -> 27.98 | Z53: =SUM(Z41:Z52) -> 142.56 | ... BX53: =SUM(BX41:BX52) -> 80.94 | BY53: =SUM(BY41:BY52)-BY49 -> 80.95 | BZ53: =SUM(BZ41:BZ52) -> 90.94 | CA53: =SUM(CA41:CA52) -> 143.84 | CB53: =SUM(CB41:CB52) -> 93.94 | CC53: =SUM(CC41:CC52) -> 82.95 | CD53: =SUM(CD41:CD52) -> 101.93 | CE53: =SUM(CE41:CE52) -> 112.92 | CF53: =SUM(CF41:CF52) -> 102.93 | CG53: =SUM(CG41:CG52) -> 101.34 | ... GT53: =SUM(GT41:GT52) -> 81.95
B55: SPESE VARIABILI
B56: - ACQUISTI GENERICI | C56: =SUM(V56:AG56) -> 7471 | D56: =SUM(AH56:AS56) -> 7592.53 | E56: =SUM(AT56:BE56) -> 4798.17 | F56: =SUM(BF56:BQ56) -> 7081.88 | G56: =SUM(BR56:CC56) -> 10399.37 | H56: =SUM(CD56:CO56) -> 15772.008 | I56: =SUM(CP56:DA56) -> 16621.274 | K56: =C56/12 -> 622.58333 | L56: =D56/12 -> 632.71083 | M56: =E56/12 -> 399.8475 | N56: =F56/12 -> 590.15667 | O56: =G56/12 -> 866.61417 | P56: =H56/12 -> 1314.334 | Q56: =IFERROR(AVERAGEIF(CP56:DB56,">0"),0) -> 1662.1274 | S56: ='Riepilogo Mensile Spese CC'!J3 -> 375.82 | T56: ='Riepilogo Mensile Spese CC'!K3 -> 277.06 | U56: ='Riepilogo Mensile Spese CC'!L3 -> 415.31 | V56: ='Riepilogo Mensile Spese CC'!M3 -> 1163.94 | W56: ='Riepilogo Mensile Spese CC'!B4 -> 509 | X56: ='Riepilogo Mensile Spese CC'!C4 -> 518.43 | Y56: ='Riepilogo Mensile Spese CC'!D4 -> 904.96 | Z56: ='Riepilogo Mensile Spese CC'!E4 -> 492.42 | AA56: ='Riepilogo Mensile Spese CC'!F4 -> 675.95 | AB56: ='Riepilogo Mensile Spese CC'!G4 -> 464.79 | AC56: ='Riepilogo Mensile Spese CC'!H4 -> 375.6 | AD56: ='Riepilogo Mensile Spese CC'!I4 -> 1297.49 | ... AH56: ='Riepilogo Mensile Spese CC'!M4 -> 966.59 | AI56: ='Riepilogo Mensile Spese CC'!B5 -> 713.45 | AJ56: ='Riepilogo Mensile Spese CC'!C5 -> 641.65 | AK56: ='Riepilogo Mensile Spese CC'!D5 -> 640.23 | AL56: ='Riepilogo Mensile Spese CC'!E5 -> 926.99 | AM56: ='Riepilogo Mensile Spese CC'!F5 -> 1037.97 | AN56: ='Riepilogo Mensile Spese CC'!G5 -> 603.7 | AO56: ='Riepilogo Mensile Spese CC'!H5 -> 739.48 | AP56: ='Riepilogo Mensile Spese CC'!I5 -> 788.58 | ... AT56: ='Riepilogo Mensile Spese CC'!M5 -> 486.01 | AU56: ='Riepilogo Mensile Spese CC'!B6 -> 312.79 | AV56: ='Riepilogo Mensile Spese CC'!C6 -> 619.89 | AW56: ='Riepilogo Mensile Spese CC'!D6 -> 252.27 | AX56: ='Riepilogo Mensile Spese CC'!E6 -> 584.7 | AY56: ='Riepilogo Mensile Spese CC'!F6 -> 450.7 | AZ56: ='Riepilogo Mensile Spese CC'!G6 -> 273.89 | BA56: ='Riepilogo Mensile Spese CC'!H6 -> 366.3 | BB56: ='Riepilogo Mensile Spese CC'!I6 -> 440.42 | ... BF56: ='Riepilogo Mensile Spese CC'!M6 -> 869.98 | BG56: ='Riepilogo Mensile Spese CC'!B7 -> 449.37 | BH56: ='Riepilogo Mensile Spese CC'!C7 -> 335.17 | BI56: ='Riepilogo Mensile Spese CC'!D7 -> 341.64 | BJ56: ='Riepilogo Mensile Spese CC'!E7 -> 370.41 | BK56: ='Riepilogo Mensile Spese CC'!F7 -> 361.88 | BL56: ='Riepilogo Mensile Spese CC'!G7 -> 602.52 | BM56: ='Riepilogo Mensile Spese CC'!H7 -> 606.55 | BN56: ='Riepilogo Mensile Spese CC'!I7 -> 1397.92 | ... BR56: ='Riepilogo Mensile Spese CC'!M7 -> 1156.66 | BS56: ='Riepilogo Mensile Spese CC'!B8 -> 464.88 | BT56: ='Riepilogo Mensile Spese CC'!C8 -> 565.7 | BU56: ='Riepilogo Mensile Spese CC'!D8 -> 485.52 | BV56: ='Riepilogo Mensile Spese CC'!E8 -> 605.47 | BW56: ='Riepilogo Mensile Spese CC'!F8 -> 365 | BX56: ='Riepilogo Mensile Spese CC'!G8 -> 790.89 | BY56: ='Riepilogo Mensile Spese CC'!H8 -> 952.18 | BZ56: ='Riepilogo Mensile Spese CC'!I8 -> 1769.16 | ... CD56: ='Riepilogo Mensile Spese CC'!M8 -> 957.99 | CE56: ='Riepilogo Mensile Spese CC'!B9 -> 638.49 | CF56: ='Riepilogo Mensile Spese CC'!C9 -> 1210.99 | CG56: ='Riepilogo Mensile Spese CC'!D9 -> 872.46 | CH56: ='Riepilogo Mensile Spese CC'!E9 -> 1556.5 | CI56: ='Riepilogo Mensile Spese CC'!F9 -> 944.84 | CJ56: ='Riepilogo Mensile Spese CC'!G9 -> 1242.73 | CK56: ='Riepilogo Mensile Spese CC'!H9 -> 2077.828 | CL56: ='Riepilogo Mensile Spese CC'!I9 -> 1997.5 | ... CP56: ='Riepilogo Mensile Spese CC'!M9 -> 1815.68 | CQ56: ='Riepilogo Mensile Spese CC'!B10 -> 1092.67 | CR56: ='Riepilogo Mensile Spese CC'!C10 -> 1406.408 | CS56: ='Riepilogo Mensile Spese CC'!D10 -> 1307.85 | CT56: ='Riepilogo Mensile Spese CC'!E10 -> 1500.458 | CU56: ='Riepilogo Mensile Spese CC'!F10 -> 1576.948 | CV56: ='Riepilogo Mensile Spese CC'!G10 -> 1606.41 | CW56: ='Riepilogo Mensile Spese CC'!H10 -> 1971.75 | CX56: ='Riepilogo Mensile Spese CC'!I10 -> 2229.02 | ... DB56: ='Riepilogo Mensile Spese CC'!M10 -> 0 | DC56: ='Riepilogo Mensile Spese CC'!B11 -> 0 | DD56: ='Riepilogo Mensile Spese CC'!C11 -> 0 | DE56: ='Riepilogo Mensile Spese CC'!D11 -> 0 | DF56: ='Riepilogo Mensile Spese CC'!E11 -> 0 | DG56: ='Riepilogo Mensile Spese CC'!F11 -> 0 | DH56: ='Riepilogo Mensile Spese CC'!G11 -> 0 | DI56: ='Riepilogo Mensile Spese CC'!H11 -> 0 | DJ56: ='Riepilogo Mensile Spese CC'!I11 -> 0 | ... DN56: ='Riepilogo Mensile Spese CC'!M11 -> 0 | DO56: ='Riepilogo Mensile Spese CC'!B12 -> 0 | DP56: ='Riepilogo Mensile Spese CC'!C12 -> 0 | DQ56: ='Riepilogo Mensile Spese CC'!D12 -> 0 | DR56: ='Riepilogo Mensile Spese CC'!E12 -> 0 | DS56: ='Riepilogo Mensile Spese CC'!F12 -> 0 | DT56: ='Riepilogo Mensile Spese CC'!G12 -> 0 | DU56: ='Riepilogo Mensile Spese CC'!H12 -> 0 | DV56: ='Riepilogo Mensile Spese CC'!I12 -> 0 | ... DZ56: ='Riepilogo Mensile Spese CC'!M12 -> 0 | EA56: ='Riepilogo Mensile Spese CC'!B13 -> 0 | EB56: ='Riepilogo Mensile Spese CC'!C13 -> 0 | EC56: ='Riepilogo Mensile Spese CC'!D13 -> 0 | ED56: ='Riepilogo Mensile Spese CC'!E13 -> 0 | EE56: ='Riepilogo Mensile Spese CC'!F13 -> 0 | EF56: ='Riepilogo Mensile Spese CC'!G13 -> 0 | EG56: ='Riepilogo Mensile Spese CC'!H13 -> 0 | EH56: ='Riepilogo Mensile Spese CC'!I13 -> 0 | ... EL56: ='Riepilogo Mensile Spese CC'!M13 -> 0 | EM56: ='Riepilogo Mensile Spese CC'!B14 -> 0 | EN56: ='Riepilogo Mensile Spese CC'!C14 -> 0 | EO56: ='Riepilogo Mensile Spese CC'!D14 -> 0 | EP56: ='Riepilogo Mensile Spese CC'!E14 -> 0 | EQ56: ='Riepilogo Mensile Spese CC'!F14 -> 0 | ER56: ='Riepilogo Mensile Spese CC'!G14 -> 0 | ES56: ='Riepilogo Mensile Spese CC'!H14 -> 0 | ET56: ='Riepilogo Mensile Spese CC'!I14 -> 0 | ... EX56: ='Riepilogo Mensile Spese CC'!M14 -> 0 | EY56: ='Riepilogo Mensile Spese CC'!B15 -> 0 | EZ56: ='Riepilogo Mensile Spese CC'!C15 -> 0 | FA56: ='Riepilogo Mensile Spese CC'!D15 -> 0 | FB56: ='Riepilogo Mensile Spese CC'!E15 -> 0 | FC56: ='Riepilogo Mensile Spese CC'!F15 -> 0 | FD56: ='Riepilogo Mensile Spese CC'!G15 -> 0 | FE56: ='Riepilogo Mensile Spese CC'!H15 -> 0 | FF56: ='Riepilogo Mensile Spese CC'!I15 -> 0 | ... FJ56: ='Riepilogo Mensile Spese CC'!M15 -> 0 | FK56: ='Riepilogo Mensile Spese CC'!B16 -> 0 | FL56: ='Riepilogo Mensile Spese CC'!C16 -> 0 | FM56: ='Riepilogo Mensile Spese CC'!D16 -> 0 | FN56: ='Riepilogo Mensile Spese CC'!E16 -> 0 | FO56: ='Riepilogo Mensile Spese CC'!F16 -> 0 | FP56: ='Riepilogo Mensile Spese CC'!G16 -> 0 | FQ56: ='Riepilogo Mensile Spese CC'!H16 -> 0 | FR56: ='Riepilogo Mensile Spese CC'!I16 -> 0 | ... FV56: ='Riepilogo Mensile Spese CC'!M16 -> 0 | FW56: ='Riepilogo Mensile Spese CC'!B17 -> 0 | FX56: ='Riepilogo Mensile Spese CC'!C17 -> 0 | FY56: ='Riepilogo Mensile Spese CC'!D17 -> 0 | FZ56: ='Riepilogo Mensile Spese CC'!E17 -> 0 | GA56: ='Riepilogo Mensile Spese CC'!F17 -> 0 | GB56: ='Riepilogo Mensile Spese CC'!G17 -> 0 | GC56: ='Riepilogo Mensile Spese CC'!H17 -> 0 | GD56: ='Riepilogo Mensile Spese CC'!I17 -> 0 | ... GH56: ='Riepilogo Mensile Spese CC'!M17 -> 0 | GI56: ='Riepilogo Mensile Spese CC'!B18 -> 0 | GJ56: ='Riepilogo Mensile Spese CC'!C18 -> 0 | GK56: ='Riepilogo Mensile Spese CC'!D18 -> 0 | GL56: ='Riepilogo Mensile Spese CC'!E18 -> 0 | GM56: ='Riepilogo Mensile Spese CC'!F18 -> 0 | GN56: ='Riepilogo Mensile Spese CC'!G18 -> 0 | GO56: ='Riepilogo Mensile Spese CC'!H18 -> 0 | GP56: ='Riepilogo Mensile Spese CC'!I18 -> 0 | ... GT56: ='Riepilogo Mensile Spese CC'!M18 -> 0
B57: - RICARICHE TELEFONICHE | C57: =SUM(V57:AG57) -> 340 | D57: =SUM(AH57:AS57) -> 109.98 | E57: =SUM(AT57:BE57) -> 10 | F57: =SUM(BF57:BQ57) -> 0 | G57: =SUM(BR57:CC57) -> 10 | H57: =SUM(CD57:CO57) -> 10 | I57: =SUM(CP57:DA57) -> 0 | K57: =C57/12 -> 28.333333 | L57: =D57/12 -> 9.165 | M57: =E57/12 -> 0.83333333 | N57: =F57/12 -> 0 | O57: =G57/12 -> 0.83333333 | P57: =H57/12 -> 0.83333333 | Q57: =IFERROR(AVERAGEIF(CQ57:DB57,">0"),0) -> 0 | S57: 30 | T57: =30 -> 30 | U57: =10+30+30 -> 70 | V57: 30 | W57: 30 | X57: 30 | Z57: 60 | AB57: 30 | AC57: =30+30 -> 60 | AE57: 50 | AF57: 50 | AH57: 30 | AI57: 30 | AJ57: =30+19.98 -> 49.98 | AU57: =10 -> 10 | BY57: 10 | CI57: 10
B58: - PRELIEVO CONTANTI | C58: =SUM(V58:AG58) -> 2770 | D58: =SUM(AH58:AS58) -> 2984.91 | E58: =SUM(AT58:BE58) -> 4621.79 | F58: =SUM(BF58:BQ58) -> 4550 | G58: =SUM(BR58:CC58) -> 3532.9 | H58: =SUM(CD58:CO58) -> 1280 | I58: =SUM(CP58:DA58) -> 80 | K58: =C58/12 -> 230.83333 | L58: =D58/12 -> 248.7425 | M58: =E58/12 -> 385.14917 | N58: =F58/12 -> 379.16667 | O58: =G58/12 -> 294.40833 | P58: =H58/12 -> 106.66667 | Q58: =IFERROR(AVERAGEIF(CQ58:DB58,">0"),0) -> 80 | S58: =200+70+70 -> 340 | T58: =80+70+100+70+70+100 -> 490 | U58: =100+200+100 -> 400 | V58: =90+150 -> 240 | W58: =120+100 -> 220 | X58: =100+100+100 -> 300 | AA58: 150 | AB58: =100+100 -> 200 | AC58: =100+100 -> 200 | AD58: =70+70+100+100 -> 340 | AE58: =100+100+150 -> 350 | AF58: =140+100+100 -> 340 | AG58: =290+70+70 -> 430 | AH58: 150 | AI58: 100 | AJ58: =70+250+70 -> 390 | AM58: 70 | AN58: =60+70+100+70+50 -> 350 | AO58: =250+250+40 -> 540 | AP58: 250 | AQ58: =50+50+50+50+60 -> 260 | AR58: =50+100+100+80+60+40 -> 430 | AS58: =60+80+24.91+50+80+100+50 -> 444.91 | AT58: =50+100+60+180+60 -> 450 | AU58: =60+60+60+60+40+40+80 -> 400 | AV58: =60+40+50+100 -> 250 | AW58: =17.84+50+60+40+60+100+60 -> 387.84 | AX58: =40 -> 40 | AY58: =40+40+60+60+40 -> 240 | AZ58: =60+60+70+40+70+103.95+50+80 -> 533.95 | BA58: =40+100+40+50+60+60+40+40 -> 430 | BB58: =90+60+60+120+80 -> 410 | BC58: =40+100+100+100+70+60+40 -> 510 | BD58: =60+60+80+60+60+40+60 -> 420 | BE58: =40+80+40+40+50+60+60+100+40+40 -> 550 | BF58: =40+60 -> 100 | BG58: =40+40+60+40+40+60 -> 280 | BH58: =60+70+100+40+60+80+40 -> 450 | BI58: =100+190+60+50+60 -> 460 | BJ58: =60+60+60+90+60+60+60+60 -> 510 | BK58: =150+80+100+40+60+60+60+40+40 -> 630 | BL58: =60+100+40+60 -> 260 | BM58: =40+80+50+60+60 -> 290 | BN58: =100+80+60+60+60+70+80+60 -> 570 | BO58: =100+60+60+60+60 -> 340 | BP58: =60+70+60+60 -> 250 | BQ58: =80+70+60+60+60+40+40 -> 410 | BR58: =60+100+80+80+100+60 -> 480 | BS58: =40+40+60 -> 140 | BT58: =60+100+100+70 -> 330 | BU58: =80+70+40 -> 190 | BV58: =60+60+120 -> 240 | BW58: =60+80+60+80+80+202.9 -> 562.9 | BX58: =200+70+60+60 -> 390 | BY58: =120+60+40+40+40 -> 300 | BZ58: =40+60+70+60+60+60+60 -> 410 | CA58: =80+70+60+40 -> 250 | CB58: =60+60+60 -> 180 | CC58: 60 | CD58: =60+60+60 -> 180 | CE58: 60 | CF58: =60+80 -> 140 | CG58: 60 | CI58: =60+60 -> 120 | CJ58: =80+100 -> 180 | CK58: =60+40 -> 100 | CL58: =150+60 -> 210 | CM58: =80+150 -> 230 | CX58: 80
B59: - COMMISSIONI PRELIEVO | C59: =SUM(V59:AG59) -> 106.8 | D59: =SUM(AH59:AS59) -> 121.97 | E59: =SUM(AT59:BE59) -> 197.45 | F59: =SUM(BF59:BQ59) -> 188.72 | G59: =SUM(BR59:CC59) -> 145.07 | H59: =SUM(CD59:CO59) -> 51.67 | I59: =SUM(CP59:DA59) -> 3.2 | K59: =C59/12 -> 8.9 | L59: =D59/12 -> 10.164167 | M59: =E59/12 -> 16.454167 | N59: =F59/12 -> 15.726667 | O59: =G59/12 -> 12.089167 | P59: =H59/12 -> 4.3058333 | Q59: =IFERROR(AVERAGEIF(CQ59:DB59,">0"),0) -> 3.2 | S59: =8+2.8+2.8 -> 13.6 | T59: =3.2+2.8+4+2.8+4+2.8 -> 19.6 | U59: =4+8+4 -> 16 | V59: =3.6+6 -> 9.6 | W59: =4.8+4 -> 8.8 | X59: =4+4 -> 8 | AA59: 6 | AB59: =4+4 -> 8 | AC59: =4+4 -> 8 | AD59: =2.8+2.8+4+4 -> 13.6 | AE59: =4+4+6 -> 14 | AF59: =5.6+4+4 -> 13.6 | AG59: =2.8+11.6+2.8 -> 17.2 | AH59: 6 | AI59: 4 | AJ59: =2.8+10+2.8 -> 15.6 | AM59: 2.8 | AN59: =2.4+2.8+4+2.8+2.07 -> 14.07 | AO59: =10+10+2.07 -> 22.07 | AP59: 10 | AQ59: =2.07+2.07+2.07+2.07+2.4 -> 10.68 | AR59: =2.07+4+4+3.2+2.4+2.07 -> 17.74 | AS59: =2.4+3.2+2.07+2.07+3.2+4+2.07 -> 19.01 | AT59: =2.07+4+2.4+7.2+2.4 -> 18.07 | AU59: =2.4+2.4+2.4+2.4+2.07+2.07+2.07+2.07 -> 17.88 | AV59: =2.4+2.07+2.07+4 -> 10.54 | AW59: =2.07+2.07+2.4+2.07+2.4+4+2.4 -> 17.41 | AX59: 2.07 | AY59: =2.07+2.07+2.4+2.4+2.07 -> 11.01 | AZ59: =2.4+2.4+2.8+2.07+2.8+4.15+2.07+3.2 -> 21.89 | BA59: =2.07+4+2.07+2.07+2.4+2.4+2.07+2.07 -> 19.15 | BB59: =3.6+2.4+2.4+4.8+3.2 -> 16.4 | BC59: =2.07+4+4+4+2.8+2.4+2.07 -> 21.34 | BD59: =2.4+2.4+3.2+2.4+2.4+2.07+2.4 -> 17.27 | BE59: =2.07+3.2+2.07+2.07+2.07+2.4+2.4+4+2.07+2.07 -> 24.42 | BF59: =2.07+2.4 -> 4.47 | BG59: =2.07+2.07+2.4+2.07+2.07+2.4 -> 13.08 | BH59: =2.4+2.8+4+2.07+2.4+3.2+2.07 -> 18.94 | BI59: =4+7.6+2.4+2.07+2.4 -> 18.47 | BJ59: =2.4+2.4+2.4+3.6+2.4+2.4+2.4+2.4 -> 20.4 | BK59: =6+4+3.2+2.07+2.4+2.4+2.4+2.07+2.07 -> 26.61 | BL59: =2.4+4+2.07+2.4 -> 10.87 | BM59: =2.07+3.2+2.07+2.4+2.4 -> 12.14 | BN59: =4+3.2+2.4+2.4+2.4+2.8+3.2+2.4 -> 22.8 | BO59: =4+2.4+2.4+2.4+2.4 -> 13.6 | BP59: =2.4+2.8+2.4+2.4 -> 10 | BQ59: =3.2+2.8+2.4+2.4+2.4+2.07+2.07 -> 17.34 | BR59: =2.4+4+3.2+3.2+4+2.4 -> 19.2 | BS59: =2.07+2.07+2.4 -> 6.54 | BT59: =2.4+4+4+2.8 -> 13.2 | BU59: =3.2+2.8+2.07 -> 8.07 | BV59: =2.4+2.4+4.8 -> 9.6 | BW59: =2.4+3.2+2.4+3.2+3.2+8.11 -> 22.51 | BX59: =8+2.8+2.4+2.4 -> 15.6 | BY59: =4.8+2.4+2.07+2.07+2.07 -> 13.41 | BZ59: =2.07+2.4+2.8+2.4+2.4+2.4+2.4 -> 16.87 | CA59: =3.2+2.8+2.4+2.07 -> 10.47 | CB59: =2.4+2.4+2.4 -> 7.2 | CC59: 2.4 | CD59: =2.4+2.4+2.4 -> 7.2 | CE59: 2.4 | CF59: =2.4+3.2 -> 5.6 | CG59: 2.4 | CI59: =2.4+2.4 -> 4.8 | CJ59: =3.2+4 -> 7.2 | CK59: =2.4+2.07 -> 4.47 | CL59: =6+2.4 -> 8.4 | CM59: =3.2+6 -> 9.2 | CX59: 3.2
B60: - RIFORNIMENTI | C60: =SUM(V60:AG60) -> 1510.27 | D60: =SUM(AH60:AS60) -> 1486 | E60: =SUM(AT60:BE60) -> 2269.03 | F60: =SUM(BF60:BQ60) -> 2299.26 | G60: =SUM(BR60:CC60) -> 1240.36 | H60: =SUM(CD60:CO60) -> 25 | I60: =SUM(CP60:DA60) -> 229.6 | K60: =C60/12 -> 125.85583 | L60: =D60/12 -> 123.83333 | M60: =E60/12 -> 189.08583 | N60: =F60/12 -> 191.605 | O60: =G60/12 -> 103.36333 | P60: =H60/12 -> 2.0833333 | Q60: =IFERROR(AVERAGEIF(CQ60:DB60,">0"),0) -> 114.8 | S60: =69.3+25 -> 94.3 | T60: =72.03+25+25 -> 122.03 | U60: =30.35+57.16+25.12+25+25 -> 162.63 | V60: =25.02+63.48+65.38+30.02+30.03 -> 213.93 | W60: =70.03+63.01+25+25.02+64.51 -> 247.57 | X60: =70.79+68.47 -> 139.26 | Y60: =25.02+25 -> 50.02 | AB60: =56.39+66+30 -> 152.39 | AC60: =42.45+30+46.47 -> 118.92 | AD60: =25+25.13+47.45+56+73.31 -> 226.89 | AE60: =35.5+54+25 -> 114.5 | AF60: =59.39+25+25+62.38 -> 171.77 | AG60: =25.02+30+20 -> 75.02 | AH60: =37.01+30.02+30 -> 97.03 | AI60: =30.02+25+30.13+30 -> 115.15 | AJ60: =35+30.01+30.01 -> 95.02 | AK60: =30+30+30.01 -> 90.01 | AL60: =30.01+30.01+35.03 -> 95.05 | AM60: =35.04+30 -> 65.04 | AN60: =30.01+35 -> 65.01 | AO60: =30+40.01+72.35+71.12 -> 213.48 | AP60: =15+69 -> 84 | AQ60: =74.39+65+64.79 -> 204.18 | AR60: =75.41+77.01+62.03 -> 214.45 | AS60: =17.52+25.03+35.02+35.01+35 -> 147.58 | AT60: =35+35.01+35.02+30+35 -> 170.03 | AU60: =30+35+30+35.03+70.45 -> 200.48 | AV60: =35.01+35+35.05+35.01+30.01 -> 170.08 | AW60: =13+75+96.93+35.01 -> 219.94 | AX60: =35+25.01+36.58+79.47+15.01+30+85 -> 306.07 | AY60: =40.05+50.01+40.01+35.01+35.01+35+30.01 -> 265.1 | AZ60: =25.01+30+30+25.01+86.99+20+25+30.01+25 -> 297.02 | BA60: =25+30.1+25.01+25.01+25.01+25.01+25+25 -> 205.14 | BB60: =25.01+25.02+25+25.05 -> 100.08 | BC60: =25+15+40+50+60.01+15.06 -> 205.07 | BE60: =40+60.01+30.01 -> 130.02 | BF60: =40+40+60 -> 140 | BG60: =60.04+40+63.89 -> 163.93 | BH60: =55+51+58.9+55.02 -> 219.92 | BI60: =60.01+55+60.01 -> 175.02 | BJ60: =65.02+60+58+20 -> 203.02 | BK60: =60.02+60.01+50.01+40.01 -> 210.05 | BL60: 60 | BM60: =60.01+60+60.04 -> 180.05 | BN60: =60.02+25.01+25.01+90.01+92 -> 292.05 | BO60: =15.01+70+70.08+70 -> 225.09 | BP60: =75.05+65+20+20 -> 180.05 | BQ60: =30+60.08+60+40+30+30 -> 250.08 | BR60: =60+60+30+25 -> 175 | BS60: =25+30+50+65.01 -> 170.01 | BT60: =65.01+5.01+15.25+60.01+60.01 -> 205.29 | BU60: =65+65.02+65 -> 195.02 | BV60: =35+40.01+60+30+30 -> 195.01 | BW60: =45+45.01+40+40+40.02+50 -> 260.03 | BX60: =40 -> 40 | CL60: 25 | CT60: =61.03+60.03 -> 121.06 | CU60: =15.02+93.52 -> 108.54
B61: - COMMISSIONI RIFORNIMENTI | C61: =SUM(V61:AG61) -> 13.29 | D61: =SUM(AH61:AS61) -> 17.36 | E61: =SUM(AT61:BE61) -> 33.48 | F61: =SUM(BF61:BQ61) -> 15.5 | G61: =SUM(BR61:CC61) -> 12.4 | H61: =SUM(CD61:CO61) -> 1.86 | I61: =SUM(CP61:DA61) -> 2.48 | K61: =C61/12 -> 1.1075 | L61: =D61/12 -> 1.4466667 | M61: =E61/12 -> 2.79 | N61: =F61/12 -> 1.2916667 | O61: =G61/12 -> 1.0333333 | P61: =H61/12 -> 0.155 | Q61: =IFERROR(AVERAGEIF(CQ61:DB61,">0"),0) -> 1.24 | S61: =0.62 -> 0.62 | T61: =0.62+0.62 -> 1.24 | U61: =0.62+0.62+0.62+0.62 -> 2.48 | V61: =0.62+0.62+0.62 -> 1.86 | W61: =0.62+0.62 -> 1.24 | X61: 1.51 | Y61: =0.62+0.62 -> 1.24 | AB61: =0.62+0.62+0.62 -> 1.86 | AC61: 0.62 | AD61: =0.62+0.62 -> 1.24 | AE61: 0.62 | AF61: =0.62+0.62 -> 1.24 | AG61: =0.62+0.62+0.62 -> 1.86 | AH61: =0.62+0.62+0.62 -> 1.86 | AI61: =0.62+0.62+0.62+0.62 -> 2.48 | AJ61: =0.62+0.62+0.62 -> 1.86 | AK61: =0.62+0.62+0.62 -> 1.86 | AL61: =0.62+0.62+0.62 -> 1.86 | AM61: =0.62+0.62 -> 1.24 | AN61: =0.62+0.62 -> 1.24 | AO61: =0.62+0.62 -> 1.24 | AP61: 0.62 | AS61: =0.62+0.62+0.62+0.62+0.62 -> 3.1 | AT61: =0.62+0.62+0.62+0.62+0.62 -> 3.1 | AU61: =0.62+0.62+0.62 -> 1.86 | AV61: =0.62+0.62+0.62+0.62+0.62 -> 3.1 | AW61: 0.62 | AX61: =0.62+0.62+0.62+0.62 -> 2.48 | AY61: =0.62+0.62+0.62+0.62+0.62+0.62+0.62 -> 4.34 | AZ61: =0.62+0.62+0.62+0.62+0.62+0.62+0.62+0.62 -> 4.96 | BA61: =0.62+0.62+0.62+0.62+0.62+0.62+0.62+0.62 -> 4.96 | BB61: =0.62+0.62+0.62+0.62 -> 2.48 | BC61: =0.62+0.62+0.62+0.62+0.62+0.62 -> 3.72 | BE61: =0.62+0.62+0.62 -> 1.86 | BF61: =0.62+0.62+0.62 -> 1.86 | BG61: =0.62 -> 0.62 | BH61: 0 | BJ61: 0.62 | BK61: =0.62+0.62+0.62 -> 1.86 | BL61: 0.62 | BM61: =0.62+0.62+0.62 -> 1.86 | BN61: =0.62+0.62+0.62+0.62 -> 2.48 | BO61: 0.62 | BP61: =0.62+0.62 -> 1.24 | BQ61: =0.62+0.62+0.62+0.62+0.62+0.62 -> 3.72 | BR61: =0.62+0.62+0.62+0.62 -> 2.48 | BS61: =0.62+0.62+0.62 -> 1.86 | BT61: =0.62+0.62 -> 1.24 | BV61: =0.62+0.62+0.62+0.62 -> 2.48 | BW61: =0.62+0.62+0.62+0.62+0.62+0.62 -> 3.72 | BX61: =0.62 -> 0.62 | CL61: =0.62+0.62+0.62 -> 1.86 | CT61: =0.62+0.62 -> 1.24 | CU61: =0.62+0.62 -> 1.24
B62: TOTALE SPESE VARIABILI | C62: =SUM(V62:AG62) -> 12211.36 | D62: =SUM(AH62:AS62) -> 12312.75 | E62: =SUM(AT62:BE62) -> 11929.92 | F62: =SUM(BF62:BQ62) -> 14135.36 | G62: =SUM(BR62:CC62) -> 15340.1 | H62: =SUM(CD62:CO62) -> 17140.538 | I62: =SUM(CP62:DA62) -> 16936.554 | K62: =SUM(K56:K61) -> 1017.6133 | L62: =SUM(L56:L61) -> 1026.0625 | M62: =SUM(M56:M61) -> 994.16 | N62: =SUM(N56:N61) -> 1177.9467 | O62: =SUM(O56:O61) -> 1278.3417 | P62: =SUM(P56:P61) -> 1428.3782 | Q62: =IFERROR(AVERAGEIF(CQ62:DB62,">0"),0) -> 1680.0971 | S62: =SUM(S56:S61) -> 854.34 | T62: =SUM(T56:T61) -> 939.93 | U62: =SUM(U56:U61) -> 1066.42 | V62: =SUM(V56:V61) -> 1659.33 | W62: =SUM(W56:W61) -> 1016.61 | X62: =SUM(X56:X61) -> 997.2 | Y62: =SUM(Y56:Y61) -> 956.22 | Z62: =SUM(Z56:Z61) -> 552.42 | ... GT62: =SUM(GT56:GT61) -> 0
B63: +ENTRATE STRAORDINARIE | C63: =SUM(V63:AG63) -> 369.27 | D63: =SUM(AH63:AS63) -> 5 | E63: =SUM(AT63:BE63) -> 224.89 | F63: =SUM(BF63:BQ63) -> 0 | G63: =SUM(BR63:CC63) -> 648.18 | H63: =SUM(CD63:CO63) -> 313.72 | I63: =SUM(CP63:DA63) -> 71.84 | K63: =C63/12 -> 30.7725 | L63: =D63/12 -> 0.41666667 | M63: =E63/12 -> 18.740833 | N63: =F63/12 -> 0 | O63: =G63/12 -> 54.015 | P63: =H63/12 -> 26.143333 | Q63: =I63/12 -> 5.9866667 | S63: 19.3 | W63: 343.29 | AA63: 15.99 | AB63: 9.99 | AH63: 5 | AT63: 208.89 | BA63: 16 | BR63: 10 | BZ63: 607.21 | CC63: =30+0.97 -> 30.97 | CD63: =3.58+9.99+17.99+13.01 -> 44.57 | CE63: 6.99 | CH63: =46.99+17.99+19.95+27.53+61.68+6.04 -> 180.18 | CM63: =6.99+16.66+12.73+4.99+8.63 -> 50 | CN63: 20 | CO63: =6.99+4.99 -> 11.98 | CQ63: 5 | CR63: =5+0.85+8 -> 13.85 | CS63: =29.99+6.99+8 -> 44.98 | CT63: 1.01 | CY63: 7
B64: MEDIA SPESE CARTA DI CREDITO | C64: =AVERAGE(V64:AG64) -> 1078.4392 | D64: =AVERAGE(AH64:AS64) -> 1136.1492 | E64: =AVERAGE(AT64:BE64) -> 1065.4358 | F64: =IFERROR(AVERAGE(BF64:BQ64),B67) -> 1250.055 | G64: =IFERROR(AVERAGE(BR64:CC64),D65) -> 1313.5942 | H64: =IFERROR(AVERAGEIF(CD64:CO64,">0"),D65) -> 1507.584 | I64: =IFERROR(AVERAGEIF(CP64:DA64,">0"),E65) -> 1781.3164 | K64: =C64/12 -> 89.869931 | L64: =D64/12 -> 94.679097 | M64: =E64/12 -> 88.786319 | N64: =F64/12 -> 104.17125 | O64: =G64/12 -> 109.46618 | P64: =H64/12 -> 125.632 | Q64: =I64/12 -> 148.44303 | S64: =IF(S62>0,S53+S62-S63,"") -> 925 | T64: =IF(T62>0,T53+T62-T63,"") -> 1075.5 | U64: =IF(U62>0,U53+U62-U63,"") -> 1120.38 | V64: =IF(V62>0,V53+V62-V63,"") -> 1713.29 | W64: =IF(W62>0,W53+W62-W63,"") -> 874.86 | X64: =IF(X62>0,X53+X62-X63,"") -> 1181.77 | Y64: =IF(Y62>0,Y53+Y62-Y63,"") -> 984.2 | Z64: =IF(Z62>0,Z53+Z62-Z63,"") -> 694.98 | ... CE64: =IF(CE62>0,CE53+CE62-CE63,"") -> 806.82 | CF64: =IF(CF62>0,CF53+CF62-CF63,0) -> 1459.52 | CG64: =IF(CG62>0,CG53+CG62-CG63,0) -> 1036.2 | CH64: =IF(CH62>0,CH53+CH62-CH63,0) -> 1525.91 | CI64: =IF(CI62>0,CI53+CI62-CI63,0) -> 1184.57 | CJ64: =IF(CJ62>0,CJ53+CJ62-CJ63,0) -> 1531.86 | CK64: =IF(CK62>0,CK53+CK62-CK63,0) -> 2275.238 | CL64: =IF(CL62>0,CL53+CL62-CL63,0) -> 2335.7 | CM64: =IF(CM62>0,CM53+CM62-CM63,0) -> 1310.62 | ... GT64: =IF(GT62>0,GT53+GT62-GT63,0) -> 0
B65: simulazione consumo carta di credito | D65: =IF(B67<>"",B67,B71) -> 1100 | T65: =IFERROR((T64-S64)/S64,"") -> 0.1627027 | U65: =IFERROR((U64-T64)/T64,"") -> 0.041729428 | V65: =IFERROR((V64-U64)/U64,"") -> 0.52920438 | W65: =IFERROR((W64-$C$64)/$C$64,"") -> -0.18877204 | X65: =IFERROR((X64-$C$64)/$C$64,"") -> 0.095815171 | Y65: =IFERROR((Y64-$C$64)/$C$64,"") -> -0.087384778 | Z65: =IFERROR((Z64-$C$64)/$C$64,"") -> -0.35556866 | AA65: =IFERROR((AA64-$C$64)/$C$64,"") -> -0.21096152 | AB65: =IFERROR((AB64-$C$64)/$C$64,"") -> -0.18861441 | AC65: =IFERROR((AC64-$C$64)/$C$64,"") -> -0.20282013 | AD65: =IFERROR((AD64-$C$64)/$C$64,"") -> 0.83208294 | ... AH65: =IFERROR((AH64-$C$64)/$C$64,"") -> 0.25775291 | AI65: =IFERROR((AI64-$B$71)/$B$71,"") -> -0.06618257 | AJ65: =IFERROR((AJ64-$B$71)/$B$71,"") -> 0.2106244 | AK65: =IFERROR((AK64-$B$71)/$B$71,"") -> -0.30211362 | AL65: =IFERROR((AL64-$B$71)/$B$71,"") -> -0.061777691 | AM65: =IFERROR((AM64-$B$71)/$B$71,"") -> 0.05058891 | AN65: =IFERROR((AN64-$B$71)/$B$71,"") -> 0.026539285 | AO65: =IFERROR((AO64-$B$71)/$B$71,"") -> 0.3284085 | AP65: =IFERROR((AP64-$B$71)/$B$71,"") -> 0.013586241 | ... EQ65: =IFERROR((EQ64-$B$71)/$B$71,"") -> -1
S66: =S39 -> 43718 | T66: =T39 -> 43748 | U66: =U39 -> 43779 | V66: =V39 -> 43809 | W66: =W39 -> 43840 | X66: =X39 -> 43871 | Y66: =Y39 -> 43900 | Z66: =Z39 -> 43931 | ... EQ66: =EQ39 -> 47604
B67: 1100
B68: 0 | S68: =S9 -> 43739 | T68: =T9 -> 43770 | U68: =U9 -> 43800 | V68: =V9 -> 43831 | W68: =W9 -> 43862 | X68: =X9 -> 43891 | Y68: =Y9 -> 43922 | Z68: =Z9 -> 43952 | ... GT68: =GT9 -> 49310
B69: =B67*(1+B68) -> 1100 | I69: ENTRATE | S69: =IF(_xlfn.NUMBERVALUE($B$2)>=_xlfn.NUMBERVALUE(S$9),S11+S30,"") -> 2158 | T69: =IF(_xlfn.NUMBERVALUE($B$2)>=_xlfn.NUMBERVALUE(T$9),T11+T30,"") -> 2222 | U69: =IF(_xlfn.NUMBERVALUE($B$2)>=_xlfn.NUMBERVALUE(U$9),U11+U30,"") -> 5996.87 | V69: =IF(_xlfn.NUMBERVALUE($B$2)>=_xlfn.NUMBERVALUE(V$9),V11+V30,"") -> 2741 | W69: =IF(_xlfn.NUMBERVALUE($B$2)>=_xlfn.NUMBERVALUE(W$9),W11+W30,"") -> 2346 | X69: =IF(_xlfn.NUMBERVALUE($B$2)>=_xlfn.NUMBERVALUE(X$9),X11+X30,"") -> 2175 | Y69: =IF(_xlfn.NUMBERVALUE($B$2)>=_xlfn.NUMBERVALUE(Y$9),Y11+Y30,"") -> 2158 | Z69: =IF(_xlfn.NUMBERVALUE($B$2)>=_xlfn.NUMBERVALUE(Z$9),Z11+Z30,"") -> 2337 | ... GT69: =IF(_xlfn.NUMBERVALUE($B$2)>=_xlfn.NUMBERVALUE(GT$9),GT11+GT30,"")
B70: media calcolata | I70: USCITE | S70: =IF(_xlfn.NUMBERVALUE($B$2)>=_xlfn.NUMBERVALUE(S$9),S31+S27,"") -> 1701.93 | T70: =IF(_xlfn.NUMBERVALUE($B$2)>=_xlfn.NUMBERVALUE(T$9),T31+T27,"") -> 1877.43 | U70: =IF(_xlfn.NUMBERVALUE($B$2)>=_xlfn.NUMBERVALUE(U$9),U31+U27,"") -> 2640.19 | V70: =IF(_xlfn.NUMBERVALUE($B$2)>=_xlfn.NUMBERVALUE(V$9),V31+V27,"") -> 2752.11 | W70: =IF(_xlfn.NUMBERVALUE($B$2)>=_xlfn.NUMBERVALUE(W$9),W31+W27,"") -> 2343.79 | X70: =IF(_xlfn.NUMBERVALUE($B$2)>=_xlfn.NUMBERVALUE(X$9),X31+X27,"") -> 2200.93 | Y70: =IF(_xlfn.NUMBERVALUE($B$2)>=_xlfn.NUMBERVALUE(Y$9),Y31+Y27,"") -> 1801.13 | Z70: =IF(_xlfn.NUMBERVALUE($B$2)>=_xlfn.NUMBERVALUE(Z$9),Z31+Z27,"") -> 1794 | ... GT70: =IF(_xlfn.NUMBERVALUE($B$2)>=_xlfn.NUMBERVALUE(GT$9),GT31+GT27,"")
B71: =AVERAGEIF(S31:GT31,">0") -> 1185.0496 | I71: MARGINE | S71: =IF(_xlfn.NUMBERVALUE($B$2)>=_xlfn.NUMBERVALUE(S$9),S69-S70,"") -> 456.07 | T71: =IF(_xlfn.NUMBERVALUE($B$2)>=_xlfn.NUMBERVALUE(T$9),T69-T70,"") -> 344.57 | U71: =IF(_xlfn.NUMBERVALUE($B$2)>=_xlfn.NUMBERVALUE(U$9),U69-U70,"") -> 3356.68 | V71: =IF(_xlfn.NUMBERVALUE($B$2)>=_xlfn.NUMBERVALUE(V$9),V69-V70,"") -> -11.11 | W71: =IF(_xlfn.NUMBERVALUE($B$2)>=_xlfn.NUMBERVALUE(W$9),W69-W70,"") -> 2.21 | X71: =IF(_xlfn.NUMBERVALUE($B$2)>=_xlfn.NUMBERVALUE(X$9),X69-X70,"") -> -25.93 | Y71: =IF(_xlfn.NUMBERVALUE($B$2)>=_xlfn.NUMBERVALUE(Y$9),Y69-Y70,"") -> 356.87 | Z71: =IF(_xlfn.NUMBERVALUE($B$2)>=_xlfn.NUMBERVALUE(Z$9),Z69-Z70,"") -> 543 | ... AU71: =IF(_xlfn.NUMBERVALUE($B$2)>=_xlfn.NUMBERVALUE(AU$9),AU69-AU70,"") -> -14632.74 | AV71: =IF(_xlfn.NUMBERVALUE($B$2)>=_xlfn.NUMBERVALUE(AV$9),AV69-AV70,0) -> 587.26 | AW71: =IF(_xlfn.NUMBERVALUE($B$2)>=_xlfn.NUMBERVALUE(AW$9),AW69-AW70,0) -> 17761.16 | AX71: =IF(_xlfn.NUMBERVALUE($B$2)>=_xlfn.NUMBERVALUE(AX$9),AX69-AX70,0) -> -278.29 | AY71: =IF(_xlfn.NUMBERVALUE($B$2)>=_xlfn.NUMBERVALUE(AY$9),AY69-AY70,0) -> 30.03 | AZ71: =IF(_xlfn.NUMBERVALUE($B$2)>=_xlfn.NUMBERVALUE(AZ$9),AZ69-AZ70,0) -> -569.25 | BA71: =IF(_xlfn.NUMBERVALUE($B$2)>=_xlfn.NUMBERVALUE(BA$9),BA69-BA70,0) -> 147.95 | BB71: =IF(_xlfn.NUMBERVALUE($B$2)>=_xlfn.NUMBERVALUE(BB$9),BB69-BB70,0) -> -19085.2 | BC71: =IF(_xlfn.NUMBERVALUE($B$2)>=_xlfn.NUMBERVALUE(BC$9),BC69-BC70,0) -> -33.8 | ... GT71: =IF(_xlfn.NUMBERVALUE($B$2)>=_xlfn.NUMBERVALUE(GT$9),GT69-GT70,0) -> 0
S72: =S71/(S11+S28) -> 0.2113392 | T72: =T71/(T11+T28) -> 0.15507201 | U72: =U71/(U11+U28) -> 1.3579517 | V72: =V71/(V11+V28) -> -0.0040532652 | W72: =W71/(W11+W28) -> 0.00094202899 | X72: =X71/(X11+X28) -> -0.011921839 | Y72: =Y71/(Y11+Y28) -> 0.16537071 | Z72: =Z71/(Z11+Z28) -> 0.23234917 | ... GT72: =GT71/(GT11+GT28) -> 0
C73: 2020 | D73: 2021 | E73: 2022 | F73: 2023 | G73: 2024 | H73: 2025 | K73: Medio 2020 | L73: Medio 2021 | M73: Medio 2022 | N73: Medio 2023 | O73: Medio2024 | P73: Medio2025
B74: TOTALE SPESE FISSE MENSILI | C74: =SUM(V74:AG74) -> 22582.19 | D74: =SUM(AH74:AS74) -> 15303.27 | E74: =SUM(AT74:BE74) -> 49394.47 | F74: =SUM(BF74:BQ74) -> 16362.29 | G74: =SUM(BR74:CC74) -> 16274.14 | H74: =SUM(CD74:CO74) -> 14968.15 | K74: =C74/12 -> 1881.8492 | L74: =D74/12 -> 1275.2725 | M74: =E74/12 -> 4116.2058 | N74: =F74/12 -> 1363.5242 | O74: =G74/12 -> 1356.1783 | P74: =H74/12 -> 1247.3458 | S74: =IF(_xlfn.NUMBERVALUE($B$2)>=_xlfn.NUMBERVALUE(S$9),SUM(S15:S23)+S53,"") -> 866.89 | T74: =IF(_xlfn.NUMBERVALUE($B$2)>=_xlfn.NUMBERVALUE(T$9),SUM(T15:T23)+T53,"") -> 912.5 | U74: =IF(_xlfn.NUMBERVALUE($B$2)>=_xlfn.NUMBERVALUE(U$9),SUM(U15:U23)+U53,"") -> 886.02 | V74: =IF(_xlfn.NUMBERVALUE($B$2)>=_xlfn.NUMBERVALUE(V$9),SUM(V15:V23)+V53,"") -> 830.89 | W74: =IF(_xlfn.NUMBERVALUE($B$2)>=_xlfn.NUMBERVALUE(W$9),SUM(W15:W23)+W53,"") -> 1158.47 | X74: =IF(_xlfn.NUMBERVALUE($B$2)>=_xlfn.NUMBERVALUE(X$9),SUM(X15:X23)+X53,"") -> 1054.93 | Y74: =IF(_xlfn.NUMBERVALUE($B$2)>=_xlfn.NUMBERVALUE(Y$9),SUM(Y15:Y23)+Y53,"") -> 804.91 | Z74: =IF(_xlfn.NUMBERVALUE($B$2)>=_xlfn.NUMBERVALUE(Z$9),SUM(Z15:Z23)+Z53,"") -> 1099.58 | ... GT74: =IF(_xlfn.NUMBERVALUE($B$2)>=_xlfn.NUMBERVALUE(GT$9),SUM(GT15:GT23)+GT53,"")
B75: TOTALE SPESE VARIABILI MENSILI | C75: =SUM(V75:AG75) -> 21393.17 | D75: =SUM(AH75:AS75) -> 24310.96 | E75: =SUM(AT75:BE75) -> 16989.89 | F75: =SUM(BF75:BQ75) -> 16028.44 | G75: =SUM(BR75:CC75) -> 18977.82 | H75: =SUM(CD75:CO75) -> 20854.328 | K75: =C75/12 -> 1782.7642 | L75: =D75/12 -> 2025.9133 | M75: =E75/12 -> 1415.8242 | N75: =F75/12 -> 1335.7033 | O75: =G75/12 -> 1581.485 | P75: =H75/12 -> 1737.8607 | S75: =IF(_xlfn.NUMBERVALUE($B$2)>=_xlfn.NUMBERVALUE(S$9),SUM(S24:S26)+S62,"") -> 854.34 | T75: =IF(_xlfn.NUMBERVALUE($B$2)>=_xlfn.NUMBERVALUE(T$9),SUM(T24:T26)+T62,"") -> 964.93 | U75: =IF(_xlfn.NUMBERVALUE($B$2)>=_xlfn.NUMBERVALUE(U$9),SUM(U24:U26)+U62,"") -> 1754.17 | V75: =IF(_xlfn.NUMBERVALUE($B$2)>=_xlfn.NUMBERVALUE(V$9),SUM(V24:V26)+V62,"") -> 1921.22 | W75: =IF(_xlfn.NUMBERVALUE($B$2)>=_xlfn.NUMBERVALUE(W$9),SUM(W24:W26)+W62,"") -> 1528.61 | X75: =IF(_xlfn.NUMBERVALUE($B$2)>=_xlfn.NUMBERVALUE(X$9),SUM(X24:X26)+X62,"") -> 1146 | Y75: =IF(_xlfn.NUMBERVALUE($B$2)>=_xlfn.NUMBERVALUE(Y$9),SUM(Y24:Y26)+Y62,"") -> 996.22 | Z75: =IF(_xlfn.NUMBERVALUE($B$2)>=_xlfn.NUMBERVALUE(Z$9),SUM(Z24:Z26)+Z62,"") -> 694.42 | ... GT75: =IF(_xlfn.NUMBERVALUE($B$2)>=_xlfn.NUMBERVALUE(GT$9),SUM(GT24:GT26)+GT62,"")
B76: +ENTRATE FISSE MENSILI | C76: =SUM(V76:AG76) -> 26686 | D76: =SUM(AH76:AS76) -> 26628 | E76: =SUM(AT76:BE76) -> 27484 | F76: =SUM(BF76:BQ76) -> 27474 | G76: =SUM(BR76:CC76) -> 30103 | H76: =SUM(CD76:CO76) -> 30235 | K76: =C76/12 -> 2223.8333 | L76: =D76/12 -> 2219 | M76: =E76/12 -> 2290.3333 | N76: =F76/12 -> 2289.5 | O76: =G76/12 -> 2508.5833 | P76: =H76/12 -> 2519.5833 | S76: =IF(_xlfn.NUMBERVALUE($B$2)>=_xlfn.NUMBERVALUE(S$9),S11,"") -> 2158 | T76: =IF(_xlfn.NUMBERVALUE($B$2)>=_xlfn.NUMBERVALUE(T$9),T11,"") -> 2222 | U76: =IF(_xlfn.NUMBERVALUE($B$2)>=_xlfn.NUMBERVALUE(U$9),U11,"") -> 2271 | V76: =IF(_xlfn.NUMBERVALUE($B$2)>=_xlfn.NUMBERVALUE(V$9),V11,"") -> 2741 | W76: =IF(_xlfn.NUMBERVALUE($B$2)>=_xlfn.NUMBERVALUE(W$9),W11,"") -> 2166 | X76: =IF(_xlfn.NUMBERVALUE($B$2)>=_xlfn.NUMBERVALUE(X$9),X11,"") -> 2175 | Y76: =IF(_xlfn.NUMBERVALUE($B$2)>=_xlfn.NUMBERVALUE(Y$9),Y11,"") -> 2158 | Z76: =IF(_xlfn.NUMBERVALUE($B$2)>=_xlfn.NUMBERVALUE(Z$9),Z11,"") -> 2157 | ... AV76: =IF(_xlfn.NUMBERVALUE($B$2)>=_xlfn.NUMBERVALUE(AV$9),AV11,"") -> 2238 | AW76: =AW11 -> 2250 | AX76: =AX11 -> 2243 | AY76: =AY11 -> 2314 | AZ76: =AZ11 -> 2242 | BA76: =BA11 -> 2244 | BB76: =BB11 -> 2519 | BC76: =BC11 -> 2238 | BD76: =BD11 -> 2248 | ... GT76: =GT11 -> 2638
B77: +ENTRATE VARIABILI MENSILI | C77: =SUM(V77:AG77) -> 2170.39 | D77: =SUM(AH77:AS77) -> 11207 | E77: =SUM(AT77:BE77) -> 33270.18 | F77: =SUM(BF77:BQ77) -> 1061.75 | G77: =SUM(BR77:CC77) -> 3418.67 | H77: =SUM(CD77:CO77) -> 2188.06 | K77: =C77/12 -> 180.86583 | L77: =D77/12 -> 933.91667 | M77: =E77/12 -> 2772.515 | N77: =F77/12 -> 88.479167 | O77: =G77/12 -> 284.88917 | P77: =H77/12 -> 182.33833 | S77: =IF(_xlfn.NUMBERVALUE($B$2)>=_xlfn.NUMBERVALUE(S$9),S63+S28,"") -> 19.3 | T77: =IF(_xlfn.NUMBERVALUE($B$2)>=_xlfn.NUMBERVALUE(T$9),T63+T28,"") -> 0 | U77: =IF(_xlfn.NUMBERVALUE($B$2)>=_xlfn.NUMBERVALUE(U$9),U63+U28,"") -> 200.87 | V77: =IF(_xlfn.NUMBERVALUE($B$2)>=_xlfn.NUMBERVALUE(V$9),V63+V28,"") -> 0 | W77: =IF(_xlfn.NUMBERVALUE($B$2)>=_xlfn.NUMBERVALUE(W$9),W63+W28,"") -> 523.29 | X77: =IF(_xlfn.NUMBERVALUE($B$2)>=_xlfn.NUMBERVALUE(X$9),X63+X28,"") -> 0 | Y77: =IF(_xlfn.NUMBERVALUE($B$2)>=_xlfn.NUMBERVALUE(Y$9),Y63+Y28,"") -> 0 | Z77: =IF(_xlfn.NUMBERVALUE($B$2)>=_xlfn.NUMBERVALUE(Z$9),Z63+Z28,"") -> 180 | ... AV77: =IF(_xlfn.NUMBERVALUE($B$2)>=_xlfn.NUMBERVALUE(AV$9),AV63+AV28,"") -> 475.2 | AW77: =IF(_xlfn.NUMBERVALUE($B$2)>=_xlfn.NUMBERVALUE(AW$9),AW63+AW28,0) -> 18400 | AX77: =IF(_xlfn.NUMBERVALUE($B$2)>=_xlfn.NUMBERVALUE(AX$9),AX63+AX28,0) -> 0 | AY77: =IF(_xlfn.NUMBERVALUE($B$2)>=_xlfn.NUMBERVALUE(AY$9),AY63+AY28,0) -> 0 | AZ77: =IF(_xlfn.NUMBERVALUE($B$2)>=_xlfn.NUMBERVALUE(AZ$9),AZ63+AZ28,0) -> 200 | BA77: =IF(_xlfn.NUMBERVALUE($B$2)>=_xlfn.NUMBERVALUE(BA$9),BA63+BA28,0) -> 86 | BB77: =IF(_xlfn.NUMBERVALUE($B$2)>=_xlfn.NUMBERVALUE(BB$9),BB63+BB28,0) -> 100.01 | BC77: =IF(_xlfn.NUMBERVALUE($B$2)>=_xlfn.NUMBERVALUE(BC$9),BC63+BC28,0) -> 0 | BD77: =IF(_xlfn.NUMBERVALUE($B$2)>=_xlfn.NUMBERVALUE(BD$9),BD63+BD28,0) -> 0 | ... GT77: =IF(_xlfn.NUMBERVALUE($B$2)>=_xlfn.NUMBERVALUE(GT$9),GT63+GT28,0) -> 0
B78: MARGINE | C78: =SUM(V78:AG78) -> -15118.97 | D78: =SUM(AH78:AS78) -> -1779.23 | E78: =SUM(AT78:BE78) -> -5630.18 | F78: =SUM(BF78:BQ78) -> -3854.98 | G78: =SUM(BR78:CC78) -> -1730.29 | H78: =SUM(CD78:CO78) -> -3399.418 | K78: =C78/12 -> -1259.9142 | L78: =D78/12 -> -148.26917 | M78: =E78/12 -> -469.18167 | N78: =F78/12 -> -321.24833 | O78: =G78/12 -> -144.19083 | P78: =H78/12 -> -283.28483 | S78: =IF(_xlfn.NUMBERVALUE($B$2)>=_xlfn.NUMBERVALUE(S$9),(S76+S77)-(S74+S75),"") -> 456.07 | T78: =IF(_xlfn.NUMBERVALUE($B$2)>=_xlfn.NUMBERVALUE(T$9),(T76+T77)-(T74+T75),"") -> 344.57 | U78: =IF(_xlfn.NUMBERVALUE($B$2)>=_xlfn.NUMBERVALUE(U$9),(U76+U77)-(U74+U75),"") -> -168.32 | V78: =IF(_xlfn.NUMBERVALUE($B$2)>=_xlfn.NUMBERVALUE(V$9),(V76+V77)-(V74+V75),"") -> -11.11 | W78: =IF(_xlfn.NUMBERVALUE($B$2)>=_xlfn.NUMBERVALUE(W$9),(W76+W77)-(W74+W75),"") -> 2.21 | X78: =IF(_xlfn.NUMBERVALUE($B$2)>=_xlfn.NUMBERVALUE(X$9),(X76+X77)-(X74+X75),"") -> -25.93 | Y78: =IF(_xlfn.NUMBERVALUE($B$2)>=_xlfn.NUMBERVALUE(Y$9),(Y76+Y77)-(Y74+Y75),"") -> 356.87 | Z78: =IF(_xlfn.NUMBERVALUE($B$2)>=_xlfn.NUMBERVALUE(Z$9),(Z76+Z77)-(Z74+Z75),"") -> 543 | ... GT78: =IF(_xlfn.NUMBERVALUE($B$2)>=_xlfn.NUMBERVALUE(GT$9),(GT76+GT77)-(GT74+GT75),"")
B80: RICAVI STRAORDINARI | C80: =SUM(V80:AG80) -> 2170.39 | D80: =SUM(AH80:AS80) -> 11207 | E80: =SUM(AT80:BE80) -> 33270.18 | F80: =SUM(BF80:BQ80) -> 1061.75 | G80: =SUM(BR80:CC80) -> 3418.67 | H80: =SUM(CD80:CO80) -> 2188.06 | K80: =C80/12 -> 180.86583 | L80: =D80/12 -> 933.91667 | M80: =E80/12 -> 2772.515 | N80: =F80/12 -> 88.479167 | O80: =G80/12 -> 284.88917 | P80: =H80/12 -> 182.33833 | S80: =S28+S63 -> 19.3 | T80: =T28+T63 -> 0 | U80: =U28+U63 -> 200.87 | V80: =V28+V63 -> 0 | W80: =W28+W63 -> 523.29 | X80: =X28+X63 -> 0 | Y80: =Y28+Y63 -> 0 | Z80: =Z28+Z63 -> 180 | ... GT80: =GT28+GT63 -> 0
B81: SPESE STRAORDINARIE | C81: =SUM(V81:AG81) -> 9181.81 | D81: =SUM(AH81:AS81) -> 7707.81 | E81: =SUM(AT81:BE81) -> 2988.77 | F81: =SUM(BF81:BQ81) -> 1673.08 | G81: =SUM(BR81:CC81) -> 2606.85 | H81: =SUM(CD81:CO81) -> 2155.26 | K81: =C81/12 -> 765.15083 | L81: =D81/12 -> 642.3175 | M81: =E81/12 -> 249.06417 | N81: =F81/12 -> 139.42333 | O81: =G81/12 -> 217.2375 | P81: =H81/12 -> 179.605 | S81: =S26 -> 0 | T81: =T26 -> 25 | U81: =U26 -> 687.75 | V81: =V26 -> 261.89 | W81: =W26 -> 512 | X81: =X26 -> 148.8 | Y81: =Y26 -> 40 | Z81: =Z26 -> 142 | ... GT81: =GT26 -> 0
B82: MARGINE STRAORDINARIO | C82: =SUM(V82:AG82) -> -7011.42 | D82: =SUM(AH82:AS82) -> 3499.19 | E82: =SUM(AT82:BE82) -> 30281.41 | F82: =SUM(BF82:BQ82) -> -611.33 | G82: =SUM(BR82:CC82) -> 811.82 | H82: =SUM(CD82:CO82) -> 32.8 | K82: =C82/12 -> -584.285 | L82: =D82/12 -> 291.59917 | M82: =E82/12 -> 2523.4508 | N82: =F82/12 -> -50.944167 | O82: =G82/12 -> 67.651667 | P82: =H82/12 -> 2.7333333 | S82: =S80-S81 -> 19.3 | T82: =T80-T81 -> -25 | U82: =U80-U81 -> -486.88 | V82: =V80-V81 -> -261.89 | W82: =W80-W81 -> 11.29 | X82: =X80-X81 -> -148.8 | Y82: =Y80-Y81 -> -40 | Z82: =Z80-Z81 -> 38 | ... GT82: =GT80-GT81 -> 0

Sheet PRELIEVI CONTANTI
A1: DATA | B1: ANNO | C1: MESE | D1: PRELIEVO CONTO | E1: PRELIEVO CARTA | F1: INTERESSI | G1: TOTALE MESE | I1: RIEPILOGO ANNUALE PRELIEVI
A2: 43709 | B2: =YEAR(A2) -> 2019 | C2: =MONTH(A2) -> 9 | D2: 0 | E2: =BILANCIO!S58 -> 340 | F2: =8+2.8+2.8 -> 13.6 | G2: =D2+E2+F2 -> 353.6 | I2: ANNO | J2: CARTA CREDITO | K2: INTERESSI | L2: CONTO BANCA | M2: TOTALE | N2: DIFF. ANNO PREC. | O2: VAR. %
A3: 43739 | B3: =YEAR(A3) -> 2019 | C3: =MONTH(A3) -> 10 | D3: =BILANCIO!S24 -> 0 | E3: =BILANCIO!T58 -> 490 | F3: =3.2+2.8+4+2.8+4+2.8 -> 19.6 | G3: =D3+E3+F3 -> 509.6 | I3: 2019 | J3: =SUMIF($B:$B,I3,$E:$E) -> 1470 | K3: =SUMIF($B:$B,I3,$F:$F) -> 58.8 | L3: =SUMIF($B:$B,I3,$D:$D) -> 0 | M3: =J3+K3+L3 -> 1528.8 | N3: - | O3: -
A4: 43770 | B4: =YEAR(A4) -> 2019 | C4: =MONTH(A4) -> 11 | D4: =BILANCIO!T24 -> 0 | E4: =BILANCIO!U58 -> 400 | F4: =4+8+4 -> 16 | G4: =D4+E4+F4 -> 416 | I4: 2020 | J4: =SUMIF($B:$B,I4,$E:$E) -> 2680 | K4: =SUMIF($B:$B,I4,$F:$F) -> 103.2 | L4: =SUMIF($B:$B,I4,$D:$D) -> 0 | M4: =J4+K4+L4 -> 2783.2 | N4: =M4-M3 -> 1254.4 | O4: =IF(M3=0,"-",(M4-M3)/M3) -> 0.82051282
A5: 43800 | B5: =YEAR(A5) -> 2019 | C5: =MONTH(A5) -> 12 | D5: =BILANCIO!U24 -> 0 | E5: =BILANCIO!V58 -> 240 | F5: =3.6+6 -> 9.6 | G5: =D5+E5+F5 -> 249.6 | I5: 2021 | J5: =SUMIF($B:$B,I5,$E:$E) -> 3284.91 | K5: =SUMIF($B:$B,I5,$F:$F) -> 134.04 | L5: =SUMIF($B:$B,I5,$D:$D) -> 3652 | M5: =J5+K5+L5 -> 7070.95 | N5: =M5-M4 -> 4287.75 | O5: =IF(M4=0,"-",(M5-M4)/M4) -> 1.5405828
A6: 43831 | B6: =YEAR(A6) -> 2020 | C6: =MONTH(A6) -> 1 | D6: =BILANCIO!V24 -> 0 | E6: =BILANCIO!W58 -> 220 | F6: =4.8+4 -> 8.8 | G6: =D6+E6+F6 -> 228.8 | I6: 2022 | J6: =SUMIF($B:$B,I6,$E:$E) -> 4271.79 | K6: =SUMIF($B:$B,I6,$F:$F) -> 192.46 | L6: =SUMIF($B:$B,I6,$D:$D) -> 1980 | M6: =J6+K6+L6 -> 6444.25 | N6: =M6-M5 -> -626.7 | O6: =IF(M5=0,"-",(M6-M5)/M5) -> -0.088630241
A7: 43862 | B7: =YEAR(A7) -> 2020 | C7: =MONTH(A7) -> 2 | D7: =BILANCIO!W24 -> 0 | E7: =BILANCIO!X58 -> 300 | F7: =4+4 -> 8 | G7: =D7+E7+F7 -> 308 | I7: 2023 | J7: =SUMIF($B:$B,I7,$E:$E) -> 4930 | K7: =SUMIF($B:$B,I7,$F:$F) -> 196.91 | L7: =SUMIF($B:$B,I7,$D:$D) -> 220 | M7: =J7+K7+L7 -> 5346.91 | N7: =M7-M6 -> -1097.34 | O7: =IF(M6=0,"-",(M7-M6)/M6) -> -0.17028203
A8: 43891 | B8: =YEAR(A8) -> 2020 | C8: =MONTH(A8) -> 3 | D8: =BILANCIO!X24 -> 0 | E8: =BILANCIO!Y58 -> 0 | G8: =D8+E8+F8 -> 0 | I8: 2024 | J8: =SUMIF($B:$B,I8,$E:$E) -> 3232.9 | K8: =SUMIF($B:$B,I8,$F:$F) -> 128.93 | L8: =SUMIF($B:$B,I8,$D:$D) -> 442 | M8: =J8+K8+L8 -> 3803.83 | N8: =M8-M7 -> -1543.08 | O8: =IF(M7=0,"-",(M8-M7)/M7) -> -0.28859285
A9: 43922 | B9: =YEAR(A9) -> 2020 | C9: =MONTH(A9) -> 4 | D9: =BILANCIO!Y24 -> 0 | E9: =BILANCIO!Z58 -> 0 | G9: =D9+E9+F9 -> 0 | I9: 2025 | J9: =SUMIF($B:$B,I9,$E:$E) -> 1100 | K9: =SUMIF($B:$B,I9,$F:$F) -> 42.07 | L9: =SUMIF($B:$B,I9,$D:$D) -> 1030 | M9: =J9+K9+L9 -> 2172.07 | N9: =M9-M8 -> -1631.76 | O9: =IF(M8=0,"-",(M9-M8)/M8) -> -0.42897816
A10: 43952 | B10: =YEAR(A10) -> 2020 | C10: =MONTH(A10) -> 5 | D10: =BILANCIO!Z24 -> 0 | E10: =BILANCIO!AA58 -> 150 | F10: 6 | G10: =D10+E10+F10 -> 156 | I10: 2026 | J10: =SUMIF($B:$B,I10,$E:$E) -> 80 | K10: =SUMIF($B:$B,I10,$F:$F) -> 3.2 | L10: =SUMIF($B:$B,I10,$D:$D) -> 1466 | M10: =J10+K10+L10 -> 1549.2 | N10: =M10-M9 -> -622.87 | O10: =IF(M9=0,"-",(M10-M9)/M9) -> -0.28676332
A11: 43983 | B11: =YEAR(A11) -> 2020 | C11: =MONTH(A11) -> 6 | D11: =BILANCIO!AA24 -> 0 | E11: =BILANCIO!AB58 -> 200 | F11: =4+4 -> 8 | G11: =D11+E11+F11 -> 208 | I11: 2027 | J11: =SUMIF($B:$B,I11,$E:$E) -> 0 | K11: =SUMIF($B:$B,I11,$F:$F) -> 0 | L11: =SUMIF($B:$B,I11,$D:$D) -> 0 | M11: =J11+K11+L11 -> 0 | N11: =M11-M10 -> -1549.2 | O11: =IF(M10=0,"-",(M11-M10)/M10) -> -1
A12: 44013 | B12: =YEAR(A12) -> 2020 | C12: =MONTH(A12) -> 7 | D12: =BILANCIO!AB24 -> 0 | E12: =BILANCIO!AC58 -> 200 | F12: =4+4 -> 8 | G12: =D12+E12+F12 -> 208 | I12: 2028 | J12: =SUMIF($B:$B,I12,$E:$E) -> 0 | K12: =SUMIF($B:$B,I12,$F:$F) -> 0 | L12: =SUMIF($B:$B,I12,$D:$D) -> 0 | M12: =J12+K12+L12 -> 0 | N12: =M12-M11 -> 0 | O12: =IF(M11=0,"-",(M12-M11)/M11) -> -
A13: 44044 | B13: =YEAR(A13) -> 2020 | C13: =MONTH(A13) -> 8 | D13: =BILANCIO!AC24 -> 0 | E13: =BILANCIO!AD58 -> 340 | F13: =2.8+2.8+4+4 -> 13.6 | G13: =D13+E13+F13 -> 353.6 | I13: 2029 | J13: =SUMIF($B:$B,I13,$E:$E) -> 0 | K13: =SUMIF($B:$B,I13,$F:$F) -> 0 | L13: =SUMIF($B:$B,I13,$D:$D) -> 0 | M13: =J13+K13+L13 -> 0 | N13: =M13-M12 -> 0 | O13: =IF(M12=0,"-",(M13-M12)/M12) -> -
A14: 44075 | B14: =YEAR(A14) -> 2020 | C14: =MONTH(A14) -> 9 | D14: =BILANCIO!AD24 -> 0 | E14: =BILANCIO!AE58 -> 350 | F14: =4+4+6 -> 14 | G14: =D14+E14+F14 -> 364 | I14: TOTALE | J14: =SUM(J3:J13) -> 21049.6 | K14: =SUM(K3:K13) -> 859.61 | L14: =SUM(L3:L13) -> 8790 | M14: =SUM(M3:M13) -> 30699.21
A15: 44105 | B15: =YEAR(A15) -> 2020 | C15: =MONTH(A15) -> 10 | D15: =BILANCIO!AE24 -> 0 | E15: =BILANCIO!AF58 -> 340 | F15: =5.6+4+4 -> 13.6 | G15: =D15+E15+F15 -> 353.6
A16: 44136 | B16: =YEAR(A16) -> 2020 | C16: =MONTH(A16) -> 11 | D16: =BILANCIO!AF24 -> 0 | E16: =BILANCIO!AG58 -> 430 | F16: =2.8+11.6+2.8 -> 17.2 | G16: =D16+E16+F16 -> 447.2
A17: 44166 | B17: =YEAR(A17) -> 2020 | C17: =MONTH(A17) -> 12 | D17: =BILANCIO!AG24 -> 0 | E17: =BILANCIO!AH58 -> 150 | F17: 6 | G17: =D17+E17+F17 -> 156
A18: 44197 | B18: =YEAR(A18) -> 2021 | C18: =MONTH(A18) -> 1 | D18: =BILANCIO!AH24 -> 0 | E18: =BILANCIO!AI58 -> 100 | F18: 4 | G18: =D18+E18+F18 -> 104
A19: 44228 | B19: =YEAR(A19) -> 2021 | C19: =MONTH(A19) -> 2 | D19: =BILANCIO!AI24 -> 0 | E19: =BILANCIO!AJ58 -> 390 | F19: =2.8+10+2.8 -> 15.6 | G19: =D19+E19+F19 -> 405.6
A20: 44256 | B20: =YEAR(A20) -> 2021 | C20: =MONTH(A20) -> 3 | D20: =BILANCIO!AJ24 -> 2100 | E20: =BILANCIO!AK58 -> 0 | G20: =D20+E20+F20 -> 2100
A21: 44287 | B21: =YEAR(A21) -> 2021 | C21: =MONTH(A21) -> 4 | D21: =BILANCIO!AK24 -> 70 | E21: =BILANCIO!AL58 -> 0 | G21: =D21+E21+F21 -> 70
A22: 44317 | B22: =YEAR(A22) -> 2021 | C22: =MONTH(A22) -> 5 | D22: =BILANCIO!AL24 -> 0 | E22: =BILANCIO!AM58 -> 70 | F22: 2.8 | G22: =D22+E22+F22 -> 72.8
A23: 44348 | B23: =YEAR(A23) -> 2021 | C23: =MONTH(A23) -> 6 | D23: =BILANCIO!AM24 -> 170 | E23: =BILANCIO!AN58 -> 350 | F23: =2.4+2.8+4+2.8+2.07 -> 14.07 | G23: =D23+E23+F23 -> 534.07
A24: 44378 | B24: =YEAR(A24) -> 2021 | C24: =MONTH(A24) -> 7 | D24: =BILANCIO!AN24 -> 350 | E24: =BILANCIO!AO58 -> 540 | F24: =10+10+2.07 -> 22.07 | G24: =D24+E24+F24 -> 912.07
A25: 44409 | B25: =YEAR(A25) -> 2021 | C25: =MONTH(A25) -> 8 | D25: =BILANCIO!AO24 -> 350 | E25: =BILANCIO!AP58 -> 250 | F25: 10 | G25: =D25+E25+F25 -> 610
A26: 44440 | B26: =YEAR(A26) -> 2021 | C26: =MONTH(A26) -> 9 | D26: =BILANCIO!AP24 -> 250 | E26: =BILANCIO!AQ58 -> 260 | F26: =2.07+2.07+2.07+2.07+2.4 -> 10.68 | G26: =D26+E26+F26 -> 520.68
A27: 44470 | B27: =YEAR(A27) -> 2021 | C27: =MONTH(A27) -> 10 | D27: =BILANCIO!AQ24 -> 102 | E27: =BILANCIO!AR58 -> 430 | F27: =2.07+4+4+3.2+2.4+2.07 -> 17.74 | G27: =D27+E27+F27 -> 549.74
A28: 44501 | B28: =YEAR(A28) -> 2021 | C28: =MONTH(A28) -> 11 | D28: =BILANCIO!AR24 -> 0 | E28: =BILANCIO!AS58 -> 444.91 | F28: =2.4+3.2+2.07+2.07+3.2+4+2.07 -> 19.01 | G28: =D28+E28+F28 -> 463.92
A29: 44531 | B29: =YEAR(A29) -> 2021 | C29: =MONTH(A29) -> 12 | D29: =BILANCIO!AS24 -> 260 | E29: =BILANCIO!AT58 -> 450 | F29: =2.07+4+2.4+7.2+2.4 -> 18.07 | G29: =D29+E29+F29 -> 728.07
A30: 44562 | B30: =YEAR(A30) -> 2022 | C30: =MONTH(A30) -> 1 | D30: =BILANCIO!AT24 -> 0 | E30: =BILANCIO!AU58 -> 400 | F30: =2.4+2.4+2.4+2.4+2.07+2.07+2.07+2.07 -> 17.88 | G30: =D30+E30+F30 -> 417.88
A31: 44593 | B31: =YEAR(A31) -> 2022 | C31: =MONTH(A31) -> 2 | D31: =BILANCIO!AU24 -> 280 | E31: =BILANCIO!AV58 -> 250 | F31: =2.4+2.07+2.07+4 -> 10.54 | G31: =D31+E31+F31 -> 540.54
A32: 44621 | B32: =YEAR(A32) -> 2022 | C32: =MONTH(A32) -> 3 | D32: =BILANCIO!AV24 -> 120 | E32: =BILANCIO!AW58 -> 387.84 | F32: =2.07+2.07+2.4+2.07+2.4+4+2.4 -> 17.41 | G32: =D32+E32+F32 -> 525.25
A33: 44652 | B33: =YEAR(A33) -> 2022 | C33: =MONTH(A33) -> 4 | D33: =BILANCIO!AW24 -> 350 | E33: =BILANCIO!AX58 -> 40 | F33: 2.07 | G33: =D33+E33+F33 -> 392.07
A34: 44682 | B34: =YEAR(A34) -> 2022 | C34: =MONTH(A34) -> 5 | D34: =BILANCIO!AX24 -> 120 | E34: =BILANCIO!AY58 -> 240 | F34: =2.07+2.07+2.4+2.4+2.07 -> 11.01 | G34: =D34+E34+F34 -> 371.01
A35: 44713 | B35: =YEAR(A35) -> 2022 | C35: =MONTH(A35) -> 6 | D35: =BILANCIO!AY24 -> 130 | E35: =BILANCIO!AZ58 -> 533.95 | F35: =2.4+2.4+2.8+2.07+2.8+4.15+2.07+3.2 -> 21.89 | G35: =D35+E35+F35 -> 685.84
A36: 44743 | B36: =YEAR(A36) -> 2022 | C36: =MONTH(A36) -> 7 | D36: =BILANCIO!AZ24 -> 0 | E36: =BILANCIO!BA58 -> 430 | F36: =2.07+4+2.07+2.07+2.4+2.4+2.07+2.07 -> 19.15 | G36: =D36+E36+F36 -> 449.15
A37: 44774 | B37: =YEAR(A37) -> 2022 | C37: =MONTH(A37) -> 8 | D37: =BILANCIO!BA24 -> 180 | E37: =BILANCIO!BB58 -> 410 | F37: =3.6+2.4+2.4+4.8+3.2 -> 16.4 | G37: =D37+E37+F37 -> 606.4
A38: 44805 | B38: =YEAR(A38) -> 2022 | C38: =MONTH(A38) -> 9 | D38: =BILANCIO!BB24 -> 310 | E38: =BILANCIO!BC58 -> 510 | F38: =2.07+4+4+4+2.8+2.4+2.07 -> 21.34 | G38: =D38+E38+F38 -> 841.34
A39: 44835 | B39: =YEAR(A39) -> 2022 | C39: =MONTH(A39) -> 10 | D39: =BILANCIO!BC24 -> 0 | E39: =BILANCIO!BD58 -> 420 | F39: =2.4+2.4+3.2+2.4+2.4+2.07+2.4 -> 17.27 | G39: =D39+E39+F39 -> 437.27
A40: 44866 | B40: =YEAR(A40) -> 2022 | C40: =MONTH(A40) -> 11 | D40: =BILANCIO!BD24 -> 0 | E40: =BILANCIO!BE58 -> 550 | F40: =2.07+3.2+2.07+2.07+2.07+2.4+2.4+4+2.07+2.07 -> 24.42 | G40: =D40+E40+F40 -> 574.42
A41: 44896 | B41: =YEAR(A41) -> 2022 | C41: =MONTH(A41) -> 12 | D41: =BILANCIO!BE24 -> 490 | E41: =BILANCIO!BF58 -> 100 | F41: =BILANCIO!BG59 -> 13.08 | G41: =D41+E41+F41 -> 603.08
A42: 44927 | B42: =YEAR(A42) -> 2023 | C42: =MONTH(A42) -> 1 | D42: =BILANCIO!BF24 -> 100 | E42: =BILANCIO!BG58 -> 280 | F42: =BILANCIO!BH59 -> 18.94 | G42: =D42+E42+F42 -> 398.94
A43: 44958 | B43: =YEAR(A43) -> 2023 | C43: =MONTH(A43) -> 2 | D43: =BILANCIO!BG24 -> 0 | E43: =BILANCIO!BH58 -> 450 | F43: =BILANCIO!BI59 -> 18.47 | G43: =D43+E43+F43 -> 468.47
A44: 44986 | B44: =YEAR(A44) -> 2023 | C44: =MONTH(A44) -> 3 | D44: =BILANCIO!BH24 -> 0 | E44: =BILANCIO!BI58 -> 460 | F44: =BILANCIO!BJ59 -> 20.4 | G44: =D44+E44+F44 -> 480.4
A45: 45017 | B45: =YEAR(A45) -> 2023 | C45: =MONTH(A45) -> 4 | D45: =BILANCIO!BI24 -> 0 | E45: =BILANCIO!BJ58 -> 510 | F45: =BILANCIO!BK59 -> 26.61 | G45: =D45+E45+F45 -> 536.61
A46: 45047 | B46: =YEAR(A46) -> 2023 | C46: =MONTH(A46) -> 5 | D46: =BILANCIO!BJ24 -> 0 | E46: =BILANCIO!BK58 -> 630 | F46: =BILANCIO!BL59 -> 10.87 | G46: =D46+E46+F46 -> 640.87
A47: 45078 | B47: =YEAR(A47) -> 2023 | C47: =MONTH(A47) -> 6 | D47: =BILANCIO!BK24 -> 0 | E47: =BILANCIO!BL58 -> 260 | F47: =BILANCIO!BM59 -> 12.14 | G47: =D47+E47+F47 -> 272.14
A48: 45108 | B48: =YEAR(A48) -> 2023 | C48: =MONTH(A48) -> 7 | D48: =BILANCIO!BL24 -> 0 | E48: =BILANCIO!BM58 -> 290 | F48: =BILANCIO!BN59 -> 22.8 | G48: =D48+E48+F48 -> 312.8
A49: 45139 | B49: =YEAR(A49) -> 2023 | C49: =MONTH(A49) -> 8 | D49: =BILANCIO!BM24 -> 0 | E49: =BILANCIO!BN58 -> 570 | F49: =BILANCIO!BO59 -> 13.6 | G49: =D49+E49+F49 -> 583.6
A50: 45170 | B50: =YEAR(A50) -> 2023 | C50: =MONTH(A50) -> 9 | D50: =BILANCIO!BN24 -> 50 | E50: =BILANCIO!BO58 -> 340 | F50: =BILANCIO!BP59 -> 10 | G50: =D50+E50+F50 -> 400
A51: 45200 | B51: =YEAR(A51) -> 2023 | C51: =MONTH(A51) -> 10 | D51: =BILANCIO!BO24 -> 0 | E51: =BILANCIO!BP58 -> 250 | F51: =BILANCIO!BQ59 -> 17.34 | G51: =D51+E51+F51 -> 267.34
A52: 45231 | B52: =YEAR(A52) -> 2023 | C52: =MONTH(A52) -> 11 | D52: =BILANCIO!BP24 -> 0 | E52: =BILANCIO!BQ58 -> 410 | F52: =BILANCIO!BR59 -> 19.2 | G52: =D52+E52+F52 -> 429.2
A53: 45261 | B53: =YEAR(A53) -> 2023 | C53: =MONTH(A53) -> 12 | D53: =BILANCIO!BQ24 -> 70 | E53: =BILANCIO!BR58 -> 480 | F53: =BILANCIO!BS59 -> 6.54 | G53: =D53+E53+F53 -> 556.54
A54: 45292 | B54: =YEAR(A54) -> 2024 | C54: =MONTH(A54) -> 1 | D54: =BILANCIO!BR24 -> 0 | E54: =BILANCIO!BS58 -> 140 | F54: =BILANCIO!BT59 -> 13.2 | G54: =D54+E54+F54 -> 153.2
A55: 45323 | B55: =YEAR(A55) -> 2024 | C55: =MONTH(A55) -> 2 | D55: =BILANCIO!BS24 -> 0 | E55: =BILANCIO!BT58 -> 330 | F55: =BILANCIO!BU59 -> 8.07 | G55: =D55+E55+F55 -> 338.07
A56: 45352 | B56: =YEAR(A56) -> 2024 | C56: =MONTH(A56) -> 3 | D56: =BILANCIO!BT24 -> 92 | E56: =BILANCIO!BU58 -> 190 | F56: =BILANCIO!BV59 -> 9.6 | G56: =D56+E56+F56 -> 291.6
A57: 45383 | B57: =YEAR(A57) -> 2024 | C57: =MONTH(A57) -> 4 | D57: =BILANCIO!BU24 -> 0 | E57: =BILANCIO!BV58 -> 240 | F57: =BILANCIO!BW59 -> 22.51 | G57: =D57+E57+F57 -> 262.51
A58: 45413 | B58: =YEAR(A58) -> 2024 | C58: =MONTH(A58) -> 5 | D58: =BILANCIO!BV24 -> 0 | E58: =BILANCIO!BW58 -> 562.9 | F58: =BILANCIO!BX59 -> 15.6 | G58: =D58+E58+F58 -> 578.5
A59: 45444 | B59: =YEAR(A59) -> 2024 | C59: =MONTH(A59) -> 6 | D59: =BILANCIO!BW24 -> 70 | E59: =BILANCIO!BX58 -> 390 | F59: =BILANCIO!BY59 -> 13.41 | G59: =D59+E59+F59 -> 473.41
A60: 45474 | B60: =YEAR(A60) -> 2024 | C60: =MONTH(A60) -> 7 | D60: =BILANCIO!BX24 -> 0 | E60: =BILANCIO!BY58 -> 300 | F60: =BILANCIO!BZ59 -> 16.87 | G60: =D60+E60+F60 -> 316.87
A61: 45505 | B61: =YEAR(A61) -> 2024 | C61: =MONTH(A61) -> 8 | D61: =BILANCIO!BY24 -> 0 | E61: =BILANCIO!BZ58 -> 410 | F61: =BILANCIO!CA59 -> 10.47 | G61: =D61+E61+F61 -> 420.47
A62: 45536 | B62: =YEAR(A62) -> 2024 | C62: =MONTH(A62) -> 9 | D62: =BILANCIO!BZ24 -> 70 | E62: =BILANCIO!CA58 -> 250 | F62: =BILANCIO!CB59 -> 7.2 | G62: =D62+E62+F62 -> 327.2
A63: 45566 | B63: =YEAR(A63) -> 2024 | C63: =MONTH(A63) -> 10 | D63: =BILANCIO!CA24 -> 40 | E63: =BILANCIO!CB58 -> 180 | F63: =BILANCIO!CC59 -> 2.4 | G63: =D63+E63+F63 -> 222.4
A64: 45597 | B64: =YEAR(A64) -> 2024 | C64: =MONTH(A64) -> 11 | D64: =BILANCIO!CB24 -> 0 | E64: =BILANCIO!CC58 -> 60 | F64: =BILANCIO!CD59 -> 7.2 | G64: =D64+E64+F64 -> 67.2
A65: 45627 | B65: =YEAR(A65) -> 2024 | C65: =MONTH(A65) -> 12 | D65: =BILANCIO!CC24 -> 170 | E65: =BILANCIO!CD58 -> 180 | F65: =BILANCIO!CE$59 -> 2.4 | G65: =D65+E65+F65 -> 352.4
A66: 45658 | B66: =YEAR(A66) -> 2025 | C66: =MONTH(A66) -> 1 | D66: =BILANCIO!CD24 -> 210 | E66: =BILANCIO!CE58 -> 60 | F66: =BILANCIO!CF$59 -> 5.6 | G66: =D66+E66+F66 -> 275.6
A67: 45689 | B67: =YEAR(A67) -> 2025 | C67: =MONTH(A67) -> 2 | D67: =BILANCIO!CE24 -> 0 | E67: =BILANCIO!CF58 -> 140 | F67: =BILANCIO!CG$59 -> 2.4 | G67: =D67+E67+F67 -> 142.4
A68: 45717 | B68: =YEAR(A68) -> 2025 | C68: =MONTH(A68) -> 3 | D68: =BILANCIO!CF24 -> 90 | E68: =BILANCIO!CG58 -> 60 | F68: =BILANCIO!CH$59 -> 0 | G68: =D68+E68+F68 -> 150
A69: 45748 | B69: =YEAR(A69) -> 2025 | C69: =MONTH(A69) -> 4 | D69: =BILANCIO!CG24 -> 0 | E69: =BILANCIO!CH58 -> 0 | F69: =BILANCIO!CI$59 -> 4.8 | G69: =D69+E69+F69 -> 4.8
A70: 45778 | B70: =YEAR(A70) -> 2025 | C70: =MONTH(A70) -> 5 | D70: =BILANCIO!CH$24 -> 70 | E70: =BILANCIO!CI58 -> 120 | F70: =BILANCIO!CJ$59 -> 7.2 | G70: =D70+E70+F70 -> 197.2
A71: 45809 | B71: =YEAR(A71) -> 2025 | C71: =MONTH(A71) -> 6 | D71: =BILANCIO!CI$24 -> 0 | E71: =BILANCIO!CJ58 -> 180 | F71: =BILANCIO!CK$59 -> 4.47 | G71: =D71+E71+F71 -> 184.47
A72: 45839 | B72: =YEAR(A72) -> 2025 | C72: =MONTH(A72) -> 7 | D72: =BILANCIO!CJ$24 -> 70 | E72: =BILANCIO!CK58 -> 100 | F72: =BILANCIO!CL$59 -> 8.4 | G72: =D72+E72+F72 -> 178.4
A73: 45870 | B73: =YEAR(A73) -> 2025 | C73: =MONTH(A73) -> 8 | D73: =BILANCIO!CK$24 -> 110 | E73: =BILANCIO!CL58 -> 210 | F73: =BILANCIO!CM$59 -> 9.2 | G73: =D73+E73+F73 -> 329.2
A74: 45901 | B74: =YEAR(A74) -> 2025 | C74: =MONTH(A74) -> 9 | D74: =BILANCIO!CL$24 -> 0 | E74: =BILANCIO!CM58 -> 230 | F74: =BILANCIO!CN$59 -> 0 | G74: =D74+E74+F74 -> 230
A75: 45931 | B75: =YEAR(A75) -> 2025 | C75: =MONTH(A75) -> 10 | D75: =BILANCIO!CM$24 -> 140 | E75: =BILANCIO!CN58 -> 0 | F75: =BILANCIO!CO$59 -> 0 | G75: =D75+E75+F75 -> 140
A76: 45962 | B76: =YEAR(A76) -> 2025 | C76: =MONTH(A76) -> 11 | D76: =BILANCIO!CN$24 -> 0 | E76: =BILANCIO!CO58 -> 0 | F76: =BILANCIO!CP$59 -> 0 | G76: =D76+E76+F76 -> 0
A77: 45992 | B77: =YEAR(A77) -> 2025 | C77: =MONTH(A77) -> 12 | D77: =BILANCIO!CO$24 -> 340 | E77: =BILANCIO!CP58 -> 0 | F77: =BILANCIO!CQ$59 -> 0 | G77: =D77+E77+F77 -> 340
A78: 46023 | B78: =YEAR(A78) -> 2026 | C78: =MONTH(A78) -> 1 | D78: =BILANCIO!CP$24 -> 0 | E78: =BILANCIO!CQ58 -> 0 | F78: =BILANCIO!CR$59 -> 0 | G78: =D78+E78+F78 -> 0
A79: 46054 | B79: =YEAR(A79) -> 2026 | C79: =MONTH(A79) -> 2 | D79: =BILANCIO!CQ$24 -> 0 | E79: =BILANCIO!CR58 -> 0 | F79: =BILANCIO!CS$59 -> 0 | G79: =D79+E79+F79 -> 0
A80: 46082 | B80: =YEAR(A80) -> 2026 | C80: =MONTH(A80) -> 3 | D80: =BILANCIO!CR$24 -> 72 | E80: =BILANCIO!CS58 -> 0 | F80: =BILANCIO!CT$59 -> 0 | G80: =D80+E80+F80 -> 72
A81: 46113 | B81: =YEAR(A81) -> 2026 | C81: =MONTH(A81) -> 4 | D81: =BILANCIO!CS$24 -> 80 | E81: =BILANCIO!CT58 -> 0 | F81: =BILANCIO!CU$59 -> 0 | G81: =D81+E81+F81 -> 80
A82: 46143 | B82: =YEAR(A82) -> 2026 | C82: =MONTH(A82) -> 5 | D82: =BILANCIO!CT$24 -> 350 | E82: =BILANCIO!CU58 -> 0 | F82: =BILANCIO!CV$59 -> 0 | G82: =D82+E82+F82 -> 350
A83: 46174 | B83: =YEAR(A83) -> 2026 | C83: =MONTH(A83) -> 6 | D83: =BILANCIO!CU$24 -> 280 | E83: =BILANCIO!CV58 -> 0 | F83: =BILANCIO!CW$59 -> 0 | G83: =D83+E83+F83 -> 280
A84: 46204 | B84: =YEAR(A84) -> 2026 | C84: =MONTH(A84) -> 7 | D84: =BILANCIO!CV$24 -> 70 | E84: =BILANCIO!CW58 -> 0 | F84: =BILANCIO!CX$59 -> 3.2 | G84: =D84+E84+F84 -> 73.2
A85: 46235 | B85: =YEAR(A85) -> 2026 | C85: =MONTH(A85) -> 8 | D85: =BILANCIO!CW$24 -> 190 | E85: =BILANCIO!CX58 -> 80 | F85: =BILANCIO!CY$59 -> 0 | G85: =D85+E85+F85 -> 270
A86: 46266 | B86: =YEAR(A86) -> 2026 | C86: =MONTH(A86) -> 9 | D86: =BILANCIO!CX$24 -> 424 | E86: =BILANCIO!CY58 -> 0 | F86: =BILANCIO!CZ$59 -> 0 | G86: =D86+E86+F86 -> 424
A87: 46296 | B87: =YEAR(A87) -> 2026 | C87: =MONTH(A87) -> 10 | D87: =BILANCIO!CY$24 -> 0 | E87: =BILANCIO!CZ58 -> 0 | F87: =BILANCIO!DA$59 -> 0 | G87: =D87+E87+F87 -> 0
A88: 46327 | B88: =YEAR(A88) -> 2026 | C88: =MONTH(A88) -> 11 | D88: =BILANCIO!CZ$24 -> 0 | E88: =BILANCIO!DA58 -> 0 | F88: =BILANCIO!DB$59 -> 0 | G88: =D88+E88+F88 -> 0
A89: 46357 | B89: =YEAR(A89) -> 2026 | C89: =MONTH(A89) -> 12 | D89: =BILANCIO!DA$24 -> 0 | E89: =BILANCIO!DB58 -> 0 | F89: =BILANCIO!DC$59 -> 0 | G89: =D89+E89+F89 -> 0
A90: 46388 | B90: =YEAR(A90) -> 2027 | C90: =MONTH(A90) -> 1 | D90: =BILANCIO!DB$24 -> 0 | E90: =BILANCIO!DC58 -> 0 | F90: =BILANCIO!DD$59 -> 0 | G90: =D90+E90+F90 -> 0
A91: 46419 | B91: =YEAR(A91) -> 2027 | C91: =MONTH(A91) -> 2 | D91: =BILANCIO!DC$24 -> 0 | E91: =BILANCIO!DD58 -> 0 | F91: =BILANCIO!DE$59 -> 0 | G91: =D91+E91+F91 -> 0
A92: 46447 | B92: =YEAR(A92) -> 2027 | C92: =MONTH(A92) -> 3 | D92: =BILANCIO!DD$24 -> 0 | E92: =BILANCIO!DE58 -> 0 | F92: =BILANCIO!DF$59 -> 0 | G92: =D92+E92+F92 -> 0
A93: 46478 | B93: =YEAR(A93) -> 2027 | C93: =MONTH(A93) -> 4 | D93: =BILANCIO!DE$24 -> 0 | E93: =BILANCIO!DF58 -> 0 | F93: =BILANCIO!DG$59 -> 0 | G93: =D93+E93+F93 -> 0
A94: 46508 | B94: =YEAR(A94) -> 2027 | C94: =MONTH(A94) -> 5 | D94: =BILANCIO!DF$24 -> 0 | E94: =BILANCIO!DG58 -> 0 | F94: =BILANCIO!DH$59 -> 0 | G94: =D94+E94+F94 -> 0
A95: 46539 | B95: =YEAR(A95) -> 2027 | C95: =MONTH(A95) -> 6 | D95: =BILANCIO!DG$24 -> 0 | E95: =BILANCIO!DH58 -> 0 | F95: =BILANCIO!DI$59 -> 0 | G95: =D95+E95+F95 -> 0
A96: 46569 | B96: =YEAR(A96) -> 2027 | C96: =MONTH(A96) -> 7 | D96: =BILANCIO!DH$24 -> 0 | E96: =BILANCIO!DI58 -> 0 | F96: =BILANCIO!DJ$59 -> 0 | G96: =D96+E96+F96 -> 0
A97: 46600 | B97: =YEAR(A97) -> 2027 | C97: =MONTH(A97) -> 8 | D97: =BILANCIO!DI$24 -> 0 | E97: =BILANCIO!DJ58 -> 0 | F97: =BILANCIO!DK$59 -> 0 | G97: =D97+E97+F97 -> 0
A98: 46631 | B98: =YEAR(A98) -> 2027 | C98: =MONTH(A98) -> 9 | D98: =BILANCIO!DJ$24 -> 0 | E98: =BILANCIO!DK58 -> 0 | F98: =BILANCIO!DL$59 -> 0 | G98: =D98+E98+F98 -> 0
A99: 46661 | B99: =YEAR(A99) -> 2027 | C99: =MONTH(A99) -> 10 | D99: =BILANCIO!DK$24 -> 0 | E99: =BILANCIO!DL58 -> 0 | F99: =BILANCIO!DM$59 -> 0 | G99: =D99+E99+F99 -> 0
A100: 46692 | B100: =YEAR(A100) -> 2027 | C100: =MONTH(A100) -> 11 | D100: =BILANCIO!DL$24 -> 0 | E100: =BILANCIO!DM58 -> 0 | F100: =BILANCIO!DN$59 -> 0 | G100: =D100+E100+F100 -> 0
...

Sheet Dettaglio Spese Generiche CC
A1: TIPOLOGIA | B1: MESE | C1: ANNO | D1: MESE | E1: COMPOSTO | F1: COMPOSTO | G1: TIPOLOGIA | H1: CATEGORIA | I1: IMPORTO | J1: RATA | K1: TRAMITE | L1: NOTE
A2: AZZURRA SNC | B2: SETTEMBRE | C2: 2026 | D2: =MATCH(B2,{"GENNAIO","FEBBRAIO","MARZO","APRILE","MAGGIO","GIUGNO","LUGLIO","AGOSTO","SETTEMBRE","OTTOBRE","NOVEMBRE","DICEMBRE"},0) -> 9 | E2: =CONCATENATE(,B2," ",C2) -> SETTEMBRE 2026 | F2: =CONCATENATE(D2," ",E2) -> 9 SETTEMBRE 2026 | G2: BAR E RISTORANTI | H2: =VLOOKUP(G2,CATEGORIE!$H$3:$I$55,2,FALSE) -> COSTO SVAGHI | I2: 32
A3: LITTLE HOLLAND BAARN | B3: SETTEMBRE | C3: 2026 | D3: =MATCH(B3,{"GENNAIO","FEBBRAIO","MARZO","APRILE","MAGGIO","GIUGNO","LUGLIO","AGOSTO","SETTEMBRE","OTTOBRE","NOVEMBRE","DICEMBRE"},0) -> 9 | E3: =CONCATENATE(,B3," ",C3) -> SETTEMBRE 2026 | F3: =CONCATENATE(D3," ",E3) -> 9 SETTEMBRE 2026 | G3: BAR E RISTORANTI | H3: =VLOOKUP(G3,CATEGORIE!$H$3:$I$55,2,FALSE) -> COSTO SVAGHI | I3: 6
A4: AMAZON | B4: SETTEMBRE | C4: 2026 | D4: =MATCH(B4,{"GENNAIO","FEBBRAIO","MARZO","APRILE","MAGGIO","GIUGNO","LUGLIO","AGOSTO","SETTEMBRE","OTTOBRE","NOVEMBRE","DICEMBRE"},0) -> 9 | E4: =CONCATENATE(,B4," ",C4) -> SETTEMBRE 2026 | F4: =CONCATENATE(D4," ",E4) -> 9 SETTEMBRE 2026 | G4: SPESE PER LA CASA | H4: =VLOOKUP(G4,CATEGORIE!$H$3:$I$55,2,FALSE) -> COSTO CASA | I4: 20 | L4: SPESA PAPA'
A5: POLIDORI DISTRIBUZIONE | B5: SETTEMBRE | C5: 2026 | D5: =MATCH(B5,{"GENNAIO","FEBBRAIO","MARZO","APRILE","MAGGIO","GIUGNO","LUGLIO","AGOSTO","SETTEMBRE","OTTOBRE","NOVEMBRE","DICEMBRE"},0) -> 9 | E5: =CONCATENATE(,B5," ",C5) -> SETTEMBRE 2026 | F5: =CONCATENATE(D5," ",E5) -> 9 SETTEMBRE 2026 | G5: MACCHINETTA AUTOMATICA | H5: =VLOOKUP(G5,CATEGORIE!$H$3:$I$55,2,FALSE) -> COSTO SOPRAVVIVENZA | I5: 5
A6: SAX TANKSTELLEN | B6: SETTEMBRE | C6: 2026 | D6: =MATCH(B6,{"GENNAIO","FEBBRAIO","MARZO","APRILE","MAGGIO","GIUGNO","LUGLIO","AGOSTO","SETTEMBRE","OTTOBRE","NOVEMBRE","DICEMBRE"},0) -> 9 | E6: =CONCATENATE(,B6," ",C6) -> SETTEMBRE 2026 | F6: =CONCATENATE(D6," ",E6) -> 9 SETTEMBRE 2026 | G6: TRASPORTI E PARCHEGGI | H6: =VLOOKUP(G6,CATEGORIE!$H$3:$I$55,2,FALSE) -> COSTO MOBILITA' | I6: 0.7
A7: REVOLUT | B7: SETTEMBRE | C7: 2026 | D7: =MATCH(B7,{"GENNAIO","FEBBRAIO","MARZO","APRILE","MAGGIO","GIUGNO","LUGLIO","AGOSTO","SETTEMBRE","OTTOBRE","NOVEMBRE","DICEMBRE"},0) -> 9 | E7: =CONCATENATE(,B7," ",C7) -> SETTEMBRE 2026 | F7: =CONCATENATE(D7," ",E7) -> 9 SETTEMBRE 2026 | G7: PRELIEVO CONTANTI | H7: =VLOOKUP(G7,CATEGORIE!$H$3:$I$55,2,FALSE) -> MOVIMENTI CONTO | I7: 30 | K7: REVOLUT
A8: POLIDORI DISTRIBUZIONE | B8: SETTEMBRE | C8: 2026 | D8: =MATCH(B8,{"GENNAIO","FEBBRAIO","MARZO","APRILE","MAGGIO","GIUGNO","LUGLIO","AGOSTO","SETTEMBRE","OTTOBRE","NOVEMBRE","DICEMBRE"},0) -> 9 | E8: =CONCATENATE(,B8," ",C8) -> SETTEMBRE 2026 | F8: =CONCATENATE(D8," ",E8) -> 9 SETTEMBRE 2026 | G8: MACCHINETTA AUTOMATICA | H8: =VLOOKUP(G8,CATEGORIE!$H$3:$I$55,2,FALSE) -> COSTO SOPRAVVIVENZA | I8: 5
A9: CDA LOUNGE BAR | B9: SETTEMBRE | C9: 2026 | D9: =MATCH(B9,{"GENNAIO","FEBBRAIO","MARZO","APRILE","MAGGIO","GIUGNO","LUGLIO","AGOSTO","SETTEMBRE","OTTOBRE","NOVEMBRE","DICEMBRE"},0) -> 9 | E9: =CONCATENATE(,B9," ",C9) -> SETTEMBRE 2026 | F9: =CONCATENATE(D9," ",E9) -> 9 SETTEMBRE 2026 | G9: BAR E RISTORANTI | H9: =VLOOKUP(G9,CATEGORIE!$H$3:$I$55,2,FALSE) -> COSTO SVAGHI | I9: 14.5
A10: POLIDORI DISTRIBUZIONE | B10: SETTEMBRE | C10: 2026 | D10: =MATCH(B10,{"GENNAIO","FEBBRAIO","MARZO","APRILE","MAGGIO","GIUGNO","LUGLIO","AGOSTO","SETTEMBRE","OTTOBRE","NOVEMBRE","DICEMBRE"},0) -> 9 | E10: =CONCATENATE(,B10," ",C10) -> SETTEMBRE 2026 | F10: =CONCATENATE(D10," ",E10) -> 9 SETTEMBRE 2026 | G10: MACCHINETTA AUTOMATICA | H10: =VLOOKUP(G10,CATEGORIE!$H$3:$I$55,2,FALSE) -> COSTO SOPRAVVIVENZA | I10: 5
A11: BOOKING | B11: SETTEMBRE | C11: 2026 | D11: =MATCH(B11,{"GENNAIO","FEBBRAIO","MARZO","APRILE","MAGGIO","GIUGNO","LUGLIO","AGOSTO","SETTEMBRE","OTTOBRE","NOVEMBRE","DICEMBRE"},0) -> 9 | E11: =CONCATENATE(,B11," ",C11) -> SETTEMBRE 2026 | F11: =CONCATENATE(D11," ",E11) -> 9 SETTEMBRE 2026 | G11: HOTEL & SERVIZI | H11: =VLOOKUP(G11,CATEGORIE!$H$3:$I$55,2,FALSE) -> COSTO VACANZE | I11: 324 | L11: Matrimonio CUC
A12: POLIDORI DISTRIBUZIONE | B12: SETTEMBRE | C12: 2026 | D12: =MATCH(B12,{"GENNAIO","FEBBRAIO","MARZO","APRILE","MAGGIO","GIUGNO","LUGLIO","AGOSTO","SETTEMBRE","OTTOBRE","NOVEMBRE","DICEMBRE"},0) -> 9 | E12: =CONCATENATE(,B12," ",C12) -> SETTEMBRE 2026 | F12: =CONCATENATE(D12," ",E12) -> 9 SETTEMBRE 2026 | G12: MACCHINETTA AUTOMATICA | H12: =VLOOKUP(G12,CATEGORIE!$H$3:$I$55,2,FALSE) -> COSTO SOPRAVVIVENZA | I12: 5
A13: MEDICENTER RONCHI | B13: SETTEMBRE | C13: 2026 | D13: =MATCH(B13,{"GENNAIO","FEBBRAIO","MARZO","APRILE","MAGGIO","GIUGNO","LUGLIO","AGOSTO","SETTEMBRE","OTTOBRE","NOVEMBRE","DICEMBRE"},0) -> 9 | E13: =CONCATENATE(,B13," ",C13) -> SETTEMBRE 2026 | F13: =CONCATENATE(D13," ",E13) -> 9 SETTEMBRE 2026 | G13: VISITE MEDICHE | H13: =VLOOKUP(G13,CATEGORIE!$H$3:$I$55,2,FALSE) -> COSTO SOPRAVVIVENZA | I13: 33
A14: ZAHRE BEER | B14: SETTEMBRE | C14: 2026 | D14: =MATCH(B14,{"GENNAIO","FEBBRAIO","MARZO","APRILE","MAGGIO","GIUGNO","LUGLIO","AGOSTO","SETTEMBRE","OTTOBRE","NOVEMBRE","DICEMBRE"},0) -> 9 | E14: =CONCATENATE(,B14," ",C14) -> SETTEMBRE 2026 | F14: =CONCATENATE(D14," ",E14) -> 9 SETTEMBRE 2026 | G14: BAR E RISTORANTI | H14: =VLOOKUP(G14,CATEGORIE!$H$3:$I$55,2,FALSE) -> COSTO SVAGHI | I14: 30
A15: PRO LOCO FOLGARIA (FRIULI DOC) | B15: SETTEMBRE | C15: 2026 | D15: =MATCH(B15,{"GENNAIO","FEBBRAIO","MARZO","APRILE","MAGGIO","GIUGNO","LUGLIO","AGOSTO","SETTEMBRE","OTTOBRE","NOVEMBRE","DICEMBRE"},0) -> 9 | E15: =CONCATENATE(,B15," ",C15) -> SETTEMBRE 2026 | F15: =CONCATENATE(D15," ",E15) -> 9 SETTEMBRE 2026 | G15: BAR E RISTORANTI | H15: =VLOOKUP(G15,CATEGORIE!$H$3:$I$55,2,FALSE) -> COSTO SVAGHI | I15: 68.5
A16: UFFICINA | B16: SETTEMBRE | C16: 2026 | D16: =MATCH(B16,{"GENNAIO","FEBBRAIO","MARZO","APRILE","MAGGIO","GIUGNO","LUGLIO","AGOSTO","SETTEMBRE","OTTOBRE","NOVEMBRE","DICEMBRE"},0) -> 9 | E16: =CONCATENATE(,B16," ",C16) -> SETTEMBRE 2026 | F16: =CONCATENATE(D16," ",E16) -> 9 SETTEMBRE 2026 | G16: BAR E RISTORANTI | H16: =VLOOKUP(G16,CATEGORIE!$H$3:$I$55,2,FALSE) -> COSTO SVAGHI | I16: 17
A17: POLIDORI DISTRIBUZIONE | B17: SETTEMBRE | C17: 2026 | D17: =MATCH(B17,{"GENNAIO","FEBBRAIO","MARZO","APRILE","MAGGIO","GIUGNO","LUGLIO","AGOSTO","SETTEMBRE","OTTOBRE","NOVEMBRE","DICEMBRE"},0) -> 9 | E17: =CONCATENATE(,B17," ",C17) -> SETTEMBRE 2026 | F17: =CONCATENATE(D17," ",E17) -> 9 SETTEMBRE 2026 | G17: MACCHINETTA AUTOMATICA | H17: =VLOOKUP(G17,CATEGORIE!$H$3:$I$55,2,FALSE) -> COSTO SOPRAVVIVENZA | I17: 5
A18: SPESA LIDL | B18: SETTEMBRE | C18: 2026 | D18: =MATCH(B18,{"GENNAIO","FEBBRAIO","MARZO","APRILE","MAGGIO","GIUGNO","LUGLIO","AGOSTO","SETTEMBRE","OTTOBRE","NOVEMBRE","DICEMBRE"},0) -> 9 | E18: =CONCATENATE(,B18," ",C18) -> SETTEMBRE 2026 | F18: =CONCATENATE(D18," ",E18) -> 9 SETTEMBRE 2026 | G18: ALIMENTARI | H18: =VLOOKUP(G18,CATEGORIE!$H$3:$I$55,2,FALSE) -> COSTO SOPRAVVIVENZA | I18: 37.76
A19: SPESA LIDL | B19: SETTEMBRE | C19: 2026 | D19: =MATCH(B19,{"GENNAIO","FEBBRAIO","MARZO","APRILE","MAGGIO","GIUGNO","LUGLIO","AGOSTO","SETTEMBRE","OTTOBRE","NOVEMBRE","DICEMBRE"},0) -> 9 | E19: =CONCATENATE(,B19," ",C19) -> SETTEMBRE 2026 | F19: =CONCATENATE(D19," ",E19) -> 9 SETTEMBRE 2026 | G19: ALIMENTARI | H19: =VLOOKUP(G19,CATEGORIE!$H$3:$I$55,2,FALSE) -> COSTO SOPRAVVIVENZA | I19: 13.28
A20: STABILIMENTO TIVOLI | B20: SETTEMBRE | C20: 2026 | D20: =MATCH(B20,{"GENNAIO","FEBBRAIO","MARZO","APRILE","MAGGIO","GIUGNO","LUGLIO","AGOSTO","SETTEMBRE","OTTOBRE","NOVEMBRE","DICEMBRE"},0) -> 9 | E20: =CONCATENATE(,B20," ",C20) -> SETTEMBRE 2026 | F20: =CONCATENATE(D20," ",E20) -> 9 SETTEMBRE 2026 | G20: BAR E RISTORANTI | H20: =VLOOKUP(G20,CATEGORIE!$H$3:$I$55,2,FALSE) -> COSTO SVAGHI | I20: 8
A21: LA TAVERNETTA PALMANOVA | B21: SETTEMBRE | C21: 2026 | D21: =MATCH(B21,{"GENNAIO","FEBBRAIO","MARZO","APRILE","MAGGIO","GIUGNO","LUGLIO","AGOSTO","SETTEMBRE","OTTOBRE","NOVEMBRE","DICEMBRE"},0) -> 9 | E21: =CONCATENATE(,B21," ",C21) -> SETTEMBRE 2026 | F21: =CONCATENATE(D21," ",E21) -> 9 SETTEMBRE 2026 | G21: BAR E RISTORANTI | H21: =VLOOKUP(G21,CATEGORIE!$H$3:$I$55,2,FALSE) -> COSTO SVAGHI | I21: 48.5
A22: AMAZON | B22: SETTEMBRE | C22: 2026 | D22: =MATCH(B22,{"GENNAIO","FEBBRAIO","MARZO","APRILE","MAGGIO","GIUGNO","LUGLIO","AGOSTO","SETTEMBRE","OTTOBRE","NOVEMBRE","DICEMBRE"},0) -> 9 | E22: =CONCATENATE(,B22," ",C22) -> SETTEMBRE 2026 | F22: =CONCATENATE(D22," ",E22) -> 9 SETTEMBRE 2026 | G22: ACQUISTI ONLINE | H22: =VLOOKUP(G22,CATEGORIE!$H$3:$I$55,2,FALSE) -> COSTO SFIZI | I22: 15.95 | L22: SPESA PAPA'
A23: POLIDORI DISTRIBUZIONE | B23: SETTEMBRE | C23: 2026 | D23: =MATCH(B23,{"GENNAIO","FEBBRAIO","MARZO","APRILE","MAGGIO","GIUGNO","LUGLIO","AGOSTO","SETTEMBRE","OTTOBRE","NOVEMBRE","DICEMBRE"},0) -> 9 | E23: =CONCATENATE(,B23," ",C23) -> SETTEMBRE 2026 | F23: =CONCATENATE(D23," ",E23) -> 9 SETTEMBRE 2026 | G23: MACCHINETTA AUTOMATICA | H23: =VLOOKUP(G23,CATEGORIE!$H$3:$I$55,2,FALSE) -> COSTO SOPRAVVIVENZA | I23: 5
A24: UFFICINA | B24: SETTEMBRE | C24: 2026 | D24: =MATCH(B24,{"GENNAIO","FEBBRAIO","MARZO","APRILE","MAGGIO","GIUGNO","LUGLIO","AGOSTO","SETTEMBRE","OTTOBRE","NOVEMBRE","DICEMBRE"},0) -> 9 | E24: =CONCATENATE(,B24," ",C24) -> SETTEMBRE 2026 | F24: =CONCATENATE(D24," ",E24) -> 9 SETTEMBRE 2026 | G24: BAR E RISTORANTI | H24: =VLOOKUP(G24,CATEGORIE!$H$3:$I$55,2,FALSE) -> COSTO SVAGHI | I24: 4
A25: AMAZON | B25: SETTEMBRE | C25: 2026 | D25: =MATCH(B25,{"GENNAIO","FEBBRAIO","MARZO","APRILE","MAGGIO","GIUGNO","LUGLIO","AGOSTO","SETTEMBRE","OTTOBRE","NOVEMBRE","DICEMBRE"},0) -> 9 | E25: =CONCATENATE(,B25," ",C25) -> SETTEMBRE 2026 | F25: =CONCATENATE(D25," ",E25) -> 9 SETTEMBRE 2026 | G25: SPESE PER LA CASA | H25: =VLOOKUP(G25,CATEGORIE!$H$3:$I$55,2,FALSE) -> COSTO CASA | I25: 75.9 | L25: SPESA PAPA'
A26: AMAZON | B26: SETTEMBRE | C26: 2026 | D26: =MATCH(B26,{"GENNAIO","FEBBRAIO","MARZO","APRILE","MAGGIO","GIUGNO","LUGLIO","AGOSTO","SETTEMBRE","OTTOBRE","NOVEMBRE","DICEMBRE"},0) -> 9 | E26: =CONCATENATE(,B26," ",C26) -> SETTEMBRE 2026 | F26: =CONCATENATE(D26," ",E26) -> 9 SETTEMBRE 2026 | G26: ACQUISTI ONLINE | H26: =VLOOKUP(G26,CATEGORIE!$H$3:$I$55,2,FALSE) -> COSTO SFIZI | I26: 21.99 | L26: REGALO DAVIDE TOSO
A27: AMAZON | B27: SETTEMBRE | C27: 2026 | D27: =MATCH(B27,{"GENNAIO","FEBBRAIO","MARZO","APRILE","MAGGIO","GIUGNO","LUGLIO","AGOSTO","SETTEMBRE","OTTOBRE","NOVEMBRE","DICEMBRE"},0) -> 9 | E27: =CONCATENATE(,B27," ",C27) -> SETTEMBRE 2026 | F27: =CONCATENATE(D27," ",E27) -> 9 SETTEMBRE 2026 | G27: ACQUISTI ONLINE | H27: =VLOOKUP(G27,CATEGORIE!$H$3:$I$55,2,FALSE) -> COSTO SFIZI | I27: 19.99 | L27: SPESA PAPA'
A28: AMAZON | B28: SETTEMBRE | C28: 2026 | D28: =MATCH(B28,{"GENNAIO","FEBBRAIO","MARZO","APRILE","MAGGIO","GIUGNO","LUGLIO","AGOSTO","SETTEMBRE","OTTOBRE","NOVEMBRE","DICEMBRE"},0) -> 9 | E28: =CONCATENATE(,B28," ",C28) -> SETTEMBRE 2026 | F28: =CONCATENATE(D28," ",E28) -> 9 SETTEMBRE 2026 | G28: ACQUISTI ONLINE | H28: =VLOOKUP(G28,CATEGORIE!$H$3:$I$55,2,FALSE) -> COSTO SFIZI | I28: 23.99 | L28: SPESA PAPA'
A29: AMAZON | B29: SETTEMBRE | C29: 2026 | D29: =MATCH(B29,{"GENNAIO","FEBBRAIO","MARZO","APRILE","MAGGIO","GIUGNO","LUGLIO","AGOSTO","SETTEMBRE","OTTOBRE","NOVEMBRE","DICEMBRE"},0) -> 9 | E29: =CONCATENATE(,B29," ",C29) -> SETTEMBRE 2026 | F29: =CONCATENATE(D29," ",E29) -> 9 SETTEMBRE 2026 | G29: ACQUISTI ONLINE | H29: =VLOOKUP(G29,CATEGORIE!$H$3:$I$55,2,FALSE) -> COSTO SFIZI | I29: 19.5
A30: REVOLUT | B30: SETTEMBRE | C30: 2026 | D30: =MATCH(B30,{"GENNAIO","FEBBRAIO","MARZO","APRILE","MAGGIO","GIUGNO","LUGLIO","AGOSTO","SETTEMBRE","OTTOBRE","NOVEMBRE","DICEMBRE"},0) -> 9 | E30: =CONCATENATE(,B30," ",C30) -> SETTEMBRE 2026 | F30: =CONCATENATE(D30," ",E30) -> 9 SETTEMBRE 2026 | G30: PRELIEVO CONTANTI | H30: =VLOOKUP(G30,CATEGORIE!$H$3:$I$55,2,FALSE) -> MOVIMENTI CONTO | I30: 600 | K30: REVOLUT
A31: SPESA ENEL | B31: SETTEMBRE | C31: 2026 | D31: =MATCH(B31,{"GENNAIO","FEBBRAIO","MARZO","APRILE","MAGGIO","GIUGNO","LUGLIO","AGOSTO","SETTEMBRE","OTTOBRE","NOVEMBRE","DICEMBRE"},0) -> 9 | E31: =CONCATENATE(,B31," ",C31) -> SETTEMBRE 2026 | F31: =CONCATENATE(D31," ",E31) -> 9 SETTEMBRE 2026 | G31: SPESE PER LA CASA | H31: =VLOOKUP(G31,CATEGORIE!$H$3:$I$55,2,FALSE) -> COSTO CASA | I31: 21.23 | L31: SPESA GAS
A32: PIZZERIA CHICHIBIO | B32: SETTEMBRE | C32: 2026 | D32: =MATCH(B32,{"GENNAIO","FEBBRAIO","MARZO","APRILE","MAGGIO","GIUGNO","LUGLIO","AGOSTO","SETTEMBRE","OTTOBRE","NOVEMBRE","DICEMBRE"},0) -> 9 | E32: =CONCATENATE(,B32," ",C32) -> SETTEMBRE 2026 | F32: =CONCATENATE(D32," ",E32) -> 9 SETTEMBRE 2026 | G32: BAR E RISTORANTI | H32: =VLOOKUP(G32,CATEGORIE!$H$3:$I$55,2,FALSE) -> COSTO SVAGHI | I32: 39
A33: SPESA VISOTTO | B33: SETTEMBRE | C33: 2026 | D33: =MATCH(B33,{"GENNAIO","FEBBRAIO","MARZO","APRILE","MAGGIO","GIUGNO","LUGLIO","AGOSTO","SETTEMBRE","OTTOBRE","NOVEMBRE","DICEMBRE"},0) -> 9 | E33: =CONCATENATE(,B33," ",C33) -> SETTEMBRE 2026 | F33: =CONCATENATE(D33," ",E33) -> 9 SETTEMBRE 2026 | G33: ALIMENTARI | H33: =VLOOKUP(G33,CATEGORIE!$H$3:$I$55,2,FALSE) -> COSTO SOPRAVVIVENZA | I33: 36.04
A34: AMAZON | B34: SETTEMBRE | C34: 2026 | D34: =MATCH(B34,{"GENNAIO","FEBBRAIO","MARZO","APRILE","MAGGIO","GIUGNO","LUGLIO","AGOSTO","SETTEMBRE","OTTOBRE","NOVEMBRE","DICEMBRE"},0) -> 9 | E34: =CONCATENATE(,B34," ",C34) -> SETTEMBRE 2026 | F34: =CONCATENATE(D34," ",E34) -> 9 SETTEMBRE 2026 | G34: ACQUISTI ONLINE | H34: =VLOOKUP(G34,CATEGORIE!$H$3:$I$55,2,FALSE) -> COSTO SFIZI | I34: 73.8 | J34: 5/5 | K34: AMAZON | L34: TV PAPA'
A35: AMAZON | B35: SETTEMBRE | C35: 2026 | D35: =MATCH(B35,{"GENNAIO","FEBBRAIO","MARZO","APRILE","MAGGIO","GIUGNO","LUGLIO","AGOSTO","SETTEMBRE","OTTOBRE","NOVEMBRE","DICEMBRE"},0) -> 9 | E35: =CONCATENATE(,B35," ",C35) -> SETTEMBRE 2026 | F35: =CONCATENATE(D35," ",E35) -> 9 SETTEMBRE 2026 | G35: ACQUISTI ONLINE | H35: =VLOOKUP(G35,CATEGORIE!$H$3:$I$55,2,FALSE) -> COSTO SFIZI | I35: 45.75 | J35: 3/5 | K35: AMAZON | L35: MOVA
A36: AMAZON | B36: SETTEMBRE | C36: 2026 | D36: =MATCH(B36,{"GENNAIO","FEBBRAIO","MARZO","APRILE","MAGGIO","GIUGNO","LUGLIO","AGOSTO","SETTEMBRE","OTTOBRE","NOVEMBRE","DICEMBRE"},0) -> 9 | E36: =CONCATENATE(,B36," ",C36) -> SETTEMBRE 2026 | F36: =CONCATENATE(D36," ",E36) -> 9 SETTEMBRE 2026 | G36: SPESE PER LA CASA | H36: =VLOOKUP(G36,CATEGORIE!$H$3:$I$55,2,FALSE) -> COSTO CASA | I36: 23.9
A37: REVOLUT | B37: SETTEMBRE | C37: 2026 | D37: =MATCH(B37,{"GENNAIO","FEBBRAIO","MARZO","APRILE","MAGGIO","GIUGNO","LUGLIO","AGOSTO","SETTEMBRE","OTTOBRE","NOVEMBRE","DICEMBRE"},0) -> 9 | E37: =CONCATENATE(,B37," ",C37) -> SETTEMBRE 2026 | F37: =CONCATENATE(D37," ",E37) -> 9 SETTEMBRE 2026 | G37: PRELIEVO CONTANTI | H37: =VLOOKUP(G37,CATEGORIE!$H$3:$I$55,2,FALSE) -> MOVIMENTI CONTO | I37: 300 | K37: REVOLUT
A38: AMAZON | B38: SETTEMBRE | C38: 2026 | D38: =MATCH(B38,{"GENNAIO","FEBBRAIO","MARZO","APRILE","MAGGIO","GIUGNO","LUGLIO","AGOSTO","SETTEMBRE","OTTOBRE","NOVEMBRE","DICEMBRE"},0) -> 9 | E38: =CONCATENATE(,B38," ",C38) -> SETTEMBRE 2026 | F38: =CONCATENATE(D38," ",E38) -> 9 SETTEMBRE 2026 | G38: SPESE PER LA CASA | H38: =VLOOKUP(G38,CATEGORIE!$H$3:$I$55,2,FALSE) -> COSTO CASA | I38: 56.9 | L38: SPESA PAPA'
A39: SA DI TAPPO | B39: SETTEMBRE | C39: 2026 | D39: =MATCH(B39,{"GENNAIO","FEBBRAIO","MARZO","APRILE","MAGGIO","GIUGNO","LUGLIO","AGOSTO","SETTEMBRE","OTTOBRE","NOVEMBRE","DICEMBRE"},0) -> 9 | E39: =CONCATENATE(,B39," ",C39) -> SETTEMBRE 2026 | F39: =CONCATENATE(D39," ",E39) -> 9 SETTEMBRE 2026 | G39: BAR E RISTORANTI | H39: =VLOOKUP(G39,CATEGORIE!$H$3:$I$55,2,FALSE) -> COSTO SVAGHI | I39: 7
A40: POLIDORI DISTRIBUZIONE | B40: SETTEMBRE | C40: 2026 | D40: =MATCH(B40,{"GENNAIO","FEBBRAIO","MARZO","APRILE","MAGGIO","GIUGNO","LUGLIO","AGOSTO","SETTEMBRE","OTTOBRE","NOVEMBRE","DICEMBRE"},0) -> 9 | E40: =CONCATENATE(,B40," ",C40) -> SETTEMBRE 2026 | F40: =CONCATENATE(D40," ",E40) -> 9 SETTEMBRE 2026 | G40: MACCHINETTA AUTOMATICA | H40: =VLOOKUP(G40,CATEGORIE!$H$3:$I$55,2,FALSE) -> COSTO SOPRAVVIVENZA | I40: 5
A41: GRUPPO NEGOZI VILLESSE | B41: SETTEMBRE | C41: 2026 | D41: =MATCH(B41,{"GENNAIO","FEBBRAIO","MARZO","APRILE","MAGGIO","GIUGNO","LUGLIO","AGOSTO","SETTEMBRE","OTTOBRE","NOVEMBRE","DICEMBRE"},0) -> 9 | E41: =CONCATENATE(,B41," ",C41) -> SETTEMBRE 2026 | F41: =CONCATENATE(D41," ",E41) -> 9 SETTEMBRE 2026 | G41: BAR E RISTORANTI | H41: =VLOOKUP(G41,CATEGORIE!$H$3:$I$55,2,FALSE) -> COSTO SVAGHI | I41: 10.9
A42: TABACCHERIA BARBINI | B42: AGOSTO | C42: 2026 | D42: =MATCH(B42,{"GENNAIO","FEBBRAIO","MARZO","APRILE","MAGGIO","GIUGNO","LUGLIO","AGOSTO","SETTEMBRE","OTTOBRE","NOVEMBRE","DICEMBRE"},0) -> 8 | E42: =CONCATENATE(,B42," ",C42) -> AGOSTO 2026 | F42: =CONCATENATE(D42," ",E42) -> 8 AGOSTO 2026 | G42: BAR E RISTORANTI | H42: =VLOOKUP(G42,CATEGORIE!$H$3:$I$55,2,FALSE) -> COSTO SVAGHI | I42: 5.8
A43: POLIDORI DISTRIBUZIONE | B43: AGOSTO | C43: 2026 | D43: =MATCH(B43,{"GENNAIO","FEBBRAIO","MARZO","APRILE","MAGGIO","GIUGNO","LUGLIO","AGOSTO","SETTEMBRE","OTTOBRE","NOVEMBRE","DICEMBRE"},0) -> 8 | E43: =CONCATENATE(,B43," ",C43) -> AGOSTO 2026 | F43: =CONCATENATE(D43," ",E43) -> 8 AGOSTO 2026 | G43: MACCHINETTA AUTOMATICA | H43: =VLOOKUP(G43,CATEGORIE!$H$3:$I$55,2,FALSE) -> COSTO SOPRAVVIVENZA | I43: 5
A44: AMAZON | B44: AGOSTO | C44: 2026 | D44: =MATCH(B44,{"GENNAIO","FEBBRAIO","MARZO","APRILE","MAGGIO","GIUGNO","LUGLIO","AGOSTO","SETTEMBRE","OTTOBRE","NOVEMBRE","DICEMBRE"},0) -> 8 | E44: =CONCATENATE(,B44," ",C44) -> AGOSTO 2026 | F44: =CONCATENATE(D44," ",E44) -> 8 AGOSTO 2026 | G44: ACQUISTI ONLINE | H44: =VLOOKUP(G44,CATEGORIE!$H$3:$I$55,2,FALSE) -> COSTO SFIZI | I44: 20
A45: SPESA ENEL | B45: AGOSTO | C45: 2026 | D45: =MATCH(B45,{"GENNAIO","FEBBRAIO","MARZO","APRILE","MAGGIO","GIUGNO","LUGLIO","AGOSTO","SETTEMBRE","OTTOBRE","NOVEMBRE","DICEMBRE"},0) -> 8 | E45: =CONCATENATE(,B45," ",C45) -> AGOSTO 2026 | F45: =CONCATENATE(D45," ",E45) -> 8 AGOSTO 2026 | G45: SPESE PER LA CASA | H45: =VLOOKUP(G45,CATEGORIE!$H$3:$I$55,2,FALSE) -> COSTO CASA | I45: 92.14 | L45: SPESA ENERGIA
A46: AMAZON | B46: AGOSTO | C46: 2026 | D46: =MATCH(B46,{"GENNAIO","FEBBRAIO","MARZO","APRILE","MAGGIO","GIUGNO","LUGLIO","AGOSTO","SETTEMBRE","OTTOBRE","NOVEMBRE","DICEMBRE"},0) -> 8 | E46: =CONCATENATE(,B46," ",C46) -> AGOSTO 2026 | F46: =CONCATENATE(D46," ",E46) -> 8 AGOSTO 2026 | G46: ACQUISTI ONLINE | H46: =VLOOKUP(G46,CATEGORIE!$H$3:$I$55,2,FALSE) -> COSTO SFIZI | I46: 10.99
A47: MONDO LAVAGGIO | B47: AGOSTO | C47: 2026 | D47: =MATCH(B47,{"GENNAIO","FEBBRAIO","MARZO","APRILE","MAGGIO","GIUGNO","LUGLIO","AGOSTO","SETTEMBRE","OTTOBRE","NOVEMBRE","DICEMBRE"},0) -> 8 | E47: =CONCATENATE(,B47," ",C47) -> AGOSTO 2026 | F47: =CONCATENATE(D47," ",E47) -> 8 AGOSTO 2026 | G47: SPESE PER LA MACCHINA | H47: =VLOOKUP(G47,CATEGORIE!$H$3:$I$55,2,FALSE) -> COSTO MOBILITA' | I47: 12
A48: SPESA VISOTTO | B48: AGOSTO | C48: 2026 | D48: =MATCH(B48,{"GENNAIO","FEBBRAIO","MARZO","APRILE","MAGGIO","GIUGNO","LUGLIO","AGOSTO","SETTEMBRE","OTTOBRE","NOVEMBRE","DICEMBRE"},0) -> 8 | E48: =CONCATENATE(,B48," ",C48) -> AGOSTO 2026 | F48: =CONCATENATE(D48," ",E48) -> 8 AGOSTO 2026 | G48: ALIMENTARI | H48: =VLOOKUP(G48,CATEGORIE!$H$3:$I$55,2,FALSE) -> COSTO SOPRAVVIVENZA | I48: 5.73
A49: PRISHOP (MEGA HOME) | B49: AGOSTO | C49: 2026 | D49: =MATCH(B49,{"GENNAIO","FEBBRAIO","MARZO","APRILE","MAGGIO","GIUGNO","LUGLIO","AGOSTO","SETTEMBRE","OTTOBRE","NOVEMBRE","DICEMBRE"},0) -> 8 | E49: =CONCATENATE(,B49," ",C49) -> AGOSTO 2026 | F49: =CONCATENATE(D49," ",E49) -> 8 AGOSTO 2026 | G49: SPESE PER LA CASA | H49: =VLOOKUP(G49,CATEGORIE!$H$3:$I$55,2,FALSE) -> COSTO CASA | I49: 1.8
A50: PARCOMETRO CERVIGNANO | B50: AGOSTO | C50: 2026 | D50: =MATCH(B50,{"GENNAIO","FEBBRAIO","MARZO","APRILE","MAGGIO","GIUGNO","LUGLIO","AGOSTO","SETTEMBRE","OTTOBRE","NOVEMBRE","DICEMBRE"},0) -> 8 | E50: =CONCATENATE(,B50," ",C50) -> AGOSTO 2026 | F50: =CONCATENATE(D50," ",E50) -> 8 AGOSTO 2026 | G50: TRASPORTI E PARCHEGGI | H50: =VLOOKUP(G50,CATEGORIE!$H$3:$I$55,2,FALSE) -> COSTO MOBILITA' | I50: 0.95
A51: VERGANO ROMA TERMINI | B51: AGOSTO | C51: 2026 | D51: =MATCH(B51,{"GENNAIO","FEBBRAIO","MARZO","APRILE","MAGGIO","GIUGNO","LUGLIO","AGOSTO","SETTEMBRE","OTTOBRE","NOVEMBRE","DICEMBRE"},0) -> 8 | E51: =CONCATENATE(,B51," ",C51) -> AGOSTO 2026 | F51: =CONCATENATE(D51," ",E51) -> 8 AGOSTO 2026 | G51: BAR E RISTORANTI | H51: =VLOOKUP(G51,CATEGORIE!$H$3:$I$55,2,FALSE) -> COSTO SVAGHI | I51: 12.5 | L51: Viaggio Costiera Amalfitana 26
A52: SALUMERIA PELUSO SALERNO | B52: AGOSTO | C52: 2026 | D52: =MATCH(B52,{"GENNAIO","FEBBRAIO","MARZO","APRILE","MAGGIO","GIUGNO","LUGLIO","AGOSTO","SETTEMBRE","OTTOBRE","NOVEMBRE","DICEMBRE"},0) -> 8 | E52: =CONCATENATE(,B52," ",C52) -> AGOSTO 2026 | F52: =CONCATENATE(D52," ",E52) -> 8 AGOSTO 2026 | G52: BAR E RISTORANTI | H52: =VLOOKUP(G52,CATEGORIE!$H$3:$I$55,2,FALSE) -> COSTO SVAGHI | I52: 9.6 | L52: Viaggio Costiera Amalfitana 26
A53: AMALFI ART | B53: AGOSTO | C53: 2026 | D53: =MATCH(B53,{"GENNAIO","FEBBRAIO","MARZO","APRILE","MAGGIO","GIUGNO","LUGLIO","AGOSTO","SETTEMBRE","OTTOBRE","NOVEMBRE","DICEMBRE"},0) -> 8 | E53: =CONCATENATE(,B53," ",C53) -> AGOSTO 2026 | F53: =CONCATENATE(D53," ",E53) -> 8 AGOSTO 2026 | G53: REGALI | H53: =VLOOKUP(G53,CATEGORIE!$H$3:$I$55,2,FALSE) -> COSTO SFIZI | I53: 8.5 | L53: Viaggio Costiera Amalfitana 26
A54: SAPORI CETARESI | B54: AGOSTO | C54: 2026 | D54: =MATCH(B54,{"GENNAIO","FEBBRAIO","MARZO","APRILE","MAGGIO","GIUGNO","LUGLIO","AGOSTO","SETTEMBRE","OTTOBRE","NOVEMBRE","DICEMBRE"},0) -> 8 | E54: =CONCATENATE(,B54," ",C54) -> AGOSTO 2026 | F54: =CONCATENATE(D54," ",E54) -> 8 AGOSTO 2026 | G54: REGALI | H54: =VLOOKUP(G54,CATEGORIE!$H$3:$I$55,2,FALSE) -> COSTO SFIZI | I54: 10.5 | L54: Viaggio Costiera Amalfitana 26
A55: O,CHALET CETARA | B55: AGOSTO | C55: 2026 | D55: =MATCH(B55,{"GENNAIO","FEBBRAIO","MARZO","APRILE","MAGGIO","GIUGNO","LUGLIO","AGOSTO","SETTEMBRE","OTTOBRE","NOVEMBRE","DICEMBRE"},0) -> 8 | E55: =CONCATENATE(,B55," ",C55) -> AGOSTO 2026 | F55: =CONCATENATE(D55," ",E55) -> 8 AGOSTO 2026 | G55: BAR E RISTORANTI | H55: =VLOOKUP(G55,CATEGORIE!$H$3:$I$55,2,FALSE) -> COSTO SVAGHI | I55: 20 | L55: Viaggio Costiera Amalfitana 26
A56: VILLLA AMORE ROBERTO RAVELLO | B56: AGOSTO | C56: 2026 | D56: =MATCH(B56,{"GENNAIO","FEBBRAIO","MARZO","APRILE","MAGGIO","GIUGNO","LUGLIO","AGOSTO","SETTEMBRE","OTTOBRE","NOVEMBRE","DICEMBRE"},0) -> 8 | E56: =CONCATENATE(,B56," ",C56) -> AGOSTO 2026 | F56: =CONCATENATE(D56," ",E56) -> 8 AGOSTO 2026 | G56: BAR E RISTORANTI | H56: =VLOOKUP(G56,CATEGORIE!$H$3:$I$55,2,FALSE) -> COSTO SVAGHI | I56: 44 | L56: Viaggio Costiera Amalfitana 26
A57: CITTA CAPRI | B57: AGOSTO | C57: 2026 | D57: =MATCH(B57,{"GENNAIO","FEBBRAIO","MARZO","APRILE","MAGGIO","GIUGNO","LUGLIO","AGOSTO","SETTEMBRE","OTTOBRE","NOVEMBRE","DICEMBRE"},0) -> 8 | E57: =CONCATENATE(,B57," ",C57) -> AGOSTO 2026 | F57: =CONCATENATE(D57," ",E57) -> 8 AGOSTO 2026 | G57: HOTEL & SERVIZI | H57: =VLOOKUP(G57,CATEGORIE!$H$3:$I$55,2,FALSE) -> COSTO VACANZE | I57: 5 | L57: Viaggio Costiera Amalfitana 26
A58: OASI POSITANO | B58: AGOSTO | C58: 2026 | D58: =MATCH(B58,{"GENNAIO","FEBBRAIO","MARZO","APRILE","MAGGIO","GIUGNO","LUGLIO","AGOSTO","SETTEMBRE","OTTOBRE","NOVEMBRE","DICEMBRE"},0) -> 8 | E58: =CONCATENATE(,B58," ",C58) -> AGOSTO 2026 | F58: =CONCATENATE(D58," ",E58) -> 8 AGOSTO 2026 | G58: VESTITI | H58: =VLOOKUP(G58,CATEGORIE!$H$3:$I$55,2,FALSE) -> COSTO SFIZI | I58: 10 | L58: Viaggio Costiera Amalfitana 26
A59: DA VINCENZO POSITANO | B59: AGOSTO | C59: 2026 | D59: =MATCH(B59,{"GENNAIO","FEBBRAIO","MARZO","APRILE","MAGGIO","GIUGNO","LUGLIO","AGOSTO","SETTEMBRE","OTTOBRE","NOVEMBRE","DICEMBRE"},0) -> 8 | E59: =CONCATENATE(,B59," ",C59) -> AGOSTO 2026 | F59: =CONCATENATE(D59," ",E59) -> 8 AGOSTO 2026 | G59: BAR E RISTORANTI | H59: =VLOOKUP(G59,CATEGORIE!$H$3:$I$55,2,FALSE) -> COSTO SVAGHI | I59: 112 | L59: Viaggio Costiera Amalfitana 26
A60: TRAVEL MAR SALERNO | B60: AGOSTO | C60: 2026 | D60: =MATCH(B60,{"GENNAIO","FEBBRAIO","MARZO","APRILE","MAGGIO","GIUGNO","LUGLIO","AGOSTO","SETTEMBRE","OTTOBRE","NOVEMBRE","DICEMBRE"},0) -> 8 | E60: =CONCATENATE(,B60," ",C60) -> AGOSTO 2026 | F60: =CONCATENATE(D60," ",E60) -> 8 AGOSTO 2026 | G60: TRASPORTI E PARCHEGGI | H60: =VLOOKUP(G60,CATEGORIE!$H$3:$I$55,2,FALSE) -> COSTO MOBILITA' | I60: 24 | L60: Viaggio Costiera Amalfitana 26
A61: RELAY ROMA TERMINI | B61: AGOSTO | C61: 2026 | D61: =MATCH(B61,{"GENNAIO","FEBBRAIO","MARZO","APRILE","MAGGIO","GIUGNO","LUGLIO","AGOSTO","SETTEMBRE","OTTOBRE","NOVEMBRE","DICEMBRE"},0) -> 8 | E61: =CONCATENATE(,B61," ",C61) -> AGOSTO 2026 | F61: =CONCATENATE(D61," ",E61) -> 8 AGOSTO 2026 | G61: BAR E RISTORANTI | H61: =VLOOKUP(G61,CATEGORIE!$H$3:$I$55,2,FALSE) -> COSTO SVAGHI | I61: 11.95 | L61: Viaggio Costiera Amalfitana 26
A62: DIDON STORE | B62: AGOSTO | C62: 2026 | D62: =MATCH(B62,{"GENNAIO","FEBBRAIO","MARZO","APRILE","MAGGIO","GIUGNO","LUGLIO","AGOSTO","SETTEMBRE","OTTOBRE","NOVEMBRE","DICEMBRE"},0) -> 8 | E62: =CONCATENATE(,B62," ",C62) -> AGOSTO 2026 | F62: =CONCATENATE(D62," ",E62) -> 8 AGOSTO 2026 | G62: SPESE PER LA CASA | H62: =VLOOKUP(G62,CATEGORIE!$H$3:$I$55,2,FALSE) -> COSTO CASA | I62: 23.39
A63: ANDRIAN MASSIMO | B63: AGOSTO | C63: 2026 | D63: =MATCH(B63,{"GENNAIO","FEBBRAIO","MARZO","APRILE","MAGGIO","GIUGNO","LUGLIO","AGOSTO","SETTEMBRE","OTTOBRE","NOVEMBRE","DICEMBRE"},0) -> 8 | E63: =CONCATENATE(,B63," ",C63) -> AGOSTO 2026 | F63: =CONCATENATE(D63," ",E63) -> 8 AGOSTO 2026 | G63: BAR E RISTORANTI | H63: =VLOOKUP(G63,CATEGORIE!$H$3:$I$55,2,FALSE) -> COSTO SVAGHI | I63: 11.2
A64: TBT FOOD | B64: AGOSTO | C64: 2026 | D64: =MATCH(B64,{"GENNAIO","FEBBRAIO","MARZO","APRILE","MAGGIO","GIUGNO","LUGLIO","AGOSTO","SETTEMBRE","OTTOBRE","NOVEMBRE","DICEMBRE"},0) -> 8 | E64: =CONCATENATE(,B64," ",C64) -> AGOSTO 2026 | F64: =CONCATENATE(D64," ",E64) -> 8 AGOSTO 2026 | G64: BAR E RISTORANTI | H64: =VLOOKUP(G64,CATEGORIE!$H$3:$I$55,2,FALSE) -> COSTO SVAGHI | I64: 13.4
A65: TABACCHERIA BARBINI | B65: AGOSTO | C65: 2026 | D65: =MATCH(B65,{"GENNAIO","FEBBRAIO","MARZO","APRILE","MAGGIO","GIUGNO","LUGLIO","AGOSTO","SETTEMBRE","OTTOBRE","NOVEMBRE","DICEMBRE"},0) -> 8 | E65: =CONCATENATE(,B65," ",C65) -> AGOSTO 2026 | F65: =CONCATENATE(D65," ",E65) -> 8 AGOSTO 2026 | G65: BAR E RISTORANTI | H65: =VLOOKUP(G65,CATEGORIE!$H$3:$I$55,2,FALSE) -> COSTO SVAGHI | I65: 5.8
A66: POLIDORI DISTRIBUZIONE | B66: AGOSTO | C66: 2026 | D66: =MATCH(B66,{"GENNAIO","FEBBRAIO","MARZO","APRILE","MAGGIO","GIUGNO","LUGLIO","AGOSTO","SETTEMBRE","OTTOBRE","NOVEMBRE","DICEMBRE"},0) -> 8 | E66: =CONCATENATE(,B66," ",C66) -> AGOSTO 2026 | F66: =CONCATENATE(D66," ",E66) -> 8 AGOSTO 2026 | G66: MACCHINETTA AUTOMATICA | H66: =VLOOKUP(G66,CATEGORIE!$H$3:$I$55,2,FALSE) -> COSTO SOPRAVVIVENZA | I66: 5
A67: BOOKING | B67: AGOSTO | C67: 2026 | D67: =MATCH(B67,{"GENNAIO","FEBBRAIO","MARZO","APRILE","MAGGIO","GIUGNO","LUGLIO","AGOSTO","SETTEMBRE","OTTOBRE","NOVEMBRE","DICEMBRE"},0) -> 8 | E67: =CONCATENATE(,B67," ",C67) -> AGOSTO 2026 | F67: =CONCATENATE(D67," ",E67) -> 8 AGOSTO 2026 | G67: HOTEL & SERVIZI | H67: =VLOOKUP(G67,CATEGORIE!$H$3:$I$55,2,FALSE) -> COSTO VACANZE | I67: 1349 | L67: Viaggio Costiera Amalfitana 26
A68: AMAZON | B68: AGOSTO | C68: 2026 | D68: =MATCH(B68,{"GENNAIO","FEBBRAIO","MARZO","APRILE","MAGGIO","GIUGNO","LUGLIO","AGOSTO","SETTEMBRE","OTTOBRE","NOVEMBRE","DICEMBRE"},0) -> 8 | E68: =CONCATENATE(,B68," ",C68) -> AGOSTO 2026 | F68: =CONCATENATE(D68," ",E68) -> 8 AGOSTO 2026 | G68: ACQUISTI ONLINE | H68: =VLOOKUP(G68,CATEGORIE!$H$3:$I$55,2,FALSE) -> COSTO SFIZI | I68: 73.8 | J68: 4/5 | K68: AMAZON | L68: TV PAPA'
A69: AMAZON | B69: AGOSTO | C69: 2026 | D69: =MATCH(B69,{"GENNAIO","FEBBRAIO","MARZO","APRILE","MAGGIO","GIUGNO","LUGLIO","AGOSTO","SETTEMBRE","OTTOBRE","NOVEMBRE","DICEMBRE"},0) -> 8 | E69: =CONCATENATE(,B69," ",C69) -> AGOSTO 2026 | F69: =CONCATENATE(D69," ",E69) -> 8 AGOSTO 2026 | G69: ACQUISTI ONLINE | H69: =VLOOKUP(G69,CATEGORIE!$H$3:$I$55,2,FALSE) -> COSTO SFIZI | I69: 20.9 | K69: AMAZON
A70: SPESA LIDL | B70: AGOSTO | C70: 2026 | D70: =MATCH(B70,{"GENNAIO","FEBBRAIO","MARZO","APRILE","MAGGIO","GIUGNO","LUGLIO","AGOSTO","SETTEMBRE","OTTOBRE","NOVEMBRE","DICEMBRE"},0) -> 8 | E70: =CONCATENATE(,B70," ",C70) -> AGOSTO 2026 | F70: =CONCATENATE(D70," ",E70) -> 8 AGOSTO 2026 | G70: ALIMENTARI | H70: =VLOOKUP(G70,CATEGORIE!$H$3:$I$55,2,FALSE) -> COSTO SOPRAVVIVENZA | I70: 17.87
A71: UFFICINA | B71: AGOSTO | C71: 2026 | D71: =MATCH(B71,{"GENNAIO","FEBBRAIO","MARZO","APRILE","MAGGIO","GIUGNO","LUGLIO","AGOSTO","SETTEMBRE","OTTOBRE","NOVEMBRE","DICEMBRE"},0) -> 8 | E71: =CONCATENATE(,B71," ",C71) -> AGOSTO 2026 | F71: =CONCATENATE(D71," ",E71) -> 8 AGOSTO 2026 | G71: BAR E RISTORANTI | H71: =VLOOKUP(G71,CATEGORIE!$H$3:$I$55,2,FALSE) -> COSTO SVAGHI | I71: 39.5
A72: AMAZON | B72: AGOSTO | C72: 2026 | D72: =MATCH(B72,{"GENNAIO","FEBBRAIO","MARZO","APRILE","MAGGIO","GIUGNO","LUGLIO","AGOSTO","SETTEMBRE","OTTOBRE","NOVEMBRE","DICEMBRE"},0) -> 8 | E72: =CONCATENATE(,B72," ",C72) -> AGOSTO 2026 | F72: =CONCATENATE(D72," ",E72) -> 8 AGOSTO 2026 | G72: ACQUISTI ONLINE | H72: =VLOOKUP(G72,CATEGORIE!$H$3:$I$55,2,FALSE) -> COSTO SFIZI | I72: 12 | K72: AMAZON
A73: SA DI TAPPO | B73: AGOSTO | C73: 2026 | D73: =MATCH(B73,{"GENNAIO","FEBBRAIO","MARZO","APRILE","MAGGIO","GIUGNO","LUGLIO","AGOSTO","SETTEMBRE","OTTOBRE","NOVEMBRE","DICEMBRE"},0) -> 8 | E73: =CONCATENATE(,B73," ",C73) -> AGOSTO 2026 | F73: =CONCATENATE(D73," ",E73) -> 8 AGOSTO 2026 | G73: BAR E RISTORANTI | H73: =VLOOKUP(G73,CATEGORIE!$H$3:$I$104,2,FALSE) -> COSTO SVAGHI | I73: 9.5
A74: SA DI TAPPO | B74: AGOSTO | C74: 2026 | D74: =MATCH(B74,{"GENNAIO","FEBBRAIO","MARZO","APRILE","MAGGIO","GIUGNO","LUGLIO","AGOSTO","SETTEMBRE","OTTOBRE","NOVEMBRE","DICEMBRE"},0) -> 8 | E74: =CONCATENATE(,B74," ",C74) -> AGOSTO 2026 | F74: =CONCATENATE(D74," ",E74) -> 8 AGOSTO 2026 | G74: BAR E RISTORANTI | H74: =VLOOKUP(G74,CATEGORIE!$H$3:$I$104,2,FALSE) -> COSTO SVAGHI | I74: 26
A75: AMAZON | B75: AGOSTO | C75: 2026 | D75: =MATCH(B75,{"GENNAIO","FEBBRAIO","MARZO","APRILE","MAGGIO","GIUGNO","LUGLIO","AGOSTO","SETTEMBRE","OTTOBRE","NOVEMBRE","DICEMBRE"},0) -> 8 | E75: =CONCATENATE(,B75," ",C75) -> AGOSTO 2026 | F75: =CONCATENATE(D75," ",E75) -> 8 AGOSTO 2026 | G75: ACQUISTI ONLINE | H75: =VLOOKUP(G75,CATEGORIE!$H$3:$I$55,2,FALSE) -> COSTO SFIZI | I75: 45.75 | J75: 2/5 | K75: AMAZON | L75: MOVA
A76: SPESA ENEL | B76: AGOSTO | C76: 2026 | D76: =MATCH(B76,{"GENNAIO","FEBBRAIO","MARZO","APRILE","MAGGIO","GIUGNO","LUGLIO","AGOSTO","SETTEMBRE","OTTOBRE","NOVEMBRE","DICEMBRE"},0) -> 8 | E76: =CONCATENATE(,B76," ",C76) -> AGOSTO 2026 | F76: =CONCATENATE(D76," ",E76) -> 8 AGOSTO 2026 | G76: SPESE PER LA CASA | H76: =VLOOKUP(G76,CATEGORIE!$H$3:$I$55,2,FALSE) -> COSTO CASA | I76: 30.25 | L76: SPESA GAS
A77: CIRCOLO SKIANT GRADISCA | B77: AGOSTO | C77: 2026 | D77: =MATCH(B77,{"GENNAIO","FEBBRAIO","MARZO","APRILE","MAGGIO","GIUGNO","LUGLIO","AGOSTO","SETTEMBRE","OTTOBRE","NOVEMBRE","DICEMBRE"},0) -> 8 | E77: =CONCATENATE(,B77," ",C77) -> AGOSTO 2026 | F77: =CONCATENATE(D77," ",E77) -> 8 AGOSTO 2026 | G77: BAR E RISTORANTI | H77: =VLOOKUP(G77,CATEGORIE!$H$3:$I$55,2,FALSE) -> COSTO SVAGHI | I77: 15
A78: BIRRERIA MONDELLI | B78: AGOSTO | C78: 2026 | D78: =MATCH(B78,{"GENNAIO","FEBBRAIO","MARZO","APRILE","MAGGIO","GIUGNO","LUGLIO","AGOSTO","SETTEMBRE","OTTOBRE","NOVEMBRE","DICEMBRE"},0) -> 8 | E78: =CONCATENATE(,B78," ",C78) -> AGOSTO 2026 | F78: =CONCATENATE(D78," ",E78) -> 8 AGOSTO 2026 | G78: BAR E RISTORANTI | H78: =VLOOKUP(G78,CATEGORIE!$H$3:$I$55,2,FALSE) -> COSTO SVAGHI | I78: 34
A79: SPESA LIDL | B79: AGOSTO | C79: 2026 | D79: =MATCH(B79,{"GENNAIO","FEBBRAIO","MARZO","APRILE","MAGGIO","GIUGNO","LUGLIO","AGOSTO","SETTEMBRE","OTTOBRE","NOVEMBRE","DICEMBRE"},0) -> 8 | E79: =CONCATENATE(,B79," ",C79) -> AGOSTO 2026 | F79: =CONCATENATE(D79," ",E79) -> 8 AGOSTO 2026 | G79: ALIMENTARI | H79: =VLOOKUP(G79,CATEGORIE!$H$3:$I$55,2,FALSE) -> COSTO SOPRAVVIVENZA | I79: 19.76
A80: TBT FOOD | B80: AGOSTO | C80: 2026 | D80: =MATCH(B80,{"GENNAIO","FEBBRAIO","MARZO","APRILE","MAGGIO","GIUGNO","LUGLIO","AGOSTO","SETTEMBRE","OTTOBRE","NOVEMBRE","DICEMBRE"},0) -> 8 | E80: =CONCATENATE(,B80," ",C80) -> AGOSTO 2026 | F80: =CONCATENATE(D80," ",E80) -> 8 AGOSTO 2026 | G80: BAR E RISTORANTI | H80: =VLOOKUP(G80,CATEGORIE!$H$3:$I$55,2,FALSE) -> COSTO SVAGHI | I80: 13.4
A81: DIDON STORE | B81: AGOSTO | C81: 2026 | D81: =MATCH(B81,{"GENNAIO","FEBBRAIO","MARZO","APRILE","MAGGIO","GIUGNO","LUGLIO","AGOSTO","SETTEMBRE","OTTOBRE","NOVEMBRE","DICEMBRE"},0) -> 8 | E81: =CONCATENATE(,B81," ",C81) -> AGOSTO 2026 | F81: =CONCATENATE(D81," ",E81) -> 8 AGOSTO 2026 | G81: SPESE PER LA CASA | H81: =VLOOKUP(G81,CATEGORIE!$H$3:$I$55,2,FALSE) -> COSTO CASA | I81: 22.68
A82: SPESA ViSOTTO | B82: AGOSTO | C82: 2026 | D82: =MATCH(B82,{"GENNAIO","FEBBRAIO","MARZO","APRILE","MAGGIO","GIUGNO","LUGLIO","AGOSTO","SETTEMBRE","OTTOBRE","NOVEMBRE","DICEMBRE"},0) -> 8 | E82: =CONCATENATE(,B82," ",C82) -> AGOSTO 2026 | F82: =CONCATENATE(D82," ",E82) -> 8 AGOSTO 2026 | G82: ALIMENTARI | H82: =VLOOKUP(G82,CATEGORIE!$H$3:$I$55,2,FALSE) -> COSTO SOPRAVVIVENZA | I82: 13.36
A83: POLIDORI DISTRIBUZIONE | B83: AGOSTO | C83: 2026 | D83: =MATCH(B83,{"GENNAIO","FEBBRAIO","MARZO","APRILE","MAGGIO","GIUGNO","LUGLIO","AGOSTO","SETTEMBRE","OTTOBRE","NOVEMBRE","DICEMBRE"},0) -> 8 | E83: =CONCATENATE(,B83," ",C83) -> AGOSTO 2026 | F83: =CONCATENATE(D83," ",E83) -> 8 AGOSTO 2026 | G83: MACCHINETTA AUTOMATICA | H83: =VLOOKUP(G83,CATEGORIE!$H$3:$I$55,2,FALSE) -> COSTO SOPRAVVIVENZA | I83: 5
A84: AMAZON | B84: LUGLIO | C84: 2026 | D84: =MATCH(B84,{"GENNAIO","FEBBRAIO","MARZO","APRILE","MAGGIO","GIUGNO","LUGLIO","AGOSTO","SETTEMBRE","OTTOBRE","NOVEMBRE","DICEMBRE"},0) -> 7 | E84: =CONCATENATE(,B84," ",C84) -> LUGLIO 2026 | F84: =CONCATENATE(D84," ",E84) -> 7 LUGLIO 2026 | G84: ACQUISTI ONLINE | H84: =VLOOKUP(G84,CATEGORIE!$H$3:$I$55,2,FALSE) -> COSTO SFIZI | I84: 20 | K84: AMAZON
A85: TOLMINATOR | B85: LUGLIO | C85: 2026 | D85: =MATCH(B85,{"GENNAIO","FEBBRAIO","MARZO","APRILE","MAGGIO","GIUGNO","LUGLIO","AGOSTO","SETTEMBRE","OTTOBRE","NOVEMBRE","DICEMBRE"},0) -> 7 | E85: =CONCATENATE(,B85," ",C85) -> LUGLIO 2026 | F85: =CONCATENATE(D85," ",E85) -> 7 LUGLIO 2026 | G85: BAR E RISTORANTI | H85: =VLOOKUP(G85,CATEGORIE!$H$3:$I$55,2,FALSE) -> COSTO SVAGHI | I85: 40 | L85: Addio al cellibato Cuc
A86: TOLMINATOR | B86: LUGLIO | C86: 2026 | D86: =MATCH(B86,{"GENNAIO","FEBBRAIO","MARZO","APRILE","MAGGIO","GIUGNO","LUGLIO","AGOSTO","SETTEMBRE","OTTOBRE","NOVEMBRE","DICEMBRE"},0) -> 7 | E86: =CONCATENATE(,B86," ",C86) -> LUGLIO 2026 | F86: =CONCATENATE(D86," ",E86) -> 7 LUGLIO 2026 | G86: BAR E RISTORANTI | H86: =VLOOKUP(G86,CATEGORIE!$H$3:$I$55,2,FALSE) -> COSTO SVAGHI | I86: 50 | L86: Addio al cellibato Cuc
A87: TOLMINATOR | B87: LUGLIO | C87: 2026 | D87: =MATCH(B87,{"GENNAIO","FEBBRAIO","MARZO","APRILE","MAGGIO","GIUGNO","LUGLIO","AGOSTO","SETTEMBRE","OTTOBRE","NOVEMBRE","DICEMBRE"},0) -> 7 | E87: =CONCATENATE(,B87," ",C87) -> LUGLIO 2026 | F87: =CONCATENATE(D87," ",E87) -> 7 LUGLIO 2026 | G87: BAR E RISTORANTI | H87: =VLOOKUP(G87,CATEGORIE!$H$3:$I$55,2,FALSE) -> COSTO SVAGHI | I87: 50 | L87: Addio al cellibato Cuc
A88: AUTOSTRADA | B88: LUGLIO | C88: 2026 | D88: =MATCH(B88,{"GENNAIO","FEBBRAIO","MARZO","APRILE","MAGGIO","GIUGNO","LUGLIO","AGOSTO","SETTEMBRE","OTTOBRE","NOVEMBRE","DICEMBRE"},0) -> 7 | E88: =CONCATENATE(,B88," ",C88) -> LUGLIO 2026 | F88: =CONCATENATE(D88," ",E88) -> 7 LUGLIO 2026 | G88: TRASPORTI E PARCHEGGI | H88: =VLOOKUP(G88,CATEGORIE!$H$3:$I$55,2,FALSE) -> COSTO MOBILITA' | I88: 20 | L88: Addio al cellibato Cuc
A89: SPESA ENEL | B89: LUGLIO | C89: 2026 | D89: =MATCH(B89,{"GENNAIO","FEBBRAIO","MARZO","APRILE","MAGGIO","GIUGNO","LUGLIO","AGOSTO","SETTEMBRE","OTTOBRE","NOVEMBRE","DICEMBRE"},0) -> 7 | E89: =CONCATENATE(,B89," ",C89) -> LUGLIO 2026 | F89: =CONCATENATE(D89," ",E89) -> 7 LUGLIO 2026 | G89: SPESE PER LA CASA | H89: =VLOOKUP(G89,CATEGORIE!$H$3:$I$55,2,FALSE) -> COSTO CASA | I89: 90.27 | L89: SPESA ENERGIA
A90: AMAZON | B90: LUGLIO | C90: 2026 | D90: =MATCH(B90,{"GENNAIO","FEBBRAIO","MARZO","APRILE","MAGGIO","GIUGNO","LUGLIO","AGOSTO","SETTEMBRE","OTTOBRE","NOVEMBRE","DICEMBRE"},0) -> 7 | E90: =CONCATENATE(,B90," ",C90) -> LUGLIO 2026 | F90: =CONCATENATE(D90," ",E90) -> 7 LUGLIO 2026 | G90: ACQUISTI ONLINE | H90: =VLOOKUP(G90,CATEGORIE!$H$3:$I$55,2,FALSE) -> COSTO SFIZI | I90: 13.99 | K90: AMAZON
A91: SPESA ViSOTTO | B91: LUGLIO | C91: 2026 | D91: =MATCH(B91,{"GENNAIO","FEBBRAIO","MARZO","APRILE","MAGGIO","GIUGNO","LUGLIO","AGOSTO","SETTEMBRE","OTTOBRE","NOVEMBRE","DICEMBRE"},0) -> 7 | E91: =CONCATENATE(,B91," ",C91) -> LUGLIO 2026 | F91: =CONCATENATE(D91," ",E91) -> 7 LUGLIO 2026 | G91: ALIMENTARI | H91: =VLOOKUP(G91,CATEGORIE!$H$3:$I$55,2,FALSE) -> COSTO SOPRAVVIVENZA | I91: 18.76
A92: PIZZERIA D'AUTORE (MASCARI) | B92: LUGLIO | C92: 2026 | D92: =MATCH(B92,{"GENNAIO","FEBBRAIO","MARZO","APRILE","MAGGIO","GIUGNO","LUGLIO","AGOSTO","SETTEMBRE","OTTOBRE","NOVEMBRE","DICEMBRE"},0) -> 7 | E92: =CONCATENATE(,B92," ",C92) -> LUGLIO 2026 | F92: =CONCATENATE(D92," ",E92) -> 7 LUGLIO 2026 | G92: BAR E RISTORANTI | H92: =VLOOKUP(G92,CATEGORIE!$H$3:$I$55,2,FALSE) -> COSTO SVAGHI | I92: 48.5
A93: TABACCHERIA BARBINI | B93: LUGLIO | C93: 2026 | D93: =MATCH(B93,{"GENNAIO","FEBBRAIO","MARZO","APRILE","MAGGIO","GIUGNO","LUGLIO","AGOSTO","SETTEMBRE","OTTOBRE","NOVEMBRE","DICEMBRE"},0) -> 7 | E93: =CONCATENATE(,B93," ",C93) -> LUGLIO 2026 | F93: =CONCATENATE(D93," ",E93) -> 7 LUGLIO 2026 | G93: BAR E RISTORANTI | H93: =VLOOKUP(G93,CATEGORIE!$H$3:$I$55,2,FALSE) -> COSTO SVAGHI | I93: 5.8
A94: POLIDORI DISTRIBUZIONE | B94: LUGLIO | C94: 2026 | D94: =MATCH(B94,{"GENNAIO","FEBBRAIO","MARZO","APRILE","MAGGIO","GIUGNO","LUGLIO","AGOSTO","SETTEMBRE","OTTOBRE","NOVEMBRE","DICEMBRE"},0) -> 7 | E94: =CONCATENATE(,B94," ",C94) -> LUGLIO 2026 | F94: =CONCATENATE(D94," ",E94) -> 7 LUGLIO 2026 | G94: MACCHINETTA AUTOMATICA | H94: =VLOOKUP(G94,CATEGORIE!$H$3:$I$55,2,FALSE) -> COSTO SOPRAVVIVENZA | I94: 5
A95: SPESA ViSOTTO | B95: LUGLIO | C95: 2026 | D95: =MATCH(B95,{"GENNAIO","FEBBRAIO","MARZO","APRILE","MAGGIO","GIUGNO","LUGLIO","AGOSTO","SETTEMBRE","OTTOBRE","NOVEMBRE","DICEMBRE"},0) -> 7 | E95: =CONCATENATE(,B95," ",C95) -> LUGLIO 2026 | F95: =CONCATENATE(D95," ",E95) -> 7 LUGLIO 2026 | G95: ALIMENTARI | H95: =VLOOKUP(G95,CATEGORIE!$H$3:$I$55,2,FALSE) -> COSTO SOPRAVVIVENZA | I95: 3.97
A96: PRISHOP (MEGA HOME) | B96: LUGLIO | C96: 2026 | D96: =MATCH(B96,{"GENNAIO","FEBBRAIO","MARZO","APRILE","MAGGIO","GIUGNO","LUGLIO","AGOSTO","SETTEMBRE","OTTOBRE","NOVEMBRE","DICEMBRE"},0) -> 7 | E96: =CONCATENATE(,B96," ",C96) -> LUGLIO 2026 | F96: =CONCATENATE(D96," ",E96) -> 7 LUGLIO 2026 | G96: SPESE PER LA CASA | H96: =VLOOKUP(G96,CATEGORIE!$H$3:$I$55,2,FALSE) -> COSTO CASA | I96: 6.1
A97: SPESA LIDL | B97: LUGLIO | C97: 2026 | D97: =MATCH(B97,{"GENNAIO","FEBBRAIO","MARZO","APRILE","MAGGIO","GIUGNO","LUGLIO","AGOSTO","SETTEMBRE","OTTOBRE","NOVEMBRE","DICEMBRE"},0) -> 7 | E97: =CONCATENATE(,B97," ",C97) -> LUGLIO 2026 | F97: =CONCATENATE(D97," ",E97) -> 7 LUGLIO 2026 | G97: ALIMENTARI | H97: =VLOOKUP(G97,CATEGORIE!$H$3:$I$55,2,FALSE) -> COSTO SOPRAVVIVENZA | I97: 6.47
A98: GRUPPO NEGOZI VILLESSE | B98: LUGLIO | C98: 2026 | D98: =MATCH(B98,{"GENNAIO","FEBBRAIO","MARZO","APRILE","MAGGIO","GIUGNO","LUGLIO","AGOSTO","SETTEMBRE","OTTOBRE","NOVEMBRE","DICEMBRE"},0) -> 7 | E98: =CONCATENATE(,B98," ",C98) -> LUGLIO 2026 | F98: =CONCATENATE(D98," ",E98) -> 7 LUGLIO 2026 | G98: BAR E RISTORANTI | H98: =VLOOKUP(G98,CATEGORIE!$H$3:$I$55,2,FALSE) -> COSTO SVAGHI | I98: 11.9
A99: PLAYTOMIC VILLESSE PADEL | B99: LUGLIO | C99: 2026 | D99: =MATCH(B99,{"GENNAIO","FEBBRAIO","MARZO","APRILE","MAGGIO","GIUGNO","LUGLIO","AGOSTO","SETTEMBRE","OTTOBRE","NOVEMBRE","DICEMBRE"},0) -> 7 | E99: =CONCATENATE(,B99," ",C99) -> LUGLIO 2026 | F99: =CONCATENATE(D99," ",E99) -> 7 LUGLIO 2026 | G99: CINEMA CONCERTI SPETTACOLI | H99: =VLOOKUP(G99,CATEGORIE!$H$3:$I$55,2,FALSE) -> COSTO SVAGHI | I99: 14.49
A100: REVOLUT | B100: LUGLIO | C100: 2026 | D100: =MATCH(B100,{"GENNAIO","FEBBRAIO","MARZO","APRILE","MAGGIO","GIUGNO","LUGLIO","AGOSTO","SETTEMBRE","OTTOBRE","NOVEMBRE","DICEMBRE"},0) -> 7 | E100: =CONCATENATE(,B100," ",C100) -> LUGLIO 2026 | F100: =CONCATENATE(D100," ",E100) -> 7 LUGLIO 2026 | G100: PRELIEVO CONTANTI | H100: =VLOOKUP(G100,CATEGORIE!$H$3:$I$55,2,FALSE) -> MOVIMENTI CONTO | I100: 50 | K100: REVOLUT
...

Sheet Spese Generiche BANCOMAT 
A1: TIPOLOGIA | B1: MESE | C1: ANNO | D1: MESE | E1: COMPOSTO | F1: COMPOSTO | G1: TIPOLOGIA | H1: CATEGORIA | I1: IMPORTO | J1: RATA | K1: TRAMITE | L1: NOTE
A2: SPESA VISOTTO | B2: SETTEMBRE | C2: 2026 | D2: =MATCH(B2,{"GENNAIO","FEBBRAIO","MARZO","APRILE","MAGGIO","GIUGNO","LUGLIO","AGOSTO","SETTEMBRE","OTTOBRE","NOVEMBRE","DICEMBRE"},0) -> 9 | E2: =CONCATENATE(,B2," ",C2) -> SETTEMBRE 2026 | F2: =CONCATENATE(D2," ",E2) -> 9 SETTEMBRE 2026 | G2: ALIMENTARI | H2: =VLOOKUP(G2,CATEGORIE!$H$3:$I$55,2,FALSE) -> COSTO SOPRAVVIVENZA | I2: 15.14
A3: DIDON STORE | B3: SETTEMBRE | C3: 2026 | D3: =MATCH(B3,{"GENNAIO","FEBBRAIO","MARZO","APRILE","MAGGIO","GIUGNO","LUGLIO","AGOSTO","SETTEMBRE","OTTOBRE","NOVEMBRE","DICEMBRE"},0) -> 9 | E3: =CONCATENATE(,B3," ",C3) -> SETTEMBRE 2026 | F3: =CONCATENATE(D3," ",E3) -> 9 SETTEMBRE 2026 | G3: SPESE PER LA CASA | H3: =VLOOKUP(G3,CATEGORIE!$H$3:$I$55,2,FALSE) -> COSTO CASA | I3: 19.29
A4: PIZZERIA CHICHIBIO | B4: SETTEMBRE | C4: 2026 | D4: =MATCH(B4,{"GENNAIO","FEBBRAIO","MARZO","APRILE","MAGGIO","GIUGNO","LUGLIO","AGOSTO","SETTEMBRE","OTTOBRE","NOVEMBRE","DICEMBRE"},0) -> 9 | E4: =CONCATENATE(,B4," ",C4) -> SETTEMBRE 2026 | F4: =CONCATENATE(D4," ",E4) -> 9 SETTEMBRE 2026 | G4: BAR E RISTORANTI | H4: =VLOOKUP(G4,CATEGORIE!$H$3:$I$55,2,FALSE) -> COSTO SVAGHI | I4: 43.2
A5: MICROSOFT | B5: SETTEMBRE | C5: 2026 | D5: =MATCH(B5,{"GENNAIO","FEBBRAIO","MARZO","APRILE","MAGGIO","GIUGNO","LUGLIO","AGOSTO","SETTEMBRE","OTTOBRE","NOVEMBRE","DICEMBRE"},0) -> 9 | E5: =CONCATENATE(,B5," ",C5) -> SETTEMBRE 2026 | F5: =CONCATENATE(D5," ",E5) -> 9 SETTEMBRE 2026 | G5: BAR E RISTORANTI | H5: =VLOOKUP(G5,CATEGORIE!$H$3:$I$55,2,FALSE) -> COSTO SVAGHI | I5: 29.99
A6: SPESA LIDL | B6: SETTEMBRE | C6: 2026 | D6: =MATCH(B6,{"GENNAIO","FEBBRAIO","MARZO","APRILE","MAGGIO","GIUGNO","LUGLIO","AGOSTO","SETTEMBRE","OTTOBRE","NOVEMBRE","DICEMBRE"},0) -> 9 | E6: =CONCATENATE(,B6," ",C6) -> SETTEMBRE 2026 | F6: =CONCATENATE(D6," ",E6) -> 9 SETTEMBRE 2026 | G6: ALIMENTARI | H6: =VLOOKUP(G6,CATEGORIE!$H$3:$I$55,2,FALSE) -> COSTO SOPRAVVIVENZA | I6: 16.28
A7: SHOP ASFINAG | B7: SETTEMBRE | C7: 2026 | D7: =MATCH(B7,{"GENNAIO","FEBBRAIO","MARZO","APRILE","MAGGIO","GIUGNO","LUGLIO","AGOSTO","SETTEMBRE","OTTOBRE","NOVEMBRE","DICEMBRE"},0) -> 9 | E7: =CONCATENATE(,B7," ",C7) -> SETTEMBRE 2026 | F7: =CONCATENATE(D7," ",E7) -> 9 SETTEMBRE 2026 | G7: BAR E RISTORANTI | H7: =VLOOKUP(G7,CATEGORIE!$H$3:$I$55,2,FALSE) -> COSTO SVAGHI | I7: 12.8 | L7: Matrimonio CUC
A8: GOOGLE | B8: SETTEMBRE | C8: 2026 | D8: =MATCH(B8,{"GENNAIO","FEBBRAIO","MARZO","APRILE","MAGGIO","GIUGNO","LUGLIO","AGOSTO","SETTEMBRE","OTTOBRE","NOVEMBRE","DICEMBRE"},0) -> 9 | E8: =CONCATENATE(,B8," ",C8) -> SETTEMBRE 2026 | F8: =CONCATENATE(D8," ",E8) -> 9 SETTEMBRE 2026 | G8: ACQUISTI ONLINE | H8: =VLOOKUP(G8,CATEGORIE!$H$3:$I$55,2,FALSE) -> COSTO SFIZI | I8: 12.49
A9: TOTAL SERVICE STATION ROHRDORF | B9: SETTEMBRE | C9: 2026 | D9: =MATCH(B9,{"GENNAIO","FEBBRAIO","MARZO","APRILE","MAGGIO","GIUGNO","LUGLIO","AGOSTO","SETTEMBRE","OTTOBRE","NOVEMBRE","DICEMBRE"},0) -> 9 | E9: =CONCATENATE(,B9," ",C9) -> SETTEMBRE 2026 | F9: =CONCATENATE(D9," ",E9) -> 9 SETTEMBRE 2026 | G9: RIFORNIMENTI | H9: =VLOOKUP(G9,CATEGORIE!$H$3:$I$55,2,FALSE) -> COSTO MOBILITA' | I9: 65.04 | L9: Matrimonio CUC
A10: FARMACIA DOT MONENGHI | B10: SETTEMBRE | C10: 2026 | D10: =MATCH(B10,{"GENNAIO","FEBBRAIO","MARZO","APRILE","MAGGIO","GIUGNO","LUGLIO","AGOSTO","SETTEMBRE","OTTOBRE","NOVEMBRE","DICEMBRE"},0) -> 9 | E10: =CONCATENATE(,B10," ",C10) -> SETTEMBRE 2026 | F10: =CONCATENATE(D10," ",E10) -> 9 SETTEMBRE 2026 | G10: MEDICINALI | H10: =VLOOKUP(G10,CATEGORIE!$H$3:$I$55,2,FALSE) -> COSTO SOPRAVVIVENZA | I10: 37
A11: PRI SHOP | B11: SETTEMBRE | C11: 2026 | D11: =MATCH(B11,{"GENNAIO","FEBBRAIO","MARZO","APRILE","MAGGIO","GIUGNO","LUGLIO","AGOSTO","SETTEMBRE","OTTOBRE","NOVEMBRE","DICEMBRE"},0) -> 9 | E11: =CONCATENATE(,B11," ",C11) -> SETTEMBRE 2026 | F11: =CONCATENATE(D11," ",E11) -> 9 SETTEMBRE 2026 | G11: SPESE PER LA CASA | H11: =VLOOKUP(G11,CATEGORIE!$H$3:$I$55,2,FALSE) -> COSTO CASA | I11: 19.9
A12: MICROSOFT XPASS | B12: SETTEMBRE | C12: 2026 | D12: =MATCH(B12,{"GENNAIO","FEBBRAIO","MARZO","APRILE","MAGGIO","GIUGNO","LUGLIO","AGOSTO","SETTEMBRE","OTTOBRE","NOVEMBRE","DICEMBRE"},0) -> 9 | E12: =CONCATENATE(,B12," ",C12) -> SETTEMBRE 2026 | F12: =CONCATENATE(D12," ",E12) -> 9 SETTEMBRE 2026 | G12: BAR E RISTORANTI | H12: =VLOOKUP(G12,CATEGORIE!$H$3:$I$55,2,FALSE) -> COSTO SVAGHI | I12: 20.99
A13: SPESA LIDL | B13: SETTEMBRE | C13: 2026 | D13: =MATCH(B13,{"GENNAIO","FEBBRAIO","MARZO","APRILE","MAGGIO","GIUGNO","LUGLIO","AGOSTO","SETTEMBRE","OTTOBRE","NOVEMBRE","DICEMBRE"},0) -> 9 | E13: =CONCATENATE(,B13," ",C13) -> SETTEMBRE 2026 | F13: =CONCATENATE(D13," ",E13) -> 9 SETTEMBRE 2026 | G13: ALIMENTARI | H13: =VLOOKUP(G13,CATEGORIE!$H$3:$I$55,2,FALSE) -> COSTO SOPRAVVIVENZA | I13: 92.63
A14: BOLLO AUTO QASHQAI | B14: SETTEMBRE | C14: 2026 | D14: =MATCH(B14,{"GENNAIO","FEBBRAIO","MARZO","APRILE","MAGGIO","GIUGNO","LUGLIO","AGOSTO","SETTEMBRE","OTTOBRE","NOVEMBRE","DICEMBRE"},0) -> 9 | E14: =CONCATENATE(,B14," ",C14) -> SETTEMBRE 2026 | F14: =CONCATENATE(D14," ",E14) -> 9 SETTEMBRE 2026 | G14: SPESE PER LA MACCHINA | H14: =VLOOKUP(G14,CATEGORIE!$H$3:$I$55,2,FALSE) -> COSTO MOBILITA' | I14: 418.09
A15: SPESA VISOTTO | B15: AGOSTO | C15: 2026 | D15: =MATCH(B15,{"GENNAIO","FEBBRAIO","MARZO","APRILE","MAGGIO","GIUGNO","LUGLIO","AGOSTO","SETTEMBRE","OTTOBRE","NOVEMBRE","DICEMBRE"},0) -> 8 | E15: =CONCATENATE(,B15," ",C15) -> AGOSTO 2026 | F15: =CONCATENATE(D15," ",E15) -> 8 AGOSTO 2026 | G15: ALIMENTARI | H15: =VLOOKUP(G15,CATEGORIE!$H$3:$I$55,2,FALSE) -> COSTO SOPRAVVIVENZA | I15: 5.26
A16: IKEA VILLESSE | B16: AGOSTO | C16: 2026 | D16: =MATCH(B16,{"GENNAIO","FEBBRAIO","MARZO","APRILE","MAGGIO","GIUGNO","LUGLIO","AGOSTO","SETTEMBRE","OTTOBRE","NOVEMBRE","DICEMBRE"},0) -> 8 | E16: =CONCATENATE(,B16," ",C16) -> AGOSTO 2026 | F16: =CONCATENATE(D16," ",E16) -> 8 AGOSTO 2026 | G16: SPESE PER LA CASA | H16: =VLOOKUP(G16,CATEGORIE!$H$3:$I$55,2,FALSE) -> COSTO CASA | I16: 8.95
A17: AL TAGLIATO COL COLTELLO | B17: AGOSTO | C17: 2026 | D17: =MATCH(B17,{"GENNAIO","FEBBRAIO","MARZO","APRILE","MAGGIO","GIUGNO","LUGLIO","AGOSTO","SETTEMBRE","OTTOBRE","NOVEMBRE","DICEMBRE"},0) -> 8 | E17: =CONCATENATE(,B17," ",C17) -> AGOSTO 2026 | F17: =CONCATENATE(D17," ",E17) -> 8 AGOSTO 2026 | G17: BAR E RISTORANTI | H17: =VLOOKUP(G17,CATEGORIE!$H$3:$I$55,2,FALSE) -> COSTO SVAGHI | I17: 22
A18: SPESA DIDON | B18: AGOSTO | C18: 2026 | D18: =MATCH(B18,{"GENNAIO","FEBBRAIO","MARZO","APRILE","MAGGIO","GIUGNO","LUGLIO","AGOSTO","SETTEMBRE","OTTOBRE","NOVEMBRE","DICEMBRE"},0) -> 8 | E18: =CONCATENATE(,B18," ",C18) -> AGOSTO 2026 | F18: =CONCATENATE(D18," ",E18) -> 8 AGOSTO 2026 | G18: SPESE PER LA CASA | H18: =VLOOKUP(G18,CATEGORIE!$H$3:$I$55,2,FALSE) -> COSTO CASA | I18: 14.3
A19: PONTAROLO COMMERCIALE | B19: AGOSTO | C19: 2026 | D19: =MATCH(B19,{"GENNAIO","FEBBRAIO","MARZO","APRILE","MAGGIO","GIUGNO","LUGLIO","AGOSTO","SETTEMBRE","OTTOBRE","NOVEMBRE","DICEMBRE"},0) -> 8 | E19: =CONCATENATE(,B19," ",C19) -> AGOSTO 2026 | F19: =CONCATENATE(D19," ",E19) -> 8 AGOSTO 2026 | G19: SPESE PER LA CASA | H19: =VLOOKUP(G19,CATEGORIE!$H$3:$I$55,2,FALSE) -> COSTO CASA | I19: 19
A20: BRICOCENTER | B20: AGOSTO | C20: 2026 | D20: =MATCH(B20,{"GENNAIO","FEBBRAIO","MARZO","APRILE","MAGGIO","GIUGNO","LUGLIO","AGOSTO","SETTEMBRE","OTTOBRE","NOVEMBRE","DICEMBRE"},0) -> 8 | E20: =CONCATENATE(,B20," ",C20) -> AGOSTO 2026 | F20: =CONCATENATE(D20," ",E20) -> 8 AGOSTO 2026 | G20: SPESE PER LA CASA | H20: =VLOOKUP(G20,CATEGORIE!$H$3:$I$55,2,FALSE) -> COSTO CASA | I20: 11.6
A21: SATUR | B21: AGOSTO | C21: 2026 | D21: =MATCH(B21,{"GENNAIO","FEBBRAIO","MARZO","APRILE","MAGGIO","GIUGNO","LUGLIO","AGOSTO","SETTEMBRE","OTTOBRE","NOVEMBRE","DICEMBRE"},0) -> 8 | E21: =CONCATENATE(,B21," ",C21) -> AGOSTO 2026 | F21: =CONCATENATE(D21," ",E21) -> 8 AGOSTO 2026 | G21: SPESE PER LA CASA | H21: =VLOOKUP(G21,CATEGORIE!$H$3:$I$55,2,FALSE) -> COSTO CASA | I21: 10.39
... A24: BRICOCENTER | B24: AGOSTO | C24: 2026 | D24: =MATCH(B24,{"GENNAIO","FEBBRAIO","MARZO","APRILE","MAGGIO","GIUGNO","LUGLIO","AGOSTO","SETTEMBRE","OTTOBRE","NOVEMBRE","DICEMBRE"},0) -> 8 | E24: =CONCATENATE(,B24," ",C24) -> AGOSTO 2026 | F24: =CONCATENATE(D24," ",E24) -> 8 AGOSTO 2026 | G24: SPESE PER LA CASA | H24: =VLOOKUP(G24,CATEGORIE!$H$3:$I$55,2,FALSE) -> COSTO CASA | I24: 63.3
A25: RISTORANTE AL CANCELLETTO | B25: AGOSTO | C25: 2026 | D25: =MATCH(B25,{"GENNAIO","FEBBRAIO","MARZO","APRILE","MAGGIO","GIUGNO","LUGLIO","AGOSTO","SETTEMBRE","OTTOBRE","NOVEMBRE","DICEMBRE"},0) -> 8 | E25: =CONCATENATE(,B25," ",C25) -> AGOSTO 2026 | F25: =CONCATENATE(D25," ",E25) -> 8 AGOSTO 2026 | G25: BAR E RISTORANTI | H25: =VLOOKUP(G25,CATEGORIE!$H$3:$I$55,2,FALSE) -> COSTO SVAGHI | I25: 84 | L25: Viaggio Costiera Amalfitana 26
A26: LA MAURELLA | B26: AGOSTO | C26: 2026 | D26: =MATCH(B26,{"GENNAIO","FEBBRAIO","MARZO","APRILE","MAGGIO","GIUGNO","LUGLIO","AGOSTO","SETTEMBRE","OTTOBRE","NOVEMBRE","DICEMBRE"},0) -> 8 | E26: =CONCATENATE(,B26," ",C26) -> AGOSTO 2026 | F26: =CONCATENATE(D26," ",E26) -> 8 AGOSTO 2026 | G26: HOTEL & SERVIZI | H26: =VLOOKUP(G26,CATEGORIE!$H$3:$I$55,2,FALSE) -> COSTO VACANZE | I26: 1852 | L26: Viaggio Costiera Amalfitana 26
A27: MICROSOFT XPASS | B27: AGOSTO | C27: 2026 | D27: =MATCH(B27,{"GENNAIO","FEBBRAIO","MARZO","APRILE","MAGGIO","GIUGNO","LUGLIO","AGOSTO","SETTEMBRE","OTTOBRE","NOVEMBRE","DICEMBRE"},0) -> 8 | E27: =CONCATENATE(,B27," ",C27) -> AGOSTO 2026 | F27: =CONCATENATE(D27," ",E27) -> 8 AGOSTO 2026 | G27: BAR E RISTORANTI | H27: =VLOOKUP(G27,CATEGORIE!$H$3:$I$55,2,FALSE) -> COSTO SVAGHI | I27: 20.99
A28: BIGLIETTERIA CAPRI | B28: AGOSTO | C28: 2026 | D28: =MATCH(B28,{"GENNAIO","FEBBRAIO","MARZO","APRILE","MAGGIO","GIUGNO","LUGLIO","AGOSTO","SETTEMBRE","OTTOBRE","NOVEMBRE","DICEMBRE"},0) -> 8 | E28: =CONCATENATE(,B28," ",C28) -> AGOSTO 2026 | F28: =CONCATENATE(D28," ",E28) -> 8 AGOSTO 2026 | G28: TRASPORTI E PARCHEGGI | H28: =VLOOKUP(G28,CATEGORIE!$H$3:$I$55,2,FALSE) -> COSTO MOBILITA' | I28: 48 | L28: Viaggio Costiera Amalfitana 26
A29: TRATTORIA DA ARMANDINO | B29: AGOSTO | C29: 2026 | D29: =MATCH(B29,{"GENNAIO","FEBBRAIO","MARZO","APRILE","MAGGIO","GIUGNO","LUGLIO","AGOSTO","SETTEMBRE","OTTOBRE","NOVEMBRE","DICEMBRE"},0) -> 8 | E29: =CONCATENATE(,B29," ",C29) -> AGOSTO 2026 | F29: =CONCATENATE(D29," ",E29) -> 8 AGOSTO 2026 | G29: BAR E RISTORANTI | H29: =VLOOKUP(G29,CATEGORIE!$H$3:$I$55,2,FALSE) -> COSTO SVAGHI | I29: 107 | L29: Viaggio Costiera Amalfitana 26
A30: BACARO FORESTO | B30: AGOSTO | C30: 2026 | D30: =MATCH(B30,{"GENNAIO","FEBBRAIO","MARZO","APRILE","MAGGIO","GIUGNO","LUGLIO","AGOSTO","SETTEMBRE","OTTOBRE","NOVEMBRE","DICEMBRE"},0) -> 8 | E30: =CONCATENATE(,B30," ",C30) -> AGOSTO 2026 | F30: =CONCATENATE(D30," ",E30) -> 8 AGOSTO 2026 | G30: BAR E RISTORANTI | H30: =VLOOKUP(G30,CATEGORIE!$H$3:$I$55,2,FALSE) -> COSTO SVAGHI | I30: 85
A31: AUTOSTRADA | B31: LUGLIO | C31: 2026 | D31: =MATCH(B31,{"GENNAIO","FEBBRAIO","MARZO","APRILE","MAGGIO","GIUGNO","LUGLIO","AGOSTO","SETTEMBRE","OTTOBRE","NOVEMBRE","DICEMBRE"},0) -> 7 | E31: =CONCATENATE(,B31," ",C31) -> LUGLIO 2026 | F31: =CONCATENATE(D31," ",E31) -> 7 LUGLIO 2026 | G31: TRASPORTI E PARCHEGGI | H31: =VLOOKUP(G31,CATEGORIE!$H$3:$I$55,2,FALSE) -> COSTO MOBILITA' | I31: 6
A32: AUTOSTRADA | B32: LUGLIO | C32: 2026 | D32: =MATCH(B32,{"GENNAIO","FEBBRAIO","MARZO","APRILE","MAGGIO","GIUGNO","LUGLIO","AGOSTO","SETTEMBRE","OTTOBRE","NOVEMBRE","DICEMBRE"},0) -> 7 | E32: =CONCATENATE(,B32," ",C32) -> LUGLIO 2026 | F32: =CONCATENATE(D32," ",E32) -> 7 LUGLIO 2026 | G32: TRASPORTI E PARCHEGGI | H32: =VLOOKUP(G32,CATEGORIE!$H$3:$I$55,2,FALSE) -> COSTO MOBILITA' | I32: 5.3
A33: COMMISSIONE BONIFICO | B33: LUGLIO | C33: 2026 | D33: =MATCH(B33,{"GENNAIO","FEBBRAIO","MARZO","APRILE","MAGGIO","GIUGNO","LUGLIO","AGOSTO","SETTEMBRE","OTTOBRE","NOVEMBRE","DICEMBRE"},0) -> 7 | E33: =CONCATENATE(,B33," ",C33) -> LUGLIO 2026 | F33: =CONCATENATE(D33," ",E33) -> 7 LUGLIO 2026 | G33: TASSE | H33: =VLOOKUP(G33,CATEGORIE!$H$3:$I$55,2,FALSE) -> TASSE | I33: 0.9 | L33: Assilt Papa'
A34: MICROSOFT XPASS | B34: LUGLIO | C34: 2026 | D34: =MATCH(B34,{"GENNAIO","FEBBRAIO","MARZO","APRILE","MAGGIO","GIUGNO","LUGLIO","AGOSTO","SETTEMBRE","OTTOBRE","NOVEMBRE","DICEMBRE"},0) -> 7 | E34: =CONCATENATE(,B34," ",C34) -> LUGLIO 2026 | F34: =CONCATENATE(D34," ",E34) -> 7 LUGLIO 2026 | G34: BAR E RISTORANTI | H34: =VLOOKUP(G34,CATEGORIE!$H$3:$I$55,2,FALSE) -> COSTO SVAGHI | I34: 20.99
A35: ASSILT | B35: LUGLIO | C35: 2026 | D35: =MATCH(B35,{"GENNAIO","FEBBRAIO","MARZO","APRILE","MAGGIO","GIUGNO","LUGLIO","AGOSTO","SETTEMBRE","OTTOBRE","NOVEMBRE","DICEMBRE"},0) -> 7 | E35: =CONCATENATE(,B35," ",C35) -> LUGLIO 2026 | F35: =CONCATENATE(D35," ",E35) -> 7 LUGLIO 2026 | G35: REGALI | H35: =VLOOKUP(G35,CATEGORIE!$H$3:$I$55,2,FALSE) -> COSTO SFIZI | I35: 128.45 | L35: Assilt Papa'
A36: UFFICINA | B36: LUGLIO | C36: 2026 | D36: =MATCH(B36,{"GENNAIO","FEBBRAIO","MARZO","APRILE","MAGGIO","GIUGNO","LUGLIO","AGOSTO","SETTEMBRE","OTTOBRE","NOVEMBRE","DICEMBRE"},0) -> 7 | E36: =CONCATENATE(,B36," ",C36) -> LUGLIO 2026 | F36: =CONCATENATE(D36," ",E36) -> 7 LUGLIO 2026 | G36: BAR E RISTORANTI | H36: =VLOOKUP(G36,CATEGORIE!$H$3:$I$104,2,FALSE) -> COSTO SVAGHI | I36: 14.5
A37: PIZZERIA ALL'ANFORA | B37: LUGLIO | C37: 2026 | D37: =MATCH(B37,{"GENNAIO","FEBBRAIO","MARZO","APRILE","MAGGIO","GIUGNO","LUGLIO","AGOSTO","SETTEMBRE","OTTOBRE","NOVEMBRE","DICEMBRE"},0) -> 7 | E37: =CONCATENATE(,B37," ",C37) -> LUGLIO 2026 | F37: =CONCATENATE(D37," ",E37) -> 7 LUGLIO 2026 | G37: BAR E RISTORANTI | H37: =VLOOKUP(G37,CATEGORIE!$H$3:$I$104,2,FALSE) -> COSTO SVAGHI | I37: 38
A38: SPESA LIDL | B38: LUGLIO | C38: 2026 | D38: =MATCH(B38,{"GENNAIO","FEBBRAIO","MARZO","APRILE","MAGGIO","GIUGNO","LUGLIO","AGOSTO","SETTEMBRE","OTTOBRE","NOVEMBRE","DICEMBRE"},0) -> 7 | E38: =CONCATENATE(,B38," ",C38) -> LUGLIO 2026 | F38: =CONCATENATE(D38," ",E38) -> 7 LUGLIO 2026 | G38: ALIMENTARI | H38: =VLOOKUP(G38,CATEGORIE!$H$3:$I$55,2,FALSE) -> COSTO SOPRAVVIVENZA | I38: 16.8
A39: UFFICINA | B39: GIUGNO | C39: 2026 | D39: =MATCH(B39,{"GENNAIO","FEBBRAIO","MARZO","APRILE","MAGGIO","GIUGNO","LUGLIO","AGOSTO","SETTEMBRE","OTTOBRE","NOVEMBRE","DICEMBRE"},0) -> 6 | E39: =CONCATENATE(,B39," ",C39) -> GIUGNO 2026 | F39: =CONCATENATE(D39," ",E39) -> 6 GIUGNO 2026 | G39: BAR E RISTORANTI | H39: =VLOOKUP(G39,CATEGORIE!$H$3:$I$104,2,FALSE) -> COSTO SVAGHI | I39: 18.5
A40: BAR SOLARIUM | B40: GIUGNO | C40: 2026 | D40: =MATCH(B40,{"GENNAIO","FEBBRAIO","MARZO","APRILE","MAGGIO","GIUGNO","LUGLIO","AGOSTO","SETTEMBRE","OTTOBRE","NOVEMBRE","DICEMBRE"},0) -> 6 | E40: =CONCATENATE(,B40," ",C40) -> GIUGNO 2026 | F40: =CONCATENATE(D40," ",E40) -> 6 GIUGNO 2026 | G40: BAR E RISTORANTI | H40: =VLOOKUP(G40,CATEGORIE!$H$3:$I$104,2,FALSE) -> COSTO SVAGHI | I40: 6.7
A41: BAR SOLARIUM | B41: GIUGNO | C41: 2026 | D41: =MATCH(B41,{"GENNAIO","FEBBRAIO","MARZO","APRILE","MAGGIO","GIUGNO","LUGLIO","AGOSTO","SETTEMBRE","OTTOBRE","NOVEMBRE","DICEMBRE"},0) -> 6 | E41: =CONCATENATE(,B41," ",C41) -> GIUGNO 2026 | F41: =CONCATENATE(D41," ",E41) -> 6 GIUGNO 2026 | G41: BAR E RISTORANTI | H41: =VLOOKUP(G41,CATEGORIE!$H$3:$I$104,2,FALSE) -> COSTO SVAGHI | I41: 16.7
A42: UFFICINA | B42: GIUGNO | C42: 2026 | D42: =MATCH(B42,{"GENNAIO","FEBBRAIO","MARZO","APRILE","MAGGIO","GIUGNO","LUGLIO","AGOSTO","SETTEMBRE","OTTOBRE","NOVEMBRE","DICEMBRE"},0) -> 6 | E42: =CONCATENATE(,B42," ",C42) -> GIUGNO 2026 | F42: =CONCATENATE(D42," ",E42) -> 6 GIUGNO 2026 | G42: BAR E RISTORANTI | H42: =VLOOKUP(G42,CATEGORIE!$H$3:$I$55,2,FALSE) -> COSTO SVAGHI | I42: 22
A43: SPESA VISOTTO | B43: GIUGNO | C43: 2026 | D43: =MATCH(B43,{"GENNAIO","FEBBRAIO","MARZO","APRILE","MAGGIO","GIUGNO","LUGLIO","AGOSTO","SETTEMBRE","OTTOBRE","NOVEMBRE","DICEMBRE"},0) -> 6 | E43: =CONCATENATE(,B43," ",C43) -> GIUGNO 2026 | F43: =CONCATENATE(D43," ",E43) -> 6 GIUGNO 2026 | G43: ALIMENTARI | H43: =VLOOKUP(G43,CATEGORIE!$H$3:$I$55,2,FALSE) -> COSTO SOPRAVVIVENZA | I43: 25.15
A44: TARI | B44: GIUGNO | C44: 2026 | D44: =MATCH(B44,{"GENNAIO","FEBBRAIO","MARZO","APRILE","MAGGIO","GIUGNO","LUGLIO","AGOSTO","SETTEMBRE","OTTOBRE","NOVEMBRE","DICEMBRE"},0) -> 6 | E44: =CONCATENATE(,B44," ",C44) -> GIUGNO 2026 | F44: =CONCATENATE(D44," ",E44) -> 6 GIUGNO 2026 | G44: TASSE | H44: =VLOOKUP(G44,CATEGORIE!$H$3:$I$55,2,FALSE) -> TASSE | I44: 44 | L44: Tari 2026
A45: TARI | B45: GIUGNO | C45: 2026 | D45: =MATCH(B45,{"GENNAIO","FEBBRAIO","MARZO","APRILE","MAGGIO","GIUGNO","LUGLIO","AGOSTO","SETTEMBRE","OTTOBRE","NOVEMBRE","DICEMBRE"},0) -> 6 | E45: =CONCATENATE(,B45," ",C45) -> GIUGNO 2026 | F45: =CONCATENATE(D45," ",E45) -> 6 GIUGNO 2026 | G45: TASSE | H45: =VLOOKUP(G45,CATEGORIE!$H$3:$I$55,2,FALSE) -> TASSE | I45: 43 | L45: Tari 2026
A46: DIDON STORE | B46: GIUGNO | C46: 2026 | D46: =MATCH(B46,{"GENNAIO","FEBBRAIO","MARZO","APRILE","MAGGIO","GIUGNO","LUGLIO","AGOSTO","SETTEMBRE","OTTOBRE","NOVEMBRE","DICEMBRE"},0) -> 6 | E46: =CONCATENATE(,B46," ",C46) -> GIUGNO 2026 | F46: =CONCATENATE(D46," ",E46) -> 6 GIUGNO 2026 | G46: ALIMENTARI | H46: =VLOOKUP(G46,CATEGORIE!$H$3:$I$55,2,FALSE) -> COSTO SOPRAVVIVENZA | I46: 24
A47: AUTOGRILL | B47: GIUGNO | C47: 2026 | D47: =MATCH(B47,{"GENNAIO","FEBBRAIO","MARZO","APRILE","MAGGIO","GIUGNO","LUGLIO","AGOSTO","SETTEMBRE","OTTOBRE","NOVEMBRE","DICEMBRE"},0) -> 6 | E47: =CONCATENATE(,B47," ",C47) -> GIUGNO 2026 | F47: =CONCATENATE(D47," ",E47) -> 6 GIUGNO 2026 | G47: BAR E RISTORANTI | H47: =VLOOKUP(G47,CATEGORIE!$H$3:$I$55,2,FALSE) -> COSTO SVAGHI | I47: 22.3
A48: SPESA LIDL | B48: GIUGNO | C48: 2026 | D48: =MATCH(B48,{"GENNAIO","FEBBRAIO","MARZO","APRILE","MAGGIO","GIUGNO","LUGLIO","AGOSTO","SETTEMBRE","OTTOBRE","NOVEMBRE","DICEMBRE"},0) -> 6 | E48: =CONCATENATE(,B48," ",C48) -> GIUGNO 2026 | F48: =CONCATENATE(D48," ",E48) -> 6 GIUGNO 2026 | G48: ALIMENTARI | H48: =VLOOKUP(G48,CATEGORIE!$H$3:$I$55,2,FALSE) -> COSTO SOPRAVVIVENZA | I48: 28.08
A49: MICROSOFT XPASS | B49: GIUGNO | C49: 2026 | D49: =MATCH(B49,{"GENNAIO","FEBBRAIO","MARZO","APRILE","MAGGIO","GIUGNO","LUGLIO","AGOSTO","SETTEMBRE","OTTOBRE","NOVEMBRE","DICEMBRE"},0) -> 6 | E49: =CONCATENATE(,B49," ",C49) -> GIUGNO 2026 | F49: =CONCATENATE(D49," ",E49) -> 6 GIUGNO 2026 | G49: BAR E RISTORANTI | H49: =VLOOKUP(G49,CATEGORIE!$H$3:$I$55,2,FALSE) -> COSTO SVAGHI | I49: 20.99
A50: COMMISSIONE BONIFICO | B50: GIUGNO | C50: 2026 | D50: =MATCH(B50,{"GENNAIO","FEBBRAIO","MARZO","APRILE","MAGGIO","GIUGNO","LUGLIO","AGOSTO","SETTEMBRE","OTTOBRE","NOVEMBRE","DICEMBRE"},0) -> 6 | E50: =CONCATENATE(,B50," ",C50) -> GIUGNO 2026 | F50: =CONCATENATE(D50," ",E50) -> 6 GIUGNO 2026 | G50: TASSE | H50: =VLOOKUP(G50,CATEGORIE!$H$3:$I$55,2,FALSE) -> TASSE | I50: 0.5
A51: BONIFICO AQUI E SILVIA | B51: GIUGNO | C51: 2026 | D51: =MATCH(B51,{"GENNAIO","FEBBRAIO","MARZO","APRILE","MAGGIO","GIUGNO","LUGLIO","AGOSTO","SETTEMBRE","OTTOBRE","NOVEMBRE","DICEMBRE"},0) -> 6 | E51: =CONCATENATE(,B51," ",C51) -> GIUGNO 2026 | F51: =CONCATENATE(D51," ",E51) -> 6 GIUGNO 2026 | G51: REGALI | H51: =VLOOKUP(G51,CATEGORIE!$H$3:$I$55,2,FALSE) -> COSTO SFIZI | I51: 350 | L51: Regali Nozze Aqui e Silvia
A52: BU.CO | B52: GIUGNO | C52: 2026 | D52: =MATCH(B52,{"GENNAIO","FEBBRAIO","MARZO","APRILE","MAGGIO","GIUGNO","LUGLIO","AGOSTO","SETTEMBRE","OTTOBRE","NOVEMBRE","DICEMBRE"},0) -> 6 | E52: =CONCATENATE(,B52," ",C52) -> GIUGNO 2026 | F52: =CONCATENATE(D52," ",E52) -> 6 GIUGNO 2026 | G52: BAR E RISTORANTI | H52: =VLOOKUP(G52,CATEGORIE!$H$3:$I$55,2,FALSE) -> COSTO SVAGHI | I52: 40.7
A53: SPESA VISOTTO | B53: MAGGIO | C53: 2026 | D53: =MATCH(B53,{"GENNAIO","FEBBRAIO","MARZO","APRILE","MAGGIO","GIUGNO","LUGLIO","AGOSTO","SETTEMBRE","OTTOBRE","NOVEMBRE","DICEMBRE"},0) -> 5 | E53: =CONCATENATE(,B53," ",C53) -> MAGGIO 2026 | F53: =CONCATENATE(D53," ",E53) -> 5 MAGGIO 2026 | G53: ALIMENTARI | H53: =VLOOKUP(G53,CATEGORIE!$H$3:$I$55,2,FALSE) -> COSTO SOPRAVVIVENZA | I53: 12.67
A54: MEDICENTER RONCHI | B54: MAGGIO | C54: 2026 | D54: =MATCH(B54,{"GENNAIO","FEBBRAIO","MARZO","APRILE","MAGGIO","GIUGNO","LUGLIO","AGOSTO","SETTEMBRE","OTTOBRE","NOVEMBRE","DICEMBRE"},0) -> 5 | E54: =CONCATENATE(,B54," ",C54) -> MAGGIO 2026 | F54: =CONCATENATE(D54," ",E54) -> 5 MAGGIO 2026 | G54: VISITE MEDICHE | H54: =VLOOKUP(G54,CATEGORIE!$H$3:$I$55,2,FALSE) -> COSTO SOPRAVVIVENZA | I54: 33
A55: COMMISSIONE BONIFICO | B55: MAGGIO | C55: 2026 | D55: =MATCH(B55,{"GENNAIO","FEBBRAIO","MARZO","APRILE","MAGGIO","GIUGNO","LUGLIO","AGOSTO","SETTEMBRE","OTTOBRE","NOVEMBRE","DICEMBRE"},0) -> 5 | E55: =CONCATENATE(,B55," ",C55) -> MAGGIO 2026 | F55: =CONCATENATE(D55," ",E55) -> 5 MAGGIO 2026 | G55: TASSE | H55: =VLOOKUP(G55,CATEGORIE!$H$3:$I$55,2,FALSE) -> TASSE | I55: 0.5
A56: AGENZIA SERENA GROUP | B56: MAGGIO | C56: 2026 | D56: =MATCH(B56,{"GENNAIO","FEBBRAIO","MARZO","APRILE","MAGGIO","GIUGNO","LUGLIO","AGOSTO","SETTEMBRE","OTTOBRE","NOVEMBRE","DICEMBRE"},0) -> 5 | E56: =CONCATENATE(,B56," ",C56) -> MAGGIO 2026 | F56: =CONCATENATE(D56," ",E56) -> 5 MAGGIO 2026 | G56: TRASFERIMENTO DENARO | H56: MOVIMENTI CONTO | I56: 155.06 | L56: Spesa badante papa'
A57: BRICOCENTER | B57: APRILE | C57: 2026 | D57: =MATCH(B57,{"GENNAIO","FEBBRAIO","MARZO","APRILE","MAGGIO","GIUGNO","LUGLIO","AGOSTO","SETTEMBRE","OTTOBRE","NOVEMBRE","DICEMBRE"},0) -> 4 | E57: =CONCATENATE(,B57," ",C57) -> APRILE 2026 | F57: =CONCATENATE(D57," ",E57) -> 4 APRILE 2026 | G57: SPESE PER LA CASA | H57: =VLOOKUP(G57,CATEGORIE!$H$3:$I$55,2,FALSE) -> COSTO CASA | I57: 13.2
A58: SPESA LIDL | B58: APRILE | C58: 2026 | D58: =MATCH(B58,{"GENNAIO","FEBBRAIO","MARZO","APRILE","MAGGIO","GIUGNO","LUGLIO","AGOSTO","SETTEMBRE","OTTOBRE","NOVEMBRE","DICEMBRE"},0) -> 4 | E58: =CONCATENATE(,B58," ",C58) -> APRILE 2026 | F58: =CONCATENATE(D58," ",E58) -> 4 APRILE 2026 | G58: ALIMENTARI | H58: =VLOOKUP(G58,CATEGORIE!$H$3:$I$55,2,FALSE) -> COSTO SOPRAVVIVENZA | I58: 9.37
A59: PARROCCHIA SAN UDINE | B59: APRILE | C59: 2026 | D59: =MATCH(B59,{"GENNAIO","FEBBRAIO","MARZO","APRILE","MAGGIO","GIUGNO","LUGLIO","AGOSTO","SETTEMBRE","OTTOBRE","NOVEMBRE","DICEMBRE"},0) -> 4 | E59: =CONCATENATE(,B59," ",C59) -> APRILE 2026 | F59: =CONCATENATE(D59," ",E59) -> 4 APRILE 2026 | G59: BAR E RISTORANTI | H59: =VLOOKUP(G59,CATEGORIE!$H$3:$I$55,2,FALSE) -> COSTO SVAGHI | I59: 26
A60: SPESA VISOTTO | B60: APRILE | C60: 2026 | D60: =MATCH(B60,{"GENNAIO","FEBBRAIO","MARZO","APRILE","MAGGIO","GIUGNO","LUGLIO","AGOSTO","SETTEMBRE","OTTOBRE","NOVEMBRE","DICEMBRE"},0) -> 4 | E60: =CONCATENATE(,B60," ",C60) -> APRILE 2026 | F60: =CONCATENATE(D60," ",E60) -> 4 APRILE 2026 | G60: ALIMENTARI | H60: =VLOOKUP(G60,CATEGORIE!$H$3:$I$55,2,FALSE) -> COSTO SOPRAVVIVENZA | I60: 28.57
A61: COMBIPEL | B61: APRILE | C61: 2026 | D61: =MATCH(B61,{"GENNAIO","FEBBRAIO","MARZO","APRILE","MAGGIO","GIUGNO","LUGLIO","AGOSTO","SETTEMBRE","OTTOBRE","NOVEMBRE","DICEMBRE"},0) -> 4 | E61: =CONCATENATE(,B61," ",C61) -> APRILE 2026 | F61: =CONCATENATE(D61," ",E61) -> 4 APRILE 2026 | G61: VESTITI | H61: =VLOOKUP(G61,CATEGORIE!$H$3:$I$55,2,FALSE) -> COSTO SFIZI | I61: 99.72
A62: HALFPRICE UDINE | B62: APRILE | C62: 2026 | D62: =MATCH(B62,{"GENNAIO","FEBBRAIO","MARZO","APRILE","MAGGIO","GIUGNO","LUGLIO","AGOSTO","SETTEMBRE","OTTOBRE","NOVEMBRE","DICEMBRE"},0) -> 4 | E62: =CONCATENATE(,B62," ",C62) -> APRILE 2026 | F62: =CONCATENATE(D62," ",E62) -> 4 APRILE 2026 | G62: VESTITI | H62: =VLOOKUP(G62,CATEGORIE!$H$3:$I$55,2,FALSE) -> COSTO SFIZI | I62: 44.27
A63: IKEA VILLESSE | B63: APRILE | C63: 2026 | D63: =MATCH(B63,{"GENNAIO","FEBBRAIO","MARZO","APRILE","MAGGIO","GIUGNO","LUGLIO","AGOSTO","SETTEMBRE","OTTOBRE","NOVEMBRE","DICEMBRE"},0) -> 4 | E63: =CONCATENATE(,B63," ",C63) -> APRILE 2026 | F63: =CONCATENATE(D63," ",E63) -> 4 APRILE 2026 | G63: SPESE PER LA CASA | H63: =VLOOKUP(G63,CATEGORIE!$H$3:$I$55,2,FALSE) -> COSTO CASA | I63: 79.1
A64: AGENZIA SERENA GROUP | B64: APRILE | C64: 2026 | D64: =MATCH(B64,{"GENNAIO","FEBBRAIO","MARZO","APRILE","MAGGIO","GIUGNO","LUGLIO","AGOSTO","SETTEMBRE","OTTOBRE","NOVEMBRE","DICEMBRE"},0) -> 4 | E64: =CONCATENATE(,B64," ",C64) -> APRILE 2026 | F64: =CONCATENATE(D64," ",E64) -> 4 APRILE 2026 | G64: TRASFERIMENTO DENARO | H64: MOVIMENTI CONTO | I64: 427.5 | L64: Spesa badante papa'
A65: PROSCIUTTIFICIO ALBERTI | B65: APRILE | C65: 2026 | D65: =MATCH(B65,{"GENNAIO","FEBBRAIO","MARZO","APRILE","MAGGIO","GIUGNO","LUGLIO","AGOSTO","SETTEMBRE","OTTOBRE","NOVEMBRE","DICEMBRE"},0) -> 4 | E65: =CONCATENATE(,B65," ",C65) -> APRILE 2026 | F65: =CONCATENATE(D65," ",E65) -> 4 APRILE 2026 | G65: BAR E RISTORANTI | H65: =VLOOKUP(G65,CATEGORIE!$H$3:$I$55,2,FALSE) -> COSTO SVAGHI | I65: 10
A66: PIZZERIA CHICHIBIO | B66: APRILE | C66: 2026 | D66: =MATCH(B66,{"GENNAIO","FEBBRAIO","MARZO","APRILE","MAGGIO","GIUGNO","LUGLIO","AGOSTO","SETTEMBRE","OTTOBRE","NOVEMBRE","DICEMBRE"},0) -> 4 | E66: =CONCATENATE(,B66," ",C66) -> APRILE 2026 | F66: =CONCATENATE(D66," ",E66) -> 4 APRILE 2026 | G66: BAR E RISTORANTI | H66: =VLOOKUP(G66,CATEGORIE!$H$3:$I$55,2,FALSE) -> COSTO SVAGHI | I66: 36.7
A67: BAR LE FUCINE | B67: APRILE | C67: 2026 | D67: =MATCH(B67,{"GENNAIO","FEBBRAIO","MARZO","APRILE","MAGGIO","GIUGNO","LUGLIO","AGOSTO","SETTEMBRE","OTTOBRE","NOVEMBRE","DICEMBRE"},0) -> 4 | E67: =CONCATENATE(,B67," ",C67) -> APRILE 2026 | F67: =CONCATENATE(D67," ",E67) -> 4 APRILE 2026 | G67: BAR E RISTORANTI | H67: =VLOOKUP(G67,CATEGORIE!$H$3:$I$55,2,FALSE) -> COSTO SVAGHI | I67: 65
A68: CDA LOUNGE BAR | B68: APRILE | C68: 2026 | D68: =MATCH(B68,{"GENNAIO","FEBBRAIO","MARZO","APRILE","MAGGIO","GIUGNO","LUGLIO","AGOSTO","SETTEMBRE","OTTOBRE","NOVEMBRE","DICEMBRE"},0) -> 4 | E68: =CONCATENATE(,B68," ",C68) -> APRILE 2026 | F68: =CONCATENATE(D68," ",E68) -> 4 APRILE 2026 | G68: BAR E RISTORANTI | H68: =VLOOKUP(G68,CATEGORIE!$H$3:$I$55,2,FALSE) -> COSTO SVAGHI | I68: 28.5
A69: CDA LOUNGE BAR | B69: APRILE | C69: 2026 | D69: =MATCH(B69,{"GENNAIO","FEBBRAIO","MARZO","APRILE","MAGGIO","GIUGNO","LUGLIO","AGOSTO","SETTEMBRE","OTTOBRE","NOVEMBRE","DICEMBRE"},0) -> 4 | E69: =CONCATENATE(,B69," ",C69) -> APRILE 2026 | F69: =CONCATENATE(D69," ",E69) -> 4 APRILE 2026 | G69: BAR E RISTORANTI | H69: =VLOOKUP(G69,CATEGORIE!$H$3:$I$55,2,FALSE) -> COSTO SVAGHI | I69: 437.5 | L69: Buffet addio Refrion
A70: COMMISSIONE BONIFICO | B70: APRILE | C70: 2026 | D70: =MATCH(B70,{"GENNAIO","FEBBRAIO","MARZO","APRILE","MAGGIO","GIUGNO","LUGLIO","AGOSTO","SETTEMBRE","OTTOBRE","NOVEMBRE","DICEMBRE"},0) -> 4 | E70: =CONCATENATE(,B70," ",C70) -> APRILE 2026 | F70: =CONCATENATE(D70," ",E70) -> 4 APRILE 2026 | G70: TASSE | H70: =VLOOKUP(G70,CATEGORIE!$H$3:$I$55,2,FALSE) -> TASSE | I70: 0.9 | L70: Assilt Papa'
A71: ASSILT | B71: APRILE | C71: 2026 | D71: =MATCH(B71,{"GENNAIO","FEBBRAIO","MARZO","APRILE","MAGGIO","GIUGNO","LUGLIO","AGOSTO","SETTEMBRE","OTTOBRE","NOVEMBRE","DICEMBRE"},0) -> 4 | E71: =CONCATENATE(,B71," ",C71) -> APRILE 2026 | F71: =CONCATENATE(D71," ",E71) -> 4 APRILE 2026 | G71: REGALI | H71: =VLOOKUP(G71,CATEGORIE!$H$3:$I$55,2,FALSE) -> COSTO SFIZI | I71: 128.45 | L71: Assilt Papa'
A72: TARI | B72: MARZO | C72: 2026 | D72: =MATCH(B72,{"GENNAIO","FEBBRAIO","MARZO","APRILE","MAGGIO","GIUGNO","LUGLIO","AGOSTO","SETTEMBRE","OTTOBRE","NOVEMBRE","DICEMBRE"},0) -> 3 | E72: =CONCATENATE(,B72," ",C72) -> MARZO 2026 | F72: =CONCATENATE(D72," ",E72) -> 3 MARZO 2026 | G72: TASSE | H72: =VLOOKUP(G72,CATEGORIE!$H$3:$I$55,2,FALSE) -> TASSE | I72: 72.6 | L72: Tari 2026
A73: DA EDY REMANZACCO | B73: GENNAIO | C73: 2026 | D73: =MATCH(B73,{"GENNAIO","FEBBRAIO","MARZO","APRILE","MAGGIO","GIUGNO","LUGLIO","AGOSTO","SETTEMBRE","OTTOBRE","NOVEMBRE","DICEMBRE"},0) -> 1 | E73: =CONCATENATE(,B73," ",C73) -> GENNAIO 2026 | F73: =CONCATENATE(D73," ",E73) -> 1 GENNAIO 2026 | G73: BAR E RISTORANTI | H73: =VLOOKUP(G73,CATEGORIE!$H$3:$I$55,2,FALSE) -> COSTO SVAGHI | I73: 225.2
A74: COMMISSIONE BONIFICO | B74: GENNAIO | C74: 2026 | D74: =MATCH(B74,{"GENNAIO","FEBBRAIO","MARZO","APRILE","MAGGIO","GIUGNO","LUGLIO","AGOSTO","SETTEMBRE","OTTOBRE","NOVEMBRE","DICEMBRE"},0) -> 1 | E74: =CONCATENATE(,B74," ",C74) -> GENNAIO 2026 | F74: =CONCATENATE(D74," ",E74) -> 1 GENNAIO 2026 | G74: TASSE | H74: =VLOOKUP(G74,CATEGORIE!$H$3:$I$55,2,FALSE) -> TASSE | I74: 0.5
A75: CAFC | B75: GENNAIO | C75: 2026 | D75: =MATCH(B75,{"GENNAIO","FEBBRAIO","MARZO","APRILE","MAGGIO","GIUGNO","LUGLIO","AGOSTO","SETTEMBRE","OTTOBRE","NOVEMBRE","DICEMBRE"},0) -> 1 | E75: =CONCATENATE(,B75," ",C75) -> GENNAIO 2026 | F75: =CONCATENATE(D75," ",E75) -> 1 GENNAIO 2026 | G75: TASSE | H75: =VLOOKUP(G75,CATEGORIE!$H$3:$I$55,2,FALSE) -> TASSE | I75: 31.91
A76: PAGAMENTO RITENUTE ALLA FONTE | B76: GENNAIO | C76: 2026 | D76: =MATCH(B76,{"GENNAIO","FEBBRAIO","MARZO","APRILE","MAGGIO","GIUGNO","LUGLIO","AGOSTO","SETTEMBRE","OTTOBRE","NOVEMBRE","DICEMBRE"},0) -> 1 | E76: =CONCATENATE(,B76," ",C76) -> GENNAIO 2026 | F76: =CONCATENATE(D76," ",E76) -> 1 GENNAIO 2026 | G76: TASSE | H76: =VLOOKUP(G76,CATEGORIE!$H$3:$I$55,2,FALSE) -> TASSE | I76: 0.03
A77: IMPOSTA DI BOLLO | B77: GENNAIO | C77: 2026 | D77: =MATCH(B77,{"GENNAIO","FEBBRAIO","MARZO","APRILE","MAGGIO","GIUGNO","LUGLIO","AGOSTO","SETTEMBRE","OTTOBRE","NOVEMBRE","DICEMBRE"},0) -> 1 | E77: =CONCATENATE(,B77," ",C77) -> GENNAIO 2026 | F77: =CONCATENATE(D77," ",E77) -> 1 GENNAIO 2026 | G77: TASSE | H77: =VLOOKUP(G77,CATEGORIE!$H$3:$I$55,2,FALSE) -> TASSE | I77: 34.2
A78: UFFICINA | B78: DICEMBRE | C78: 2025 | D78: =MATCH(B78,{"GENNAIO","FEBBRAIO","MARZO","APRILE","MAGGIO","GIUGNO","LUGLIO","AGOSTO","SETTEMBRE","OTTOBRE","NOVEMBRE","DICEMBRE"},0) -> 12 | E78: =CONCATENATE(,B78," ",C78) -> DICEMBRE 2025 | F78: =CONCATENATE(D78," ",E78) -> 12 DICEMBRE 2025 | G78: BAR E RISTORANTI | H78: =VLOOKUP(G78,CATEGORIE!$H$3:$I$55,2,FALSE) -> COSTO SVAGHI | I78: 12
A79: UFFICINA | B79: DICEMBRE | C79: 2025 | D79: =MATCH(B79,{"GENNAIO","FEBBRAIO","MARZO","APRILE","MAGGIO","GIUGNO","LUGLIO","AGOSTO","SETTEMBRE","OTTOBRE","NOVEMBRE","DICEMBRE"},0) -> 12 | E79: =CONCATENATE(,B79," ",C79) -> DICEMBRE 2025 | F79: =CONCATENATE(D79," ",E79) -> 12 DICEMBRE 2025 | G79: BAR E RISTORANTI | H79: =VLOOKUP(G79,CATEGORIE!$H$3:$I$55,2,FALSE) -> COSTO SVAGHI | I79: 20
A80: BOTTEGA VERDE | B80: DICEMBRE | C80: 2025 | D80: =MATCH(B80,{"GENNAIO","FEBBRAIO","MARZO","APRILE","MAGGIO","GIUGNO","LUGLIO","AGOSTO","SETTEMBRE","OTTOBRE","NOVEMBRE","DICEMBRE"},0) -> 12 | E80: =CONCATENATE(,B80," ",C80) -> DICEMBRE 2025 | F80: =CONCATENATE(D80," ",E80) -> 12 DICEMBRE 2025 | G80: REGALI | H80: =VLOOKUP(G80,CATEGORIE!$H$3:$I$55,2,FALSE) -> COSTO SFIZI | I80: 25.98 | L80: Regali Natale 2025
A81: BABY & BOYS | B81: DICEMBRE | C81: 2025 | D81: =MATCH(B81,{"GENNAIO","FEBBRAIO","MARZO","APRILE","MAGGIO","GIUGNO","LUGLIO","AGOSTO","SETTEMBRE","OTTOBRE","NOVEMBRE","DICEMBRE"},0) -> 12 | E81: =CONCATENATE(,B81," ",C81) -> DICEMBRE 2025 | F81: =CONCATENATE(D81," ",E81) -> 12 DICEMBRE 2025 | G81: REGALI | H81: =VLOOKUP(G81,CATEGORIE!$H$3:$I$55,2,FALSE) -> COSTO SFIZI | I81: 42.5 | L81: Regali Natale 2025
A82: PROSCIUTTIFICIO ALBERTI | B82: DICEMBRE | C82: 2025 | D82: =MATCH(B82,{"GENNAIO","FEBBRAIO","MARZO","APRILE","MAGGIO","GIUGNO","LUGLIO","AGOSTO","SETTEMBRE","OTTOBRE","NOVEMBRE","DICEMBRE"},0) -> 12 | E82: =CONCATENATE(,B82," ",C82) -> DICEMBRE 2025 | F82: =CONCATENATE(D82," ",E82) -> 12 DICEMBRE 2025 | G82: BAR E RISTORANTI | H82: =VLOOKUP(G82,CATEGORIE!$H$3:$I$55,2,FALSE) -> COSTO SVAGHI | I82: 80 | L82: Regali Natale 2025
A83: MEDICENTER RONCHI | B83: DICEMBRE | C83: 2025 | D83: =MATCH(B83,{"GENNAIO","FEBBRAIO","MARZO","APRILE","MAGGIO","GIUGNO","LUGLIO","AGOSTO","SETTEMBRE","OTTOBRE","NOVEMBRE","DICEMBRE"},0) -> 12 | E83: =CONCATENATE(,B83," ",C83) -> DICEMBRE 2025 | F83: =CONCATENATE(D83," ",E83) -> 12 DICEMBRE 2025 | G83: VISITE MEDICHE | H83: =VLOOKUP(G83,CATEGORIE!$H$3:$I$55,2,FALSE) -> COSTO SOPRAVVIVENZA | I83: 33
A84: SPESA VISOTTO | B84: DICEMBRE | C84: 2025 | D84: =MATCH(B84,{"GENNAIO","FEBBRAIO","MARZO","APRILE","MAGGIO","GIUGNO","LUGLIO","AGOSTO","SETTEMBRE","OTTOBRE","NOVEMBRE","DICEMBRE"},0) -> 12 | E84: =CONCATENATE(,B84," ",C84) -> DICEMBRE 2025 | F84: =CONCATENATE(D84," ",E84) -> 12 DICEMBRE 2025 | G84: ALIMENTARI | H84: =VLOOKUP(G84,CATEGORIE!$H$3:$I$55,2,FALSE) -> COSTO SOPRAVVIVENZA | I84: 10.99
A85: SPESA DIDON | B85: DICEMBRE | C85: 2025 | D85: =MATCH(B85,{"GENNAIO","FEBBRAIO","MARZO","APRILE","MAGGIO","GIUGNO","LUGLIO","AGOSTO","SETTEMBRE","OTTOBRE","NOVEMBRE","DICEMBRE"},0) -> 12 | E85: =CONCATENATE(,B85," ",C85) -> DICEMBRE 2025 | F85: =CONCATENATE(D85," ",E85) -> 12 DICEMBRE 2025 | G85: SPESE PER LA CASA | H85: =VLOOKUP(G85,CATEGORIE!$H$3:$I$55,2,FALSE) -> COSTO CASA | I85: 25.89
A86: SPESA LIDL | B86: DICEMBRE | C86: 2025 | D86: =MATCH(B86,{"GENNAIO","FEBBRAIO","MARZO","APRILE","MAGGIO","GIUGNO","LUGLIO","AGOSTO","SETTEMBRE","OTTOBRE","NOVEMBRE","DICEMBRE"},0) -> 12 | E86: =CONCATENATE(,B86," ",C86) -> DICEMBRE 2025 | F86: =CONCATENATE(D86," ",E86) -> 12 DICEMBRE 2025 | G86: ALIMENTARI | H86: =VLOOKUP(G86,CATEGORIE!$H$3:$I$55,2,FALSE) -> COSTO SOPRAVVIVENZA | I86: 17.35
A87: IKEA VILLESSE | B87: DICEMBRE | C87: 2025 | D87: =MATCH(B87,{"GENNAIO","FEBBRAIO","MARZO","APRILE","MAGGIO","GIUGNO","LUGLIO","AGOSTO","SETTEMBRE","OTTOBRE","NOVEMBRE","DICEMBRE"},0) -> 12 | E87: =CONCATENATE(,B87," ",C87) -> DICEMBRE 2025 | F87: =CONCATENATE(D87," ",E87) -> 12 DICEMBRE 2025 | G87: SPESE PER LA CASA | H87: =VLOOKUP(G87,CATEGORIE!$H$3:$I$55,2,FALSE) -> COSTO CASA | I87: 43.75
A88: GIUNTI AL PUNTO | B88: DICEMBRE | C88: 2025 | D88: =MATCH(B88,{"GENNAIO","FEBBRAIO","MARZO","APRILE","MAGGIO","GIUGNO","LUGLIO","AGOSTO","SETTEMBRE","OTTOBRE","NOVEMBRE","DICEMBRE"},0) -> 12 | E88: =CONCATENATE(,B88," ",C88) -> DICEMBRE 2025 | F88: =CONCATENATE(D88," ",E88) -> 12 DICEMBRE 2025 | G88: REGALI | H88: =VLOOKUP(G88,CATEGORIE!$H$3:$I$55,2,FALSE) -> COSTO SFIZI | I88: 4.95 | L88: Regali Natale 2025
A89: MEDIAWORLD | B89: DICEMBRE | C89: 2025 | D89: =MATCH(B89,{"GENNAIO","FEBBRAIO","MARZO","APRILE","MAGGIO","GIUGNO","LUGLIO","AGOSTO","SETTEMBRE","OTTOBRE","NOVEMBRE","DICEMBRE"},0) -> 12 | E89: =CONCATENATE(,B89," ",C89) -> DICEMBRE 2025 | F89: =CONCATENATE(D89," ",E89) -> 12 DICEMBRE 2025 | G89: REGALI | H89: =VLOOKUP(G89,CATEGORIE!$H$3:$I$55,2,FALSE) -> COSTO SFIZI | I89: 34.99 | L89: Regali Natale 2025
